Workbook
Name ADC_att: Parameters!$C$40
Name ADC_exh: Parameters!$C$41
Name ADC_rol: Parameters!$C$42
Name Cred_full: Parameters!$C$25:$E$25
Name Cred_mature: Parameters!$C$26:$E$26
Name Disc_rate: Parameters!$C$18
Name Exp_ratio: Parameters!$C$11:$E$11
Name Ext_shock: Parameters!$C$34
Name Ext_tail: Parameters!$C$32:$E$32
Name Ext_taillag: Parameters!$C$33
Name Loss_trend: Parameters!$C$17
Name Plan_LR: Parameters!$C$24:$E$24
Name Val_rate_max: Parameters!$C$50
Name Val_rate_min: Parameters!$C$49
Name Val_ratio_max: Parameters!$C$48

Sheet Cover
B2: Northgate Mutual Insurance Society
B3: Commercial Motor - Unpaid Claim Liability and Reinsurance Model
B4: Reserving date: 31 December 2025 | All monetary amounts in GBP thousands (£000)
B6: Purpose | C6: Estimate the unpaid claim liability for the Commercial Motor account under three
C7: alternative reserving bases, test the result against a management-directed adverse
C8: scenario, and evaluate an Adverse Development Cover offered by the reinsurer.
B10: Contents
B11: Raw Data | C11: Source data as received, prior to any adjustment (Tables 1-3)
B12: Data Validation | C12: Defect detection, correction rules and validated triangles
B13: Parameters | C13: All model parameters and assumptions (Tables 4-10)
B14: Dev Factors | C14: Age-to-age factors, selections and cumulative development factors
B15: S1 Chain Ladder | C15: Base scenario 1 - Chain Ladder ultimates and reserves
B16: On-Level & Cred | C16: On-levelling, loss trend and credibility-weighted a priori loss ratios
B17: S2 Expected Claims | C17: Base scenario 2 - Expected Claims ultimates and reserves
B18: S3 BF | C18: Base scenario 3 - Bornhuetter-Ferguson ultimates and reserves
B19: Extension | C19: Extension scenario - tail factor and claims inflation shock, all three bases
B20: ADC | C20: Adverse Development Cover - layer analysis and break-even shock rate
B21: Summary | C21: Comparative results and charts
B22: Checks | C22: Consolidated check dashboard
B23: Audit Trail | C23: Full methodology, assumptions and check documentation
B25: Cell convention
B26: Blue text | C26: Hardcoded input or scenario lever - edit here
B27: Black text | C27: Formula calculated on this sheet
B28: Green text | C28: Link to another sheet in this workbook
B29: Yellow fill | C29: Key assumption set by management or judgement
B30: Green fill | C30: Check - must read OK
B31: Red fill | C31: Data defect identified by the validation rules
B33: Note | C33: The model contains no volatile functions, no macros and no external links.

Sheet Raw Data
B1: Raw Data - as received, before validation
B2: Source: Northgate Mutual claims administration system extract of 14 January 2026 (paid amounts) and finance system (premium and rate history). Received as a flat file and pasted unaltered.
B3: This sheet is deliberately left unadjusted. All corrections are made on the "Data Validation" sheet so that the audit path from source to model input is visible.
B5: Table 1: Raw cumulative paid claims by rating group (£000)
B6: Rows are accident years; columns are development age in months from the start of the accident year.
B8: Group A - Light commercial vehicles
B9: Accident year | C9: 12 months | D9: 24 months | E9: 36 months | F9: 48 months | G9: 60 months | H9: 72 months
B10: 2020 | C10: 960.7 | D10: 1755.3 | E10: 2087.5 | F10: 2271 | G10: 2344.6 | H10: 2432.5
B11: 2021 | C11: 951.5 | D11: 1752.7 | E11: 2106 | F11: 2326.4 | G11: 2437.7
B12: 2022 | C12: 1459.8 | D12: 2147.4 | E12: 2643.7 | F12: 2612
B13: 2023 | C13: 1306.2 | D13: n/a | E13: 2705.1
B14: 2024 | C14: 1423.4 | D14: 2305.4
B15: 2025 | C15: 1525.9
B18: Group B - Heavy goods vehicles
B19: Accident year | C19: 12 months | D19: 24 months | E19: 36 months | F19: 48 months | G19: 60 months | H19: 72 months
B20: 2020 | C20: 630.7 | D20: 1200.1 | E20: 1455.9 | F20: 1629.2 | G20: 1815 | H20: 1851.3
B21: 2021 | C21: 681.6 | D21: 1386.2 | F21: 2000.7 | G21: 2106.4
B22: 2022 | C22: 778.7 | D22: 1456.6 | E22: 1941.2 | F22: 2119.6
B23: 2023 | C23: 757.7 | D23: 1549 | E23: 1982.1
B24: 2024 | C24: 960.5 | D24: 1694.4
B25: 2025 | C25: 907
B28: Group C - Specialist haulage
B29: Accident year | C29: 12 months | D29: 24 months | E29: 36 months | F29: 48 months | G29: 60 months | H29: 72 months
B30: 2020 | C30: 321.3 | D30: 6865 | E30: 959.7 | F30: 1162.1 | G30: 1241.6 | H30: 1300.2
B31: 2021 | C31: 388 | D31: 799.2 | E31: 1092 | F31: 1318.5 | G31: 1409.9
B32: 2022 | C32: 457.3 | D32: 1002.9 | E32: 1336.5 | F32: 1598
B33: 2023 | C33: 450.7 | D33: 947.8 | E33: 1260.1
B34: 2024 | C34: 491.9 | D34: 991.2
B35: 2025 | C35: 469
B38: Table 2: Raw reported claim counts by rating group
B39: Counts of reported claims, used only to set credibility weights. Source: claims administration system.
B40: Accident year | C40: Group A | D40: Group B | E40: Group C
B41: 2020 | C41: 300 | D41: 145 | E41: 60
B42: 2021 | C42: 315 | D42: 150 | E42: 64
B43: 2022 | C43: 325 | D43: 155 | E43: 68
B44: 2023 | C44: 340 | D44: 160 | E44: 72
B45: 2024 | C45: 360 | D45: 175 | E45: 80
B46: 2025 | C46: 380 | D46: 190 | E46: 86
B49: Table 3: Raw history of rate changes by rating group
B50: Average rate change achieved on renewal, effective 1 January of the accident year shown. Source: underwriting rate monitoring return.
B51: Accident year | C51: Group A | D51: Group B | E51: Group C
B52: 2020 | C52: 0.02 | D52: 0.03 | E52: 0.015
B53: 2021 | C53: -0.015 | D53: -0.025 | E53: -0.03
B54: 2022 | C54: 0.01 | D54: 0.005 | E54: 0.02
B55: 2023 | C55: 0.055 | D55: 0.065 | E55: 0.07
B56: 2024 | C56: 0.075 | D56: 0.09 | E56: 1
B57: 2025 | C57: 0.035 | D57: 0.045 | E57: 0.05
B60: Table 4: Raw earned premium by rating group (£000)
B61: Premium earned in the accident year, net of acquisition costs deducted at source. Source: finance system.
B62: Accident year | C62: Group A | D62: Group B | E62: Group C
B63: 2020 | C63: 4200 | D63: 3100 | E63: 1800
B64: 2021 | C64: 4450 | D64: 3250 | E64: 1900
B65: 2022 | C65: 4600 | D65: 3300 | E65: 2000
B66: 2023 | C66: 4900 | D66: 3500 | E66: 2150
B67: 2024 | C67: 5350 | D67: 3850 | E67: 2400
B68: 2025 | C68: 5700 | D68: 4150 | E68: 2650

Sheet Data Validation
B1: Data Validation - detection and correction of defects in the source data
B2: Satisfies Part 1 requirement 3 (data validation and sensitivity checks on the input data).
B4: Validation rules applied to the raw paid triangles
B5: R1 | C5: Every in-triangle cell must contain a number. Blank cells and text entries are flagged as missing. The link from a source cell preserves a genuine blank as blank, rather than letting it read through as zero, so that a missing entry is caught here and not mistaken for a real, reported zero later in rule R3.
B6: R2 | C6: Cumulative paid claims cannot fall as development age increases, because the account carries no salvage or subrogation recoveries (see Parameters, Table 10). A cell at or below its predecessor is flagged.
B7: R3 | C7: A link ratio above the outlier bound Val_ratio_max is implausible for this class and is flagged as a probable keying error. A zero or negative predecessor is flagged directly without attempting the division, since the ratio is undefined in that case.
B8: R4 | C8: Where the predecessor cell is itself flagged, no ratio test is applied to the current cell, so that a single defect is not double-counted. The defect does however cascade: the successor of a corrupted cell is tested against the corrupted value and may be flagged in turn.
B9: R5 | C9: Rate changes outside the range Val_rate_min to Val_rate_max are flagged and corrected manually against the underwriting rate monitoring return.
B11: Correction rule
C12: A flagged cell is replaced by the preceding validated cell multiplied by the volume-weighted average link ratio for that development step, computed from clean cells only. This preserves the observed development shape of the group without importing the defect.
C13: Cells at development age 12 months have no predecessor and cannot be corrected this way; check C4 confirms that no such cell is flagged.
B15: Group A - Light commercial vehicles
C16: Raw as received (£000) | J16: Defect flags (1 = flagged) | Q16: Clean numeric values (£000) | X16: Validated cumulative paid (£000)
B17: Accident year | C17: 12 | D17: 24 | E17: 36 | F17: 48 | G17: 60 | H17: 72 | J17: 12 | K17: 24 | L17: 36 | M17: 48 | N17: 60 | O17: 72 | Q17: 12 | R17: 24 | S17: 36 | T17: 48 | U17: 60 | V17: 72 | X17: 12 | Y17: 24 | Z17: 36 | AA17: 48 | AB17: 60 | AC17: 72
B18: 2020 | C18: =IF('Raw Data'!C10="","",'Raw Data'!C10) -> 960.7 | D18: =IF('Raw Data'!D10="","",'Raw Data'!D10) -> 1755.3 | E18: =IF('Raw Data'!E10="","",'Raw Data'!E10) -> 2087.5 | F18: =IF('Raw Data'!F10="","",'Raw Data'!F10) -> 2271 | G18: =IF('Raw Data'!G10="","",'Raw Data'!G10) -> 2344.6 | H18: =IF('Raw Data'!H10="","",'Raw Data'!H10) -> 2432.5 | J18: =IF(ISNUMBER(C18),0,1) -> 0 | K18: =IF(NOT(ISNUMBER(D18)),1,IF(NOT(ISNUMBER(C18)),0,IF(OR(D18<=C18,IF(C18<=0,TRUE(),D18/C18>Val_ratio_max)),1,0))) -> 0 | L18: =IF(NOT(ISNUMBER(E18)),1,IF(NOT(ISNUMBER(D18)),0,IF(OR(E18<=D18,IF(D18<=0,TRUE(),E18/D18>Val_ratio_max)),1,0))) -> 0 | M18: =IF(NOT(ISNUMBER(F18)),1,IF(NOT(ISNUMBER(E18)),0,IF(OR(F18<=E18,IF(E18<=0,TRUE(),F18/E18>Val_ratio_max)),1,0))) -> 0 | N18: =IF(NOT(ISNUMBER(G18)),1,IF(NOT(ISNUMBER(F18)),0,IF(OR(G18<=F18,IF(F18<=0,TRUE(),G18/F18>Val_ratio_max)),1,0))) -> 0 | O18: =IF(NOT(ISNUMBER(H18)),1,IF(NOT(ISNUMBER(G18)),0,IF(OR(H18<=G18,IF(G18<=0,TRUE(),H18/G18>Val_ratio_max)),1,0))) -> 0 | Q18: =IF(J18=1,0,IF(ISNUMBER(C18),C18,0)) -> 960.7 | R18: =IF(K18=1,0,IF(ISNUMBER(D18),D18,0)) -> 1755.3 | S18: =IF(L18=1,0,IF(ISNUMBER(E18),E18,0)) -> 2087.5 | T18: =IF(M18=1,0,IF(ISNUMBER(F18),F18,0)) -> 2271 | U18: =IF(N18=1,0,IF(ISNUMBER(G18),G18,0)) -> 2344.6 | V18: =IF(O18=1,0,IF(ISNUMBER(H18),H18,0)) -> 2432.5 | X18: =IF(J18=0,C18,"CHECK C4") -> 960.7 | Y18: =IF(K18=0,D18,X18*R$25) -> 1755.3 | Z18: =IF(L18=0,E18,Y18*S$25) -> 2087.5 | AA18: =IF(M18=0,F18,Z18*T$25) -> 2271 | AB18: =IF(N18=0,G18,AA18*U$25) -> 2344.6 | AC18: =IF(O18=0,H18,AB18*V$25) -> 2432.5
B19: 2021 | C19: =IF('Raw Data'!C11="","",'Raw Data'!C11) -> 951.5 | D19: =IF('Raw Data'!D11="","",'Raw Data'!D11) -> 1752.7 | E19: =IF('Raw Data'!E11="","",'Raw Data'!E11) -> 2106 | F19: =IF('Raw Data'!F11="","",'Raw Data'!F11) -> 2326.4 | G19: =IF('Raw Data'!G11="","",'Raw Data'!G11) -> 2437.7 | J19: =IF(ISNUMBER(C19),0,1) -> 0 | K19: =IF(NOT(ISNUMBER(D19)),1,IF(NOT(ISNUMBER(C19)),0,IF(OR(D19<=C19,IF(C19<=0,TRUE(),D19/C19>Val_ratio_max)),1,0))) -> 0 | L19: =IF(NOT(ISNUMBER(E19)),1,IF(NOT(ISNUMBER(D19)),0,IF(OR(E19<=D19,IF(D19<=0,TRUE(),E19/D19>Val_ratio_max)),1,0))) -> 0 | M19: =IF(NOT(ISNUMBER(F19)),1,IF(NOT(ISNUMBER(E19)),0,IF(OR(F19<=E19,IF(E19<=0,TRUE(),F19/E19>Val_ratio_max)),1,0))) -> 0 | N19: =IF(NOT(ISNUMBER(G19)),1,IF(NOT(ISNUMBER(F19)),0,IF(OR(G19<=F19,IF(F19<=0,TRUE(),G19/F19>Val_ratio_max)),1,0))) -> 0 | O19: 0 | Q19: =IF(J19=1,0,IF(ISNUMBER(C19),C19,0)) -> 951.5 | R19: =IF(K19=1,0,IF(ISNUMBER(D19),D19,0)) -> 1752.7 | S19: =IF(L19=1,0,IF(ISNUMBER(E19),E19,0)) -> 2106 | T19: =IF(M19=1,0,IF(ISNUMBER(F19),F19,0)) -> 2326.4 | U19: =IF(N19=1,0,IF(ISNUMBER(G19),G19,0)) -> 2437.7 | V19: 0 | X19: =IF(J19=0,C19,"CHECK C4") -> 951.5 | Y19: =IF(K19=0,D19,X19*R$25) -> 1752.7 | Z19: =IF(L19=0,E19,Y19*S$25) -> 2106 | AA19: =IF(M19=0,F19,Z19*T$25) -> 2326.4 | AB19: =IF(N19=0,G19,AA19*U$25) -> 2437.7
B20: 2022 | C20: =IF('Raw Data'!C12="","",'Raw Data'!C12) -> 1459.8 | D20: =IF('Raw Data'!D12="","",'Raw Data'!D12) -> 2147.4 | E20: =IF('Raw Data'!E12="","",'Raw Data'!E12) -> 2643.7 | F20: =IF('Raw Data'!F12="","",'Raw Data'!F12) -> 2612 | J20: =IF(ISNUMBER(C20),0,1) -> 0 | K20: =IF(NOT(ISNUMBER(D20)),1,IF(NOT(ISNUMBER(C20)),0,IF(OR(D20<=C20,IF(C20<=0,TRUE(),D20/C20>Val_ratio_max)),1,0))) -> 0 | L20: =IF(NOT(ISNUMBER(E20)),1,IF(NOT(ISNUMBER(D20)),0,IF(OR(E20<=D20,IF(D20<=0,TRUE(),E20/D20>Val_ratio_max)),1,0))) -> 0 | M20: =IF(NOT(ISNUMBER(F20)),1,IF(NOT(ISNUMBER(E20)),0,IF(OR(F20<=E20,IF(E20<=0,TRUE(),F20/E20>Val_ratio_max)),1,0))) -> 1 | N20: 0 | O20: 0 | Q20: =IF(J20=1,0,IF(ISNUMBER(C20),C20,0)) -> 1459.8 | R20: =IF(K20=1,0,IF(ISNUMBER(D20),D20,0)) -> 2147.4 | S20: =IF(L20=1,0,IF(ISNUMBER(E20),E20,0)) -> 2643.7 | T20: =IF(M20=1,0,IF(ISNUMBER(F20),F20,0)) -> 0 | U20: 0 | V20: 0 | X20: =IF(J20=0,C20,"CHECK C4") -> 1459.8 | Y20: =IF(K20=0,D20,X20*R$25) -> 2147.4 | Z20: =IF(L20=0,E20,Y20*S$25) -> 2643.7 | AA20: =IF(M20=0,F20,Z20*T$25) -> 2898.3299
B21: 2023 | C21: =IF('Raw Data'!C13="","",'Raw Data'!C13) -> 1306.2 | D21: =IF('Raw Data'!D13="","",'Raw Data'!D13) -> n/a | E21: =IF('Raw Data'!E13="","",'Raw Data'!E13) -> 2705.1 | J21: =IF(ISNUMBER(C21),0,1) -> 0 | K21: =IF(NOT(ISNUMBER(D21)),1,IF(NOT(ISNUMBER(C21)),0,IF(OR(D21<=C21,IF(C21<=0,TRUE(),D21/C21>Val_ratio_max)),1,0))) -> 1 | L21: =IF(NOT(ISNUMBER(E21)),1,IF(NOT(ISNUMBER(D21)),0,IF(OR(E21<=D21,IF(D21<=0,TRUE(),E21/D21>Val_ratio_max)),1,0))) -> 0 | M21: 0 | N21: 0 | O21: 0 | Q21: =IF(J21=1,0,IF(ISNUMBER(C21),C21,0)) -> 1306.2 | R21: =IF(K21=1,0,IF(ISNUMBER(D21),D21,0)) -> 0 | S21: =IF(L21=1,0,IF(ISNUMBER(E21),E21,0)) -> 2705.1 | T21: 0 | U21: 0 | V21: 0 | X21: =IF(J21=0,C21,"CHECK C4") -> 1306.2 | Y21: =IF(K21=0,D21,X21*R$25) -> 2168.4108 | Z21: =IF(L21=0,E21,Y21*S$25) -> 2705.1
B22: 2024 | C22: =IF('Raw Data'!C14="","",'Raw Data'!C14) -> 1423.4 | D22: =IF('Raw Data'!D14="","",'Raw Data'!D14) -> 2305.4 | J22: =IF(ISNUMBER(C22),0,1) -> 0 | K22: =IF(NOT(ISNUMBER(D22)),1,IF(NOT(ISNUMBER(C22)),0,IF(OR(D22<=C22,IF(C22<=0,TRUE(),D22/C22>Val_ratio_max)),1,0))) -> 0 | L22: 0 | M22: 0 | N22: 0 | O22: 0 | Q22: =IF(J22=1,0,IF(ISNUMBER(C22),C22,0)) -> 1423.4 | R22: =IF(K22=1,0,IF(ISNUMBER(D22),D22,0)) -> 2305.4 | S22: 0 | T22: 0 | U22: 0 | V22: 0 | X22: =IF(J22=0,C22,"CHECK C4") -> 1423.4 | Y22: =IF(K22=0,D22,X22*R$25) -> 2305.4
B23: 2025 | C23: =IF('Raw Data'!C15="","",'Raw Data'!C15) -> 1525.9 | J23: =IF(ISNUMBER(C23),0,1) -> 0 | K23: 0 | L23: 0 | M23: 0 | N23: 0 | O23: 0 | Q23: =IF(J23=1,0,IF(ISNUMBER(C23),C23,0)) -> 1525.9 | R23: 0 | S23: 0 | T23: 0 | U23: 0 | V23: 0 | X23: =IF(J23=0,C23,"CHECK C4") -> 1525.9
Q24: Volume-weighted average link ratio, computed from clean cells only (a cell pair is used only where both cells are unflagged, numeric and inside the triangle) | R24: 12-24 | S24: 24-36 | T24: 36-48 | U24: 48-60 | V24: 60-72
B25: Clean link ratio | J25: Cells flagged | M25: =SUM(J18:O23) -> 2 | R25: =SUMPRODUCT((R18:R23>0)*(Q18:Q23>0)*R18:R23)/SUMPRODUCT((R18:R23>0)*(Q18:Q23>0)*Q18:Q23) -> 1.6600909 | S25: =SUMPRODUCT((S18:S23>0)*(R18:R23>0)*S18:S23)/SUMPRODUCT((S18:S23>0)*(R18:R23>0)*R18:R23) -> 1.2089684 | T25: =SUMPRODUCT((T18:T23>0)*(S18:S23>0)*T18:T23)/SUMPRODUCT((T18:T23>0)*(S18:S23>0)*S18:S23) -> 1.0963157 | U25: =SUMPRODUCT((U18:U23>0)*(T18:T23>0)*U18:U23)/SUMPRODUCT((U18:U23>0)*(T18:T23>0)*T18:T23) -> 1.0402184 | V25: =SUMPRODUCT((V18:V23>0)*(U18:U23>0)*V18:V23)/SUMPRODUCT((V18:V23>0)*(U18:U23>0)*U18:U23) -> 1.0374904
B31: Group B - Heavy goods vehicles
C32: Raw as received (£000) | J32: Defect flags (1 = flagged) | Q32: Clean numeric values (£000) | X32: Validated cumulative paid (£000)
B33: Accident year | C33: 12 | D33: 24 | E33: 36 | F33: 48 | G33: 60 | H33: 72 | J33: 12 | K33: 24 | L33: 36 | M33: 48 | N33: 60 | O33: 72 | Q33: 12 | R33: 24 | S33: 36 | T33: 48 | U33: 60 | V33: 72 | X33: 12 | Y33: 24 | Z33: 36 | AA33: 48 | AB33: 60 | AC33: 72
B34: 2020 | C34: =IF('Raw Data'!C20="","",'Raw Data'!C20) -> 630.7 | D34: =IF('Raw Data'!D20="","",'Raw Data'!D20) -> 1200.1 | E34: =IF('Raw Data'!E20="","",'Raw Data'!E20) -> 1455.9 | F34: =IF('Raw Data'!F20="","",'Raw Data'!F20) -> 1629.2 | G34: =IF('Raw Data'!G20="","",'Raw Data'!G20) -> 1815 | H34: =IF('Raw Data'!H20="","",'Raw Data'!H20) -> 1851.3 | J34: =IF(ISNUMBER(C34),0,1) -> 0 | K34: =IF(NOT(ISNUMBER(D34)),1,IF(NOT(ISNUMBER(C34)),0,IF(OR(D34<=C34,IF(C34<=0,TRUE(),D34/C34>Val_ratio_max)),1,0))) -> 0 | L34: =IF(NOT(ISNUMBER(E34)),1,IF(NOT(ISNUMBER(D34)),0,IF(OR(E34<=D34,IF(D34<=0,TRUE(),E34/D34>Val_ratio_max)),1,0))) -> 0 | M34: =IF(NOT(ISNUMBER(F34)),1,IF(NOT(ISNUMBER(E34)),0,IF(OR(F34<=E34,IF(E34<=0,TRUE(),F34/E34>Val_ratio_max)),1,0))) -> 0 | N34: =IF(NOT(ISNUMBER(G34)),1,IF(NOT(ISNUMBER(F34)),0,IF(OR(G34<=F34,IF(F34<=0,TRUE(),G34/F34>Val_ratio_max)),1,0))) -> 0 | O34: =IF(NOT(ISNUMBER(H34)),1,IF(NOT(ISNUMBER(G34)),0,IF(OR(H34<=G34,IF(G34<=0,TRUE(),H34/G34>Val_ratio_max)),1,0))) -> 0 | Q34: =IF(J34=1,0,IF(ISNUMBER(C34),C34,0)) -> 630.7 | R34: =IF(K34=1,0,IF(ISNUMBER(D34),D34,0)) -> 1200.1 | S34: =IF(L34=1,0,IF(ISNUMBER(E34),E34,0)) -> 1455.9 | T34: =IF(M34=1,0,IF(ISNUMBER(F34),F34,0)) -> 1629.2 | U34: =IF(N34=1,0,IF(ISNUMBER(G34),G34,0)) -> 1815 | V34: =IF(O34=1,0,IF(ISNUMBER(H34),H34,0)) -> 1851.3 | X34: =IF(J34=0,C34,"CHECK C4") -> 630.7 | Y34: =IF(K34=0,D34,X34*R$41) -> 1200.1 | Z34: =IF(L34=0,E34,Y34*S$41) -> 1455.9 | AA34: =IF(M34=0,F34,Z34*T$41) -> 1629.2 | AB34: =IF(N34=0,G34,AA34*U$41) -> 1815 | AC34: =IF(O34=0,H34,AB34*V$41) -> 1851.3
B35: 2021 | C35: =IF('Raw Data'!C21="","",'Raw Data'!C21) -> 681.6 | D35: =IF('Raw Data'!D21="","",'Raw Data'!D21) -> 1386.2 | E35: =IF('Raw Data'!E21="","",'Raw Data'!E21) | F35: =IF('Raw Data'!F21="","",'Raw Data'!F21) -> 2000.7 | G35: =IF('Raw Data'!G21="","",'Raw Data'!G21) -> 2106.4 | J35: =IF(ISNUMBER(C35),0,1) -> 0 | K35: =IF(NOT(ISNUMBER(D35)),1,IF(NOT(ISNUMBER(C35)),0,IF(OR(D35<=C35,IF(C35<=0,TRUE(),D35/C35>Val_ratio_max)),1,0))) -> 0 | L35: =IF(NOT(ISNUMBER(E35)),1,IF(NOT(ISNUMBER(D35)),0,IF(OR(E35<=D35,IF(D35<=0,TRUE(),E35/D35>Val_ratio_max)),1,0))) -> 1 | M35: =IF(NOT(ISNUMBER(F35)),1,IF(NOT(ISNUMBER(E35)),0,IF(OR(F35<=E35,IF(E35<=0,TRUE(),F35/E35>Val_ratio_max)),1,0))) -> 0 | N35: =IF(NOT(ISNUMBER(G35)),1,IF(NOT(ISNUMBER(F35)),0,IF(OR(G35<=F35,IF(F35<=0,TRUE(),G35/F35>Val_ratio_max)),1,0))) -> 0 | O35: 0 | Q35: =IF(J35=1,0,IF(ISNUMBER(C35),C35,0)) -> 681.6 | R35: =IF(K35=1,0,IF(ISNUMBER(D35),D35,0)) -> 1386.2 | S35: =IF(L35=1,0,IF(ISNUMBER(E35),E35,0)) -> 0 | T35: =IF(M35=1,0,IF(ISNUMBER(F35),F35,0)) -> 2000.7 | U35: =IF(N35=1,0,IF(ISNUMBER(G35),G35,0)) -> 2106.4 | V35: 0 | X35: =IF(J35=0,C35,"CHECK C4") -> 681.6 | Y35: =IF(K35=0,D35,X35*R$41) -> 1386.2 | Z35: =IF(L35=0,E35,Y35*S$41) -> 1772.986 | AA35: =IF(M35=0,F35,Z35*T$41) -> 2000.7 | AB35: =IF(N35=0,G35,AA35*U$41) -> 2106.4
B36: 2022 | C36: =IF('Raw Data'!C22="","",'Raw Data'!C22) -> 778.7 | D36: =IF('Raw Data'!D22="","",'Raw Data'!D22) -> 1456.6 | E36: =IF('Raw Data'!E22="","",'Raw Data'!E22) -> 1941.2 | F36: =IF('Raw Data'!F22="","",'Raw Data'!F22) -> 2119.6 | J36: =IF(ISNUMBER(C36),0,1) -> 0 | K36: =IF(NOT(ISNUMBER(D36)),1,IF(NOT(ISNUMBER(C36)),0,IF(OR(D36<=C36,IF(C36<=0,TRUE(),D36/C36>Val_ratio_max)),1,0))) -> 0 | L36: =IF(NOT(ISNUMBER(E36)),1,IF(NOT(ISNUMBER(D36)),0,IF(OR(E36<=D36,IF(D36<=0,TRUE(),E36/D36>Val_ratio_max)),1,0))) -> 0 | M36: =IF(NOT(ISNUMBER(F36)),1,IF(NOT(ISNUMBER(E36)),0,IF(OR(F36<=E36,IF(E36<=0,TRUE(),F36/E36>Val_ratio_max)),1,0))) -> 0 | N36: 0 | O36: 0 | Q36: =IF(J36=1,0,IF(ISNUMBER(C36),C36,0)) -> 778.7 | R36: =IF(K36=1,0,IF(ISNUMBER(D36),D36,0)) -> 1456.6 | S36: =IF(L36=1,0,IF(ISNUMBER(E36),E36,0)) -> 1941.2 | T36: =IF(M36=1,0,IF(ISNUMBER(F36),F36,0)) -> 2119.6 | U36: 0 | V36: 0 | X36: =IF(J36=0,C36,"CHECK C4") -> 778.7 | Y36: =IF(K36=0,D36,X36*R$41) -> 1456.6 | Z36: =IF(L36=0,E36,Y36*S$41) -> 1941.2 | AA36: =IF(M36=0,F36,Z36*T$41) -> 2119.6
B37: 2023 | C37: =IF('Raw Data'!C23="","",'Raw Data'!C23) -> 757.7 | D37: =IF('Raw Data'!D23="","",'Raw Data'!D23) -> 1549 | E37: =IF('Raw Data'!E23="","",'Raw Data'!E23) -> 1982.1 | J37: =IF(ISNUMBER(C37),0,1) -> 0 | K37: =IF(NOT(ISNUMBER(D37)),1,IF(NOT(ISNUMBER(C37)),0,IF(OR(D37<=C37,IF(C37<=0,TRUE(),D37/C37>Val_ratio_max)),1,0))) -> 0 | L37: =IF(NOT(ISNUMBER(E37)),1,IF(NOT(ISNUMBER(D37)),0,IF(OR(E37<=D37,IF(D37<=0,TRUE(),E37/D37>Val_ratio_max)),1,0))) -> 0 | M37: 0 | N37: 0 | O37: 0 | Q37: =IF(J37=1,0,IF(ISNUMBER(C37),C37,0)) -> 757.7 | R37: =IF(K37=1,0,IF(ISNUMBER(D37),D37,0)) -> 1549 | S37: =IF(L37=1,0,IF(ISNUMBER(E37),E37,0)) -> 1982.1 | T37: 0 | U37: 0 | V37: 0 | X37: =IF(J37=0,C37,"CHECK C4") -> 757.7 | Y37: =IF(K37=0,D37,X37*R$41) -> 1549 | Z37: =IF(L37=0,E37,Y37*S$41) -> 1982.1
B38: 2024 | C38: =IF('Raw Data'!C24="","",'Raw Data'!C24) -> 960.5 | D38: =IF('Raw Data'!D24="","",'Raw Data'!D24) -> 1694.4 | J38: =IF(ISNUMBER(C38),0,1) -> 0 | K38: =IF(NOT(ISNUMBER(D38)),1,IF(NOT(ISNUMBER(C38)),0,IF(OR(D38<=C38,IF(C38<=0,TRUE(),D38/C38>Val_ratio_max)),1,0))) -> 0 | L38: 0 | M38: 0 | N38: 0 | O38: 0 | Q38: =IF(J38=1,0,IF(ISNUMBER(C38),C38,0)) -> 960.5 | R38: =IF(K38=1,0,IF(ISNUMBER(D38),D38,0)) -> 1694.4 | S38: 0 | T38: 0 | U38: 0 | V38: 0 | X38: =IF(J38=0,C38,"CHECK C4") -> 960.5 | Y38: =IF(K38=0,D38,X38*R$41) -> 1694.4
B39: 2025 | C39: =IF('Raw Data'!C25="","",'Raw Data'!C25) -> 907 | J39: =IF(ISNUMBER(C39),0,1) -> 0 | K39: 0 | L39: 0 | M39: 0 | N39: 0 | O39: 0 | Q39: =IF(J39=1,0,IF(ISNUMBER(C39),C39,0)) -> 907 | R39: 0 | S39: 0 | T39: 0 | U39: 0 | V39: 0 | X39: =IF(J39=0,C39,"CHECK C4") -> 907
Q40: Volume-weighted average link ratio, computed from clean cells only (a cell pair is used only where both cells are unflagged, numeric and inside the triangle) | R40: 12-24 | S40: 24-36 | T40: 36-48 | U40: 48-60 | V40: 60-72
B41: Clean link ratio | J41: Cells flagged | M41: =SUM(J34:O39) -> 1 | R41: =SUMPRODUCT((R34:R39>0)*(Q34:Q39>0)*R34:R39)/SUMPRODUCT((R34:R39>0)*(Q34:Q39>0)*Q34:Q39) -> 1.9128163 | S41: =SUMPRODUCT((S34:S39>0)*(R34:R39>0)*S34:S39)/SUMPRODUCT((S34:S39>0)*(R34:R39>0)*R34:R39) -> 1.2790261 | T41: =SUMPRODUCT((T34:T39>0)*(S34:S39>0)*T34:T39)/SUMPRODUCT((T34:T39>0)*(S34:S39>0)*S34:S39) -> 1.1035295 | U41: =SUMPRODUCT((U34:U39>0)*(T34:T39>0)*U34:U39)/SUMPRODUCT((U34:U39>0)*(T34:T39>0)*T34:T39) -> 1.0803052 | V41: =SUMPRODUCT((V34:V39>0)*(U34:U39>0)*V34:V39)/SUMPRODUCT((V34:V39>0)*(U34:U39>0)*U34:U39) -> 1.02
B47: Group C - Specialist haulage
C48: Raw as received (£000) | J48: Defect flags (1 = flagged) | Q48: Clean numeric values (£000) | X48: Validated cumulative paid (£000)
B49: Accident year | C49: 12 | D49: 24 | E49: 36 | F49: 48 | G49: 60 | H49: 72 | J49: 12 | K49: 24 | L49: 36 | M49: 48 | N49: 60 | O49: 72 | Q49: 12 | R49: 24 | S49: 36 | T49: 48 | U49: 60 | V49: 72 | X49: 12 | Y49: 24 | Z49: 36 | AA49: 48 | AB49: 60 | AC49: 72
B50: 2020 | C50: =IF('Raw Data'!C30="","",'Raw Data'!C30) -> 321.3 | D50: =IF('Raw Data'!D30="","",'Raw Data'!D30) -> 6865 | E50: =IF('Raw Data'!E30="","",'Raw Data'!E30) -> 959.7 | F50: =IF('Raw Data'!F30="","",'Raw Data'!F30) -> 1162.1 | G50: =IF('Raw Data'!G30="","",'Raw Data'!G30) -> 1241.6 | H50: =IF('Raw Data'!H30="","",'Raw Data'!H30) -> 1300.2 | J50: =IF(ISNUMBER(C50),0,1) -> 0 | K50: =IF(NOT(ISNUMBER(D50)),1,IF(NOT(ISNUMBER(C50)),0,IF(OR(D50<=C50,IF(C50<=0,TRUE(),D50/C50>Val_ratio_max)),1,0))) -> 1 | L50: =IF(NOT(ISNUMBER(E50)),1,IF(NOT(ISNUMBER(D50)),0,IF(OR(E50<=D50,IF(D50<=0,TRUE(),E50/D50>Val_ratio_max)),1,0))) -> 1 | M50: =IF(NOT(ISNUMBER(F50)),1,IF(NOT(ISNUMBER(E50)),0,IF(OR(F50<=E50,IF(E50<=0,TRUE(),F50/E50>Val_ratio_max)),1,0))) -> 0 | N50: =IF(NOT(ISNUMBER(G50)),1,IF(NOT(ISNUMBER(F50)),0,IF(OR(G50<=F50,IF(F50<=0,TRUE(),G50/F50>Val_ratio_max)),1,0))) -> 0 | O50: =IF(NOT(ISNUMBER(H50)),1,IF(NOT(ISNUMBER(G50)),0,IF(OR(H50<=G50,IF(G50<=0,TRUE(),H50/G50>Val_ratio_max)),1,0))) -> 0 | Q50: =IF(J50=1,0,IF(ISNUMBER(C50),C50,0)) -> 321.3 | R50: =IF(K50=1,0,IF(ISNUMBER(D50),D50,0)) -> 0 | S50: =IF(L50=1,0,IF(ISNUMBER(E50),E50,0)) -> 0 | T50: =IF(M50=1,0,IF(ISNUMBER(F50),F50,0)) -> 1162.1 | U50: =IF(N50=1,0,IF(ISNUMBER(G50),G50,0)) -> 1241.6 | V50: =IF(O50=1,0,IF(ISNUMBER(H50),H50,0)) -> 1300.2 | X50: =IF(J50=0,C50,"CHECK C4") -> 321.3 | Y50: =IF(K50=0,D50,X50*R$57) -> 672.30574 | Z50: =IF(L50=0,E50,Y50*S$57) -> 901.80259 | AA50: =IF(M50=0,F50,Z50*T$57) -> 1162.1 | AB50: =IF(N50=0,G50,AA50*U$57) -> 1241.6 | AC50: =IF(O50=0,H50,AB50*V$57) -> 1300.2
B51: 2021 | C51: =IF('Raw Data'!C31="","",'Raw Data'!C31) -> 388 | D51: =IF('Raw Data'!D31="","",'Raw Data'!D31) -> 799.2 | E51: =IF('Raw Data'!E31="","",'Raw Data'!E31) -> 1092 | F51: =IF('Raw Data'!F31="","",'Raw Data'!F31) -> 1318.5 | G51: =IF('Raw Data'!G31="","",'Raw Data'!G31) -> 1409.9 | J51: =IF(ISNUMBER(C51),0,1) -> 0 | K51: =IF(NOT(ISNUMBER(D51)),1,IF(NOT(ISNUMBER(C51)),0,IF(OR(D51<=C51,IF(C51<=0,TRUE(),D51/C51>Val_ratio_max)),1,0))) -> 0 | L51: =IF(NOT(ISNUMBER(E51)),1,IF(NOT(ISNUMBER(D51)),0,IF(OR(E51<=D51,IF(D51<=0,TRUE(),E51/D51>Val_ratio_max)),1,0))) -> 0 | M51: =IF(NOT(ISNUMBER(F51)),1,IF(NOT(ISNUMBER(E51)),0,IF(OR(F51<=E51,IF(E51<=0,TRUE(),F51/E51>Val_ratio_max)),1,0))) -> 0 | N51: =IF(NOT(ISNUMBER(G51)),1,IF(NOT(ISNUMBER(F51)),0,IF(OR(G51<=F51,IF(F51<=0,TRUE(),G51/F51>Val_ratio_max)),1,0))) -> 0 | O51: 0 | Q51: =IF(J51=1,0,IF(ISNUMBER(C51),C51,0)) -> 388 | R51: =IF(K51=1,0,IF(ISNUMBER(D51),D51,0)) -> 799.2 | S51: =IF(L51=1,0,IF(ISNUMBER(E51),E51,0)) -> 1092 | T51: =IF(M51=1,0,IF(ISNUMBER(F51),F51,0)) -> 1318.5 | U51: =IF(N51=1,0,IF(ISNUMBER(G51),G51,0)) -> 1409.9 | V51: 0 | X51: =IF(J51=0,C51,"CHECK C4") -> 388 | Y51: =IF(K51=0,D51,X51*R$57) -> 799.2 | Z51: =IF(L51=0,E51,Y51*S$57) -> 1092 | AA51: =IF(M51=0,F51,Z51*T$57) -> 1318.5 | AB51: =IF(N51=0,G51,AA51*U$57) -> 1409.9
B52: 2022 | C52: =IF('Raw Data'!C32="","",'Raw Data'!C32) -> 457.3 | D52: =IF('Raw Data'!D32="","",'Raw Data'!D32) -> 1002.9 | E52: =IF('Raw Data'!E32="","",'Raw Data'!E32) -> 1336.5 | F52: =IF('Raw Data'!F32="","",'Raw Data'!F32) -> 1598 | J52: =IF(ISNUMBER(C52),0,1) -> 0 | K52: =IF(NOT(ISNUMBER(D52)),1,IF(NOT(ISNUMBER(C52)),0,IF(OR(D52<=C52,IF(C52<=0,TRUE(),D52/C52>Val_ratio_max)),1,0))) -> 0 | L52: =IF(NOT(ISNUMBER(E52)),1,IF(NOT(ISNUMBER(D52)),0,IF(OR(E52<=D52,IF(D52<=0,TRUE(),E52/D52>Val_ratio_max)),1,0))) -> 0 | M52: =IF(NOT(ISNUMBER(F52)),1,IF(NOT(ISNUMBER(E52)),0,IF(OR(F52<=E52,IF(E52<=0,TRUE(),F52/E52>Val_ratio_max)),1,0))) -> 0 | N52: 0 | O52: 0 | Q52: =IF(J52=1,0,IF(ISNUMBER(C52),C52,0)) -> 457.3 | R52: =IF(K52=1,0,IF(ISNUMBER(D52),D52,0)) -> 1002.9 | S52: =IF(L52=1,0,IF(ISNUMBER(E52),E52,0)) -> 1336.5 | T52: =IF(M52=1,0,IF(ISNUMBER(F52),F52,0)) -> 1598 | U52: 0 | V52: 0 | X52: =IF(J52=0,C52,"CHECK C4") -> 457.3 | Y52: =IF(K52=0,D52,X52*R$57) -> 1002.9 | Z52: =IF(L52=0,E52,Y52*S$57) -> 1336.5 | AA52: =IF(M52=0,F52,Z52*T$57) -> 1598
B53: 2023 | C53: =IF('Raw Data'!C33="","",'Raw Data'!C33) -> 450.7 | D53: =IF('Raw Data'!D33="","",'Raw Data'!D33) -> 947.8 | E53: =IF('Raw Data'!E33="","",'Raw Data'!E33) -> 1260.1 | J53: =IF(ISNUMBER(C53),0,1) -> 0 | K53: =IF(NOT(ISNUMBER(D53)),1,IF(NOT(ISNUMBER(C53)),0,IF(OR(D53<=C53,IF(C53<=0,TRUE(),D53/C53>Val_ratio_max)),1,0))) -> 0 | L53: =IF(NOT(ISNUMBER(E53)),1,IF(NOT(ISNUMBER(D53)),0,IF(OR(E53<=D53,IF(D53<=0,TRUE(),E53/D53>Val_ratio_max)),1,0))) -> 0 | M53: 0 | N53: 0 | O53: 0 | Q53: =IF(J53=1,0,IF(ISNUMBER(C53),C53,0)) -> 450.7 | R53: =IF(K53=1,0,IF(ISNUMBER(D53),D53,0)) -> 947.8 | S53: =IF(L53=1,0,IF(ISNUMBER(E53),E53,0)) -> 1260.1 | T53: 0 | U53: 0 | V53: 0 | X53: =IF(J53=0,C53,"CHECK C4") -> 450.7 | Y53: =IF(K53=0,D53,X53*R$57) -> 947.8 | Z53: =IF(L53=0,E53,Y53*S$57) -> 1260.1
B54: 2024 | C54: =IF('Raw Data'!C34="","",'Raw Data'!C34) -> 491.9 | D54: =IF('Raw Data'!D34="","",'Raw Data'!D34) -> 991.2 | J54: =IF(ISNUMBER(C54),0,1) -> 0 | K54: =IF(NOT(ISNUMBER(D54)),1,IF(NOT(ISNUMBER(C54)),0,IF(OR(D54<=C54,IF(C54<=0,TRUE(),D54/C54>Val_ratio_max)),1,0))) -> 0 | L54: 0 | M54: 0 | N54: 0 | O54: 0 | Q54: =IF(J54=1,0,IF(ISNUMBER(C54),C54,0)) -> 491.9 | R54: =IF(K54=1,0,IF(ISNUMBER(D54),D54,0)) -> 991.2 | S54: 0 | T54: 0 | U54: 0 | V54: 0 | X54: =IF(J54=0,C54,"CHECK C4") -> 491.9 | Y54: =IF(K54=0,D54,X54*R$57) -> 991.2
B55: 2025 | C55: =IF('Raw Data'!C35="","",'Raw Data'!C35) -> 469 | J55: =IF(ISNUMBER(C55),0,1) -> 0 | K55: 0 | L55: 0 | M55: 0 | N55: 0 | O55: 0 | Q55: =IF(J55=1,0,IF(ISNUMBER(C55),C55,0)) -> 469 | R55: 0 | S55: 0 | T55: 0 | U55: 0 | V55: 0 | X55: =IF(J55=0,C55,"CHECK C4") -> 469
Q56: Volume-weighted average link ratio, computed from clean cells only (a cell pair is used only where both cells are unflagged, numeric and inside the triangle) | R56: 12-24 | S56: 24-36 | T56: 36-48 | U56: 48-60 | V56: 60-72
B57: Clean link ratio | J57: Cells flagged | M57: =SUM(J50:O55) -> 2 | R57: =SUMPRODUCT((R50:R55>0)*(Q50:Q55>0)*R50:R55)/SUMPRODUCT((R50:R55>0)*(Q50:Q55>0)*Q50:Q55) -> 2.0924548 | S57: =SUMPRODUCT((S50:S55>0)*(R50:R55>0)*S50:S55)/SUMPRODUCT((S50:S55>0)*(R50:R55>0)*R50:R55) -> 1.3413579 | T57: =SUMPRODUCT((T50:T55>0)*(S50:S55>0)*T50:T55)/SUMPRODUCT((T50:T55>0)*(S50:S55>0)*S50:S55) -> 1.2009471 | U57: =SUMPRODUCT((U50:U55>0)*(T50:T55>0)*U50:U55)/SUMPRODUCT((U50:U55>0)*(T50:T55>0)*T50:T55) -> 1.0688946 | V57: =SUMPRODUCT((V50:V55>0)*(U50:U55>0)*V50:V55)/SUMPRODUCT((V50:V55>0)*(U50:U55>0)*U50:U55) -> 1.0471972
B64: Validation of the rate change history (Rule R5)
B65: A rate change outside the plausible range is almost certainly a decimal misplacement. The corrected value below is taken from the underwriting rate monitoring return and entered manually rather than derived, so that the correction is visible and attributable.
B66: Accident year | C66: Raw A | D66: Raw B | E66: Raw C | G66: Flag A | H66: Flag B | I66: Flag C | K66: Valid. A | L66: Valid. B | M66: Valid. C
B67: 2020 | C67: ='Raw Data'!C52 -> 0.02 | D67: ='Raw Data'!D52 -> 0.03 | E67: ='Raw Data'!E52 -> 0.015 | G67: =IF(OR(C67<Val_rate_min,C67>Val_rate_max),1,0) -> 0 | H67: =IF(OR(D67<Val_rate_min,D67>Val_rate_max),1,0) -> 0 | I67: =IF(OR(E67<Val_rate_min,E67>Val_rate_max),1,0) -> 0 | K67: =IF(G67=0,C67,$D$75) -> 0.02 | L67: =IF(H67=0,D67,$D$75) -> 0.03 | M67: =IF(I67=0,E67,$D$75) -> 0.015
B68: 2021 | C68: ='Raw Data'!C53 -> -0.015 | D68: ='Raw Data'!D53 -> -0.025 | E68: ='Raw Data'!E53 -> -0.03 | G68: =IF(OR(C68<Val_rate_min,C68>Val_rate_max),1,0) -> 0 | H68: =IF(OR(D68<Val_rate_min,D68>Val_rate_max),1,0) -> 0 | I68: =IF(OR(E68<Val_rate_min,E68>Val_rate_max),1,0) -> 0 | K68: =IF(G68=0,C68,$D$75) -> -0.015 | L68: =IF(H68=0,D68,$D$75) -> -0.025 | M68: =IF(I68=0,E68,$D$75) -> -0.03
B69: 2022 | C69: ='Raw Data'!C54 -> 0.01 | D69: ='Raw Data'!D54 -> 0.005 | E69: ='Raw Data'!E54 -> 0.02 | G69: =IF(OR(C69<Val_rate_min,C69>Val_rate_max),1,0) -> 0 | H69: =IF(OR(D69<Val_rate_min,D69>Val_rate_max),1,0) -> 0 | I69: =IF(OR(E69<Val_rate_min,E69>Val_rate_max),1,0) -> 0 | K69: =IF(G69=0,C69,$D$75) -> 0.01 | L69: =IF(H69=0,D69,$D$75) -> 0.005 | M69: =IF(I69=0,E69,$D$75) -> 0.02
B70: 2023 | C70: ='Raw Data'!C55 -> 0.055 | D70: ='Raw Data'!D55 -> 0.065 | E70: ='Raw Data'!E55 -> 0.07 | G70: =IF(OR(C70<Val_rate_min,C70>Val_rate_max),1,0) -> 0 | H70: =IF(OR(D70<Val_rate_min,D70>Val_rate_max),1,0) -> 0 | I70: =IF(OR(E70<Val_rate_min,E70>Val_rate_max),1,0) -> 0 | K70: =IF(G70=0,C70,$D$75) -> 0.055 | L70: =IF(H70=0,D70,$D$75) -> 0.065 | M70: =IF(I70=0,E70,$D$75) -> 0.07
B71: 2024 | C71: ='Raw Data'!C56 -> 0.075 | D71: ='Raw Data'!D56 -> 0.09 | E71: ='Raw Data'!E56 -> 1 | G71: =IF(OR(C71<Val_rate_min,C71>Val_rate_max),1,0) -> 0 | H71: =IF(OR(D71<Val_rate_min,D71>Val_rate_max),1,0) -> 0 | I71: =IF(OR(E71<Val_rate_min,E71>Val_rate_max),1,0) -> 1 | K71: =IF(G71=0,C71,$D$75) -> 0.075 | L71: =IF(H71=0,D71,$D$75) -> 0.09 | M71: =IF(I71=0,E71,$D$75) -> 0.1
B72: 2025 | C72: ='Raw Data'!C57 -> 0.035 | D72: ='Raw Data'!D57 -> 0.045 | E72: ='Raw Data'!E57 -> 0.05 | G72: =IF(OR(C72<Val_rate_min,C72>Val_rate_max),1,0) -> 0 | H72: =IF(OR(D72<Val_rate_min,D72>Val_rate_max),1,0) -> 0 | I72: =IF(OR(E72<Val_rate_min,E72>Val_rate_max),1,0) -> 0 | K72: =IF(G72=0,C72,$D$75) -> 0.035 | L72: =IF(H72=0,D72,$D$75) -> 0.045 | M72: =IF(I72=0,E72,$D$75) -> 0.05
B74: Manual correction applied
B75: Corrected rate change (Group C, 2024) | D75: 0.1
B76: Reason for the correction | D76: Rate monitoring return records +10.0%; the extract shows +100.0%, a misplaced decimal point.
B78: Sensitivity of the correction
B79: Effect on Group C 2020 on-level factor if left uncorrected | D79: =(1+$D$75)/(1+'Raw Data'!E56)-1 -> -0.45
B80: The uncorrected figure would deflate every Group C on-level premium before 2024 by the factor above, understating the on-level loss ratio and hence the a priori assumption. This implies that the correction is material and is not cosmetic.

Sheet Parameters
B1: Parameters and Assumptions
B2: Satisfies Part 1 requirement 2. Blue cells are inputs; yellow fill marks a judgemental assumption. Column G gives the defined name where one exists; column H gives the source or rationale.
B5: Table 5: Rating group definition and exposure
B6: Descriptive parameters for the three rating groups that make up the Commercial Motor account.
B7: Parameter | C7: Group A | D7: Group B | E7: Group C | G7: Defined name | H7: Source / rationale
B8: Vehicles on cover at 31 December 2025 | C8: 2840 | D8: 1120 | E8: 410 | H8: Policy administration system, in-force listing.
B9: Average sum insured per vehicle (£000) | C9: 28 | D9: 64 | E9: 95 | H9: Policy administration system, weighted by exposure.
B10: Salvage and subrogation recoveries netted in data | C10: No | D10: No | E10: No | H10: Confirmed with claims manager; supports validation rule R2.
B11: Expense ratio (% of earned premium) | C11: 0.27 | D11: 0.255 | E11: 0.29 | G11: Exp_ratio | H11: Management accounts, three-year average. Used for the combined ratio only.
B14: Table 6: Economic and expense assumptions
B15: Applied uniformly across the three rating groups unless stated otherwise.
B16: Parameter | C16: Value | G16: Defined name | H16: Source / rationale
B17: Past claims severity trend (per annum) | C17: 0.055 | G17: Loss_trend | H17: Internal severity study over accident years 2018-2025, corroborated by ABI motor claims inflation indices. Judgemental.
B18: Cost of capital / discount rate (per annum) | C18: 0.05 | G18: Disc_rate | H18: Board-approved cost of capital. Used for the discounted view only.
B21: Table 7: A priori loss ratio and credibility parameters
B22: Used to derive the a priori loss ratio underlying the Expected Claims and Bornhuetter-Ferguson bases.
B23: Parameter | C23: Group A | D23: Group B | E23: Group C | G23: Defined name | H23: Source / rationale
B24: Business plan ultimate loss ratio (2025 rate and cost level) | C24: 0.62 | D24: 0.7 | E24: 0.76 | G24: Plan_LR | H24: 2026 business plan approved by the Board, being the complement of credibility.
B25: Full credibility standard (number of claims) | C25: 1082 | D25: 1082 | E25: 1082 | G25: Cred_full | H25: Limited fluctuation standard for 90% probability of being within 5% of expected claim frequency.
B26: Accident years used for the experience indication | C26: 3 | D26: 3 | E26: 3 | G26: Cred_mature | H26: The three oldest accident years, being the most fully developed. Judgemental.
B29: Table 8: Extension scenario parameters
B30: Instruction of the Chief Actuary dated 12 February 2026. These parameters drive the extension scenario only; setting the shock to zero and the tail factors to 1.000 reproduces the base scenarios exactly.
B31: Parameter | C31: Group A | D31: Group B | E31: Group C | G31: Defined name | H31: Source / rationale
B32: Tail factor beyond 72 months development | C32: 1.012 | D32: 1.034 | E32: 1.055 | G32: Ext_tail | H32: Benchmarked against the ABI market development pattern for commercial motor. Judgemental.
B33: Average lag of tail payments beyond 72 months (years) | C33: 3 | G33: Ext_taillag | H33: Judgemental, reflecting the settlement profile of large bodily injury claims.
B34: Additional claims inflation on unpaid amounts (per annum) | C34: 0.04 | G34: Ext_shock | H34: Chief Actuary instruction, reflecting the Ogden discount rate review and observed care-cost inflation. Judgemental.
B37: Table 9: Adverse Development Cover terms
B38: Indicative terms quoted by the reinsurer on 3 February 2026 for a cover attaching to the booked reserve for the whole account.
B39: Parameter | C39: Value | G39: Defined name | H39: Source / rationale
B40: Attachment point (% of booked reserve) | C40: 1.05 | G40: ADC_att | H40: Reinsurer quotation.
B41: Exhaustion point (% of booked reserve) | C41: 1.3 | G41: ADC_exh | H41: Reinsurer quotation.
B42: Rate on line (% of limit) | C42: 0.12 | G42: ADC_rol | H42: Reinsurer quotation.
B45: Table 10: Validation thresholds and modelling conventions
B46: Thresholds used by the validation rules on the Data Validation sheet, and conventions adopted throughout the model.
B47: Parameter | C47: Value | G47: Defined name | H47: Source / rationale
B48: Maximum plausible link ratio (outlier bound) | C48: 4 | G48: Val_ratio_max | H48: Set well above the largest observed 12-24 month factor of about 2.1, so that only gross keying errors are caught.
B49: Minimum plausible annual rate change | C49: -0.25 | G49: Val_rate_min | H49: Judgemental bound on the underwriting rate monitoring return.
B50: Maximum plausible annual rate change | C50: 0.25 | G50: Val_rate_max | H50: Judgemental bound on the underwriting rate monitoring return.
B51: Development ages modelled (months) | C51: 72 | H51: Six development periods observed; beyond this the tail factor applies.
B52: Timing convention for payments within a period | C52: End of period | H52: Simplifying convention; stated as an assumption in the Audit Trail.

Sheet Dev Factors
B1: Stage 1 - Development factors
B2: Age-to-age factors are calculated from the validated cumulative paid triangles. The selection is the volume-weighted all-year average, which gives greater weight to the larger and more stable accident years. Base scenarios carry no tail; the tail is introduced only in the extension scenario.
B5: Group A - Light commercial vehicles
B6: Individual age-to-age factors
B7: Accident year | C7: 12-24 | D7: 24-36 | E7: 36-48 | F7: 48-60 | G7: 60-72
B8: 2020 | C8: ='Data Validation'!Y18/'Data Validation'!X18 -> 1.8271052 | D8: ='Data Validation'!Z18/'Data Validation'!Y18 -> 1.1892554 | E8: ='Data Validation'!AA18/'Data Validation'!Z18 -> 1.0879042 | F8: ='Data Validation'!AB18/'Data Validation'!AA18 -> 1.0324086 | G8: ='Data Validation'!AC18/'Data Validation'!AB18 -> 1.0374904
B9: 2021 | C9: ='Data Validation'!Y19/'Data Validation'!X19 -> 1.8420389 | D9: ='Data Validation'!Z19/'Data Validation'!Y19 -> 1.2015747 | E9: ='Data Validation'!AA19/'Data Validation'!Z19 -> 1.1046534 | F9: ='Data Validation'!AB19/'Data Validation'!AA19 -> 1.0478422
B10: 2022 | C10: ='Data Validation'!Y20/'Data Validation'!X20 -> 1.4710234 | D10: ='Data Validation'!Z20/'Data Validation'!Y20 -> 1.2311167 | E10: ='Data Validation'!AA20/'Data Validation'!Z20 -> 1.0963157
B11: 2023 | C11: ='Data Validation'!Y21/'Data Validation'!X21 -> 1.6600909 | D11: ='Data Validation'!Z21/'Data Validation'!Y21 -> 1.2475035
B12: 2024 | C12: ='Data Validation'!Y22/'Data Validation'!X22 -> 1.6196431
B13: Development age (months) | C13: 12 | D13: 24 | E13: 36 | F13: 48 | G13: 60 | H13: 72
B14: Selected LDF (volume-weighted, all years) | C14: =SUM('Data Validation'!Y18:Y22)/SUM('Data Validation'!X18:X22) -> 1.6600909 | D14: =SUM('Data Validation'!Z18:Z21)/SUM('Data Validation'!Y18:Y21) -> 1.2196486 | E14: =SUM('Data Validation'!AA18:AA20)/SUM('Data Validation'!Z18:Z20) -> 1.0963157 | F14: =SUM('Data Validation'!AB18:AB19)/SUM('Data Validation'!AA18:AA19) -> 1.0402184 | G14: =SUM('Data Validation'!AC18:AC18)/SUM('Data Validation'!AB18:AB18) -> 1.0374904
B15: CDF to 72 months - base (no tail) | C15: =D15*C14 -> 2.395581 | D15: =E15*D14 -> 1.443042 | E15: =F15*E14 -> 1.1831621 | F15: =G15*F14 -> 1.0792166 | G15: =H15*G14 -> 1.0374904 | H15: 1
B16: % of ultimate paid at each age - base | C16: =1/C15 -> 0.41743527 | D16: =1/D15 -> 0.6929805 | E16: =1/E15 -> 0.84519271 | F16: =1/F15 -> 0.92659806 | G16: =1/G15 -> 0.96386434 | H16: =1/H15 -> 1
B17: Check: selected factors are non-increasing and at least 1.000 | H17: =IF(AND(MIN(C14:G14)>=1,SUMPRODUCT(--(C14:F14<D14:G14))=0),"OK","REVIEW") -> OK
B20: Group B - Heavy goods vehicles
B21: Individual age-to-age factors
B22: Accident year | C22: 12-24 | D22: 24-36 | E22: 36-48 | F22: 48-60 | G22: 60-72
B23: 2020 | C23: ='Data Validation'!Y34/'Data Validation'!X34 -> 1.9028064 | D23: ='Data Validation'!Z34/'Data Validation'!Y34 -> 1.2131489 | E23: ='Data Validation'!AA34/'Data Validation'!Z34 -> 1.1190329 | F23: ='Data Validation'!AB34/'Data Validation'!AA34 -> 1.1140437 | G23: ='Data Validation'!AC34/'Data Validation'!AB34 -> 1.02
B24: 2021 | C24: ='Data Validation'!Y35/'Data Validation'!X35 -> 2.0337441 | D24: ='Data Validation'!Z35/'Data Validation'!Y35 -> 1.2790261 | E24: ='Data Validation'!AA35/'Data Validation'!Z35 -> 1.1284353 | F24: ='Data Validation'!AB35/'Data Validation'!AA35 -> 1.0528315
B25: 2022 | C25: ='Data Validation'!Y36/'Data Validation'!X36 -> 1.8705535 | D25: ='Data Validation'!Z36/'Data Validation'!Y36 -> 1.3326926 | E25: ='Data Validation'!AA36/'Data Validation'!Z36 -> 1.0919019
B26: 2023 | C26: ='Data Validation'!Y37/'Data Validation'!X37 -> 2.0443447 | D26: ='Data Validation'!Z37/'Data Validation'!Y37 -> 1.2795997
B27: 2024 | C27: ='Data Validation'!Y38/'Data Validation'!X38 -> 1.7640812
B28: Development age (months) | C28: 12 | D28: 24 | E28: 36 | F28: 48 | G28: 60 | H28: 72
B29: Selected LDF (volume-weighted, all years) | C29: =SUM('Data Validation'!Y34:Y38)/SUM('Data Validation'!X34:X38) -> 1.9128163 | D29: =SUM('Data Validation'!Z34:Z37)/SUM('Data Validation'!Y34:Y37) -> 1.2790261 | E29: =SUM('Data Validation'!AA34:AA36)/SUM('Data Validation'!Z34:Z36) -> 1.1120705 | F29: =SUM('Data Validation'!AB34:AB35)/SUM('Data Validation'!AA34:AA35) -> 1.0803052 | G29: =SUM('Data Validation'!AC34:AC34)/SUM('Data Validation'!AB34:AB34) -> 1.02
B30: CDF to 72 months - base (no tail) | C30: =D30*C29 -> 2.9980001 | D30: =E30*D29 -> 1.5673225 | E30: =F30*E29 -> 1.2254031 | F30: =G30*F29 -> 1.1019113 | G30: =H30*G29 -> 1.02 | H30: 1
B31: % of ultimate paid at each age - base | C31: =1/C30 -> 0.33355569 | D31: =1/D30 -> 0.63803078 | E31: =1/E30 -> 0.81605801 | F31: =1/F30 -> 0.90751402 | G31: =1/G30 -> 0.98039216 | H31: =1/H30 -> 1
B32: Check: selected factors are non-increasing and at least 1.000 | H32: =IF(AND(MIN(C29:G29)>=1,SUMPRODUCT(--(C29:F29<D29:G29))=0),"OK","REVIEW") -> OK
B35: Group C - Specialist haulage
B36: Individual age-to-age factors
B37: Accident year | C37: 12-24 | D37: 24-36 | E37: 36-48 | F37: 48-60 | G37: 60-72
B38: 2020 | C38: ='Data Validation'!Y50/'Data Validation'!X50 -> 2.0924548 | D38: ='Data Validation'!Z50/'Data Validation'!Y50 -> 1.3413579 | E38: ='Data Validation'!AA50/'Data Validation'!Z50 -> 1.2886412 | F38: ='Data Validation'!AB50/'Data Validation'!AA50 -> 1.0684106 | G38: ='Data Validation'!AC50/'Data Validation'!AB50 -> 1.0471972
B39: 2021 | C39: ='Data Validation'!Y51/'Data Validation'!X51 -> 2.0597938 | D39: ='Data Validation'!Z51/'Data Validation'!Y51 -> 1.3663664 | E39: ='Data Validation'!AA51/'Data Validation'!Z51 -> 1.2074176 | F39: ='Data Validation'!AB51/'Data Validation'!AA51 -> 1.0693212
B40: 2022 | C40: ='Data Validation'!Y52/'Data Validation'!X52 -> 2.1930899 | D40: ='Data Validation'!Z52/'Data Validation'!Y52 -> 1.3326354 | E40: ='Data Validation'!AA52/'Data Validation'!Z52 -> 1.1956603
B41: 2023 | C41: ='Data Validation'!Y53/'Data Validation'!X53 -> 2.102951 | D41: ='Data Validation'!Z53/'Data Validation'!Y53 -> 1.3294999
B42: 2024 | C42: ='Data Validation'!Y54/'Data Validation'!X54 -> 2.0150437
B43: Development age (months) | C43: 12 | D43: 24 | E43: 36 | F43: 48 | G43: 60 | H43: 72
B44: Selected LDF (volume-weighted, all years) | C44: =SUM('Data Validation'!Y50:Y54)/SUM('Data Validation'!X50:X54) -> 2.0924548 | D44: =SUM('Data Validation'!Z50:Z53)/SUM('Data Validation'!Y50:Y53) -> 1.3413579 | E44: =SUM('Data Validation'!AA50:AA52)/SUM('Data Validation'!Z50:Z52) -> 1.2246935 | F44: =SUM('Data Validation'!AB50:AB51)/SUM('Data Validation'!AA50:AA51) -> 1.0688946 | G44: =SUM('Data Validation'!AC50:AC50)/SUM('Data Validation'!AB50:AB50) -> 1.0471972
B45: CDF to 72 months - base (no tail) | C45: =D45*C44 -> 3.8476142 | D45: =E45*D44 -> 1.838804 | E45: =F45*E44 -> 1.3708526 | F45: =G45*F44 -> 1.1193434 | G45: =H45*G44 -> 1.0471972 | H45: 1
B46: % of ultimate paid at each age - base | C46: =1/C45 -> 0.25990132 | D46: =1/D45 -> 0.54383176 | E46: =1/E45 -> 0.72947301 | F46: =1/F45 -> 0.89338087 | G46: =1/G45 -> 0.95493001 | H46: =1/H45 -> 1
B47: Check: selected factors are non-increasing and at least 1.000 | H47: =IF(AND(MIN(C44:G44)>=1,SUMPRODUCT(--(C44:F44<D44:G44))=0),"OK","REVIEW") -> OK

Sheet S1 Chain Ladder
B1: Base Scenario 1 - Chain Ladder
B2: Ultimate claims are the latest cumulative paid amount grossed up by the cumulative development factor for the corresponding development age. The method uses only the experience of the account and makes no use of premium.
B5: Group A - Light commercial vehicles
B6: Accident year | C6: Development age (months) | D6: Paid to date (£000) | E6: CDF | F6: Ultimate claims (£000) | G6: Reserve (£000) | H6: % paid to date
B7: 2020 | C7: 72 | D7: ='Data Validation'!AC18 -> 2432.5 | E7: ='Dev Factors'!H15 -> 1 | F7: =D7*E7 -> 2432.5 | G7: =F7-D7 -> 0 | H7: =D7/F7 -> 1
B8: 2021 | C8: 60 | D8: ='Data Validation'!AB19 -> 2437.7 | E8: ='Dev Factors'!G15 -> 1.0374904 | F8: =D8*E8 -> 2529.0904 | G8: =F8-D8 -> 91.390357 | H8: =D8/F8 -> 0.96386434
B9: 2022 | C9: 48 | D9: ='Data Validation'!AA20 -> 2898.3299 | E9: ='Dev Factors'!F15 -> 1.0792166 | F9: =D9*E9 -> 3127.9257 | G9: =F9-D9 -> 229.59581 | H9: =D9/F9 -> 0.92659806
B10: 2023 | C10: 36 | D10: ='Data Validation'!Z21 -> 2705.1 | E10: ='Dev Factors'!E15 -> 1.1831621 | F10: =D10*E10 -> 3200.5719 | G10: =F10-D10 -> 495.47185 | H10: =D10/F10 -> 0.84519271
B11: 2024 | C11: 24 | D11: ='Data Validation'!Y22 -> 2305.4 | E11: ='Dev Factors'!D15 -> 1.443042 | F11: =D11*E11 -> 3326.7891 | G11: =F11-D11 -> 1021.3891 | H11: =D11/F11 -> 0.6929805
B12: 2025 | C12: 12 | D12: ='Data Validation'!X23 -> 1525.9 | E12: ='Dev Factors'!C15 -> 2.395581 | F12: =D12*E12 -> 3655.4171 | G12: =F12-D12 -> 2129.5171 | H12: =D12/F12 -> 0.41743527
B13: Total | D13: =D7+D8+D9+D10+D11+D12 -> 14304.93 | F13: =F7+F8+F9+F10+F11+F12 -> 18272.294 | G13: =G7+G8+G9+G10+G11+G12 -> 3967.3642 | H13: =D13/F13 -> 0.78287542
B14: Check: every ultimate is at least the paid to date | F14: =IF(SUMPRODUCT(--(F7:F12<D7:D12))=0,"OK","REVIEW") -> OK
B18: Group B - Heavy goods vehicles
B19: Accident year | C19: Development age (months) | D19: Paid to date (£000) | E19: CDF | F19: Ultimate claims (£000) | G19: Reserve (£000) | H19: % paid to date
B20: 2020 | C20: 72 | D20: ='Data Validation'!AC34 -> 1851.3 | E20: ='Dev Factors'!H30 -> 1 | F20: =D20*E20 -> 1851.3 | G20: =F20-D20 -> 0 | H20: =D20/F20 -> 1
B21: 2021 | C21: 60 | D21: ='Data Validation'!AB35 -> 2106.4 | E21: ='Dev Factors'!G30 -> 1.02 | F21: =D21*E21 -> 2148.528 | G21: =F21-D21 -> 42.128 | H21: =D21/F21 -> 0.98039216
B22: 2022 | C22: 48 | D22: ='Data Validation'!AA36 -> 2119.6 | E22: ='Dev Factors'!F30 -> 1.1019113 | F22: =D22*E22 -> 2335.6113 | G22: =F22-D22 -> 216.01129 | H22: =D22/F22 -> 0.90751402
B23: 2023 | C23: 36 | D23: ='Data Validation'!Z37 -> 1982.1 | E23: ='Dev Factors'!E30 -> 1.2254031 | F23: =D23*E23 -> 2428.8715 | G23: =F23-D23 -> 446.77146 | H23: =D23/F23 -> 0.81605801
B24: 2024 | C24: 24 | D24: ='Data Validation'!Y38 -> 1694.4 | E24: ='Dev Factors'!D30 -> 1.5673225 | F24: =D24*E24 -> 2655.6713 | G24: =F24-D24 -> 961.27126 | H24: =D24/F24 -> 0.63803078
B25: 2025 | C25: 12 | D25: ='Data Validation'!X39 -> 907 | E25: ='Dev Factors'!C30 -> 2.9980001 | F25: =D25*E25 -> 2719.1861 | G25: =F25-D25 -> 1812.1861 | H25: =D25/F25 -> 0.33355569
B26: Total | D26: =D20+D21+D22+D23+D24+D25 -> 10660.8 | F26: =F20+F21+F22+F23+F24+F25 -> 14139.168 | G26: =G20+G21+G22+G23+G24+G25 -> 3478.3681 | H26: =D26/F26 -> 0.75399061
B27: Check: every ultimate is at least the paid to date | F27: =IF(SUMPRODUCT(--(F20:F25<D20:D25))=0,"OK","REVIEW") -> OK
B31: Group C - Specialist haulage
B32: Accident year | C32: Development age (months) | D32: Paid to date (£000) | E32: CDF | F32: Ultimate claims (£000) | G32: Reserve (£000) | H32: % paid to date
B33: 2020 | C33: 72 | D33: ='Data Validation'!AC50 -> 1300.2 | E33: ='Dev Factors'!H45 -> 1 | F33: =D33*E33 -> 1300.2 | G33: =F33-D33 -> 0 | H33: =D33/F33 -> 1
B34: 2021 | C34: 60 | D34: ='Data Validation'!AB51 -> 1409.9 | E34: ='Dev Factors'!G45 -> 1.0471972 | F34: =D34*E34 -> 1476.4433 | G34: =F34-D34 -> 66.543283 | H34: =D34/F34 -> 0.95493001
B35: 2022 | C35: 48 | D35: ='Data Validation'!AA52 -> 1598 | E35: ='Dev Factors'!F45 -> 1.1193434 | F35: =D35*E35 -> 1788.7108 | G35: =F35-D35 -> 190.71078 | H35: =D35/F35 -> 0.89338087
B36: 2023 | C36: 36 | D36: ='Data Validation'!Z53 -> 1260.1 | E36: ='Dev Factors'!E45 -> 1.3708526 | F36: =D36*E36 -> 1727.4114 | G36: =F36-D36 -> 467.3114 | H36: =D36/F36 -> 0.72947301
B37: 2024 | C37: 24 | D37: ='Data Validation'!Y54 -> 991.2 | E37: ='Dev Factors'!D45 -> 1.838804 | F37: =D37*E37 -> 1822.6225 | G37: =F37-D37 -> 831.42248 | H37: =D37/F37 -> 0.54383176
B38: 2025 | C38: 12 | D38: ='Data Validation'!X55 -> 469 | E38: ='Dev Factors'!C45 -> 3.8476142 | F38: =D38*E38 -> 1804.5311 | G38: =F38-D38 -> 1335.5311 | H38: =D38/F38 -> 0.25990132
B39: Total | D39: =D33+D34+D35+D36+D37+D38 -> 7028.4 | F39: =F33+F34+F35+F36+F37+F38 -> 9919.919 | G39: =G33+G34+G35+G36+G37+G38 -> 2891.519 | H39: =D39/F39 -> 0.70851385
B40: Check: every ultimate is at least the paid to date | F40: =IF(SUMPRODUCT(--(F33:F38<D33:D38))=0,"OK","REVIEW") -> OK
B44: Portfolio total - all rating groups
D45: Paid to date (£000) | F45: Ultimate claims (£000) | G45: Reserve (£000)
B46: Total | D46: =D13+D26+D39 -> 31994.13 | F46: =F13+F26+F39 -> 42331.381 | G46: =G13+G26+G39 -> 10337.251

Sheet On-Level & Cred
B1: Stage 2 - On-levelling, loss trend and the credibility-weighted a priori loss ratio
B2: On-levelling restates historical earned premium to the rate level of the latest accident year; the loss trend restates historical claims to the latest cost level. Together they make the historical loss ratios comparable. The resulting experience indication is then blended with the business plan loss ratio using limited fluctuation credibility, giving the a priori loss ratio used by the Expected Claims and Bornhuetter-Ferguson bases.
B6: Group A - Light commercial vehicles
B7: Accident year | C7: Rate change (validated) | D7: Cumulative rate index | E7: On-level factor | F7: Earned premium (£000) | G7: On-level premium (£000) | H7: Trend factor | I7: Chain Ladder ultimate (£000) | J7: Trended ultimate (£000) | K7: Include in indication
B8: 2020 | C8: ='Data Validation'!K67 -> 0.02 | D8: =1+C8 -> 1.02 | E8: =$D$13/D8 -> 1.1677742 | F8: ='Raw Data'!C63 -> 4200 | G8: =F8*E8 -> 4904.6517 | H8: =(1+Loss_trend)^($B$13-B8) -> 1.30696 | I8: ='S1 Chain Ladder'!F7 -> 2432.5 | J8: =I8*H8 -> 3179.1802 | K8: =IF(B8<=$B$8+INDEX(Cred_mature,1)-1,1,0) -> 1
B9: 2021 | C9: ='Data Validation'!K68 -> -0.015 | D9: =D8*(1+C9) -> 1.0047 | E9: =$D$13/D9 -> 1.1855576 | F9: ='Raw Data'!C64 -> 4450 | G9: =F9*E9 -> 5275.7312 | H9: =(1+Loss_trend)^($B$13-B9) -> 1.2388247 | I9: ='S1 Chain Ladder'!F8 -> 2529.0904 | J9: =I9*H9 -> 3133.0995 | K9: =IF(B9<=$B$8+INDEX(Cred_mature,1)-1,1,0) -> 1
B10: 2022 | C10: ='Data Validation'!K69 -> 0.01 | D10: =D9*(1+C10) -> 1.014747 | E10: =$D$13/D10 -> 1.1738194 | F10: ='Raw Data'!C65 -> 4600 | G10: =F10*E10 -> 5399.5691 | H10: =(1+Loss_trend)^($B$13-B10) -> 1.1742414 | I10: ='S1 Chain Ladder'!F9 -> 3127.9257 | J10: =I10*H10 -> 3672.9398 | K10: =IF(B10<=$B$8+INDEX(Cred_mature,1)-1,1,0) -> 1
B11: 2023 | C11: ='Data Validation'!K70 -> 0.055 | D11: =D10*(1+C11) -> 1.0705581 | E11: =$D$13/D11 -> 1.112625 | F11: ='Raw Data'!C66 -> 4900 | G11: =F11*E11 -> 5451.8625 | H11: =(1+Loss_trend)^($B$13-B11) -> 1.113025 | I11: ='S1 Chain Ladder'!F10 -> 3200.5719 | J11: =I11*H11 -> 3562.3165 | K11: =IF(B11<=$B$8+INDEX(Cred_mature,1)-1,1,0) -> 0
B12: 2024 | C12: ='Data Validation'!K71 -> 0.075 | D12: =D11*(1+C12) -> 1.1508499 | E12: =$D$13/D12 -> 1.035 | F12: ='Raw Data'!C67 -> 5350 | G12: =F12*E12 -> 5537.25 | H12: =(1+Loss_trend)^($B$13-B12) -> 1.055 | I12: ='S1 Chain Ladder'!F11 -> 3326.7891 | J12: =I12*H12 -> 3509.7625 | K12: =IF(B12<=$B$8+INDEX(Cred_mature,1)-1,1,0) -> 0
B13: 2025 | C13: ='Data Validation'!K72 -> 0.035 | D13: =D12*(1+C13) -> 1.1911297 | E13: =$D$13/D13 -> 1 | F13: ='Raw Data'!C68 -> 5700 | G13: =F13*E13 -> 5700 | H13: =(1+Loss_trend)^($B$13-B13) -> 1 | I13: ='S1 Chain Ladder'!F12 -> 3655.4171 | J13: =I13*H13 -> 3655.4171 | K13: =IF(B13<=$B$8+INDEX(Cred_mature,1)-1,1,0) -> 0
B14: Derivation of the a priori loss ratio (at 2025 rate and cost level)
B15: Accident years used for the experience indication (oldest first) | C15: =SUM(K8:K13) -> 3
B16: Trended ultimate claims over those years (£000) | C16: =SUMPRODUCT($K$8:$K$13,$J$8:$J$13) -> 9985.2195
B17: On-level earned premium over those years (£000) | C17: =SUMPRODUCT($K$8:$K$13,$G$8:$G$13) -> 15579.952
B18: Experience indication - on-level ultimate loss ratio | C18: =C16/C17 -> 0.64090181
B19: Reported claims over those years | C19: =SUMPRODUCT($K$8:$K$13,'Raw Data'!C41:C46) -> 940
B20: Full credibility standard (claims) | C20: =INDEX(Cred_full,1) -> 1082
B21: Credibility factor Z = min(1, sqrt(n / n_full)) | C21: =MIN(1,SQRT(C19/C20)) -> 0.93207379
B22: Business plan loss ratio (complement of credibility) | C22: =INDEX(Plan_LR,1) -> 0.62
B23: A priori loss ratio = Z x indication + (1-Z) x plan | C23: =C21*C18+(1-C21)*C22 -> 0.63948203
B24: Check: Z lies in [0,1] and the a priori lies between the indication and the plan | C24: =IF(AND(C21>=0,C21<=1,C23>=MIN(C18,C22)-0.0001,C23<=MAX(C18,C22)+0.0001),"OK","REVIEW") -> OK
B25: Check: the latest accident year on-level factor equals 1.0000 | C25: =IF(ABS(E13-1)<0.000001,"OK","REVIEW") -> OK
B28: Group B - Heavy goods vehicles
B29: Accident year | C29: Rate change (validated) | D29: Cumulative rate index | E29: On-level factor | F29: Earned premium (£000) | G29: On-level premium (£000) | H29: Trend factor | I29: Chain Ladder ultimate (£000) | J29: Trended ultimate (£000) | K29: Include in indication
B30: 2020 | C30: ='Data Validation'!L67 -> 0.03 | D30: =1+C30 -> 1.03 | E30: =$D$35/D30 -> 1.1886748 | F30: ='Raw Data'!D63 -> 3100 | G30: =F30*E30 -> 3684.892 | H30: =(1+Loss_trend)^($B$35-B30) -> 1.30696 | I30: ='S1 Chain Ladder'!F20 -> 1851.3 | J30: =I30*H30 -> 2419.5751 | K30: =IF(B30<=$B$30+INDEX(Cred_mature,2)-1,1,0) -> 1
B31: 2021 | C31: ='Data Validation'!L68 -> -0.025 | D31: =D30*(1+C31) -> 1.00425 | E31: =$D$35/D31 -> 1.2191537 | F31: ='Raw Data'!D64 -> 3250 | G31: =F31*E31 -> 3962.2495 | H31: =(1+Loss_trend)^($B$35-B31) -> 1.2388247 | I31: ='S1 Chain Ladder'!F21 -> 2148.528 | J31: =I31*H31 -> 2661.6494 | K31: =IF(B31<=$B$30+INDEX(Cred_mature,2)-1,1,0) -> 1
B32: 2022 | C32: ='Data Validation'!L69 -> 0.005 | D32: =D31*(1+C32) -> 1.0092713 | E32: =$D$35/D32 -> 1.2130882 | F32: ='Raw Data'!D65 -> 3300 | G32: =F32*E32 -> 4003.1912 | H32: =(1+Loss_trend)^($B$35-B32) -> 1.1742414 | I32: ='S1 Chain Ladder'!F22 -> 2335.6113 | J32: =I32*H32 -> 2742.5714 | K32: =IF(B32<=$B$30+INDEX(Cred_mature,2)-1,1,0) -> 1
B33: 2023 | C33: ='Data Validation'!L70 -> 0.065 | D33: =D32*(1+C33) -> 1.0748739 | E33: =$D$35/D33 -> 1.13905 | F33: ='Raw Data'!D66 -> 3500 | G33: =F33*E33 -> 3986.675 | H33: =(1+Loss_trend)^($B$35-B33) -> 1.113025 | I33: ='S1 Chain Ladder'!F23 -> 2428.8715 | J33: =I33*H33 -> 2703.3947 | K33: =IF(B33<=$B$30+INDEX(Cred_mature,2)-1,1,0) -> 0
B34: 2024 | C34: ='Data Validation'!L71 -> 0.09 | D34: =D33*(1+C34) -> 1.1716125 | E34: =$D$35/D34 -> 1.045 | F34: ='Raw Data'!D67 -> 3850 | G34: =F34*E34 -> 4023.25 | H34: =(1+Loss_trend)^($B$35-B34) -> 1.055 | I34: ='S1 Chain Ladder'!F24 -> 2655.6713 | J34: =I34*H34 -> 2801.7332 | K34: =IF(B34<=$B$30+INDEX(Cred_mature,2)-1,1,0) -> 0
B35: 2025 | C35: ='Data Validation'!L72 -> 0.045 | D35: =D34*(1+C35) -> 1.2243351 | E35: =$D$35/D35 -> 1 | F35: ='Raw Data'!D68 -> 4150 | G35: =F35*E35 -> 4150 | H35: =(1+Loss_trend)^($B$35-B35) -> 1 | I35: ='S1 Chain Ladder'!F25 -> 2719.1861 | J35: =I35*H35 -> 2719.1861 | K35: =IF(B35<=$B$30+INDEX(Cred_mature,2)-1,1,0) -> 0
B36: Derivation of the a priori loss ratio (at 2025 rate and cost level)
B37: Accident years used for the experience indication (oldest first) | C37: =SUM(K30:K35) -> 3
B38: Trended ultimate claims over those years (£000) | C38: =SUMPRODUCT($K$30:$K$35,$J$30:$J$35) -> 7823.7959
B39: On-level earned premium over those years (£000) | C39: =SUMPRODUCT($K$30:$K$35,$G$30:$G$35) -> 11650.333
B40: Experience indication - on-level ultimate loss ratio | C40: =C38/C39 -> 0.67155128
B41: Reported claims over those years | C41: =SUMPRODUCT($K$30:$K$35,'Raw Data'!D41:D46) -> 450
B42: Full credibility standard (claims) | C42: =INDEX(Cred_full,2) -> 1082
B43: Credibility factor Z = min(1, sqrt(n / n_full)) | C43: =MIN(1,SQRT(C41/C42)) -> 0.64490037
B44: Business plan loss ratio (complement of credibility) | C44: =INDEX(Plan_LR,2) -> 0.7
B45: A priori loss ratio = Z x indication + (1-Z) x plan | C45: =C43*C40+(1-C43)*C44 -> 0.68165341
B46: Check: Z lies in [0,1] and the a priori lies between the indication and the plan | C46: =IF(AND(C43>=0,C43<=1,C45>=MIN(C40,C44)-0.0001,C45<=MAX(C40,C44)+0.0001),"OK","REVIEW") -> OK
B47: Check: the latest accident year on-level factor equals 1.0000 | C47: =IF(ABS(E35-1)<0.000001,"OK","REVIEW") -> OK
B50: Group C - Specialist haulage
B51: Accident year | C51: Rate change (validated) | D51: Cumulative rate index | E51: On-level factor | F51: Earned premium (£000) | G51: On-level premium (£000) | H51: Trend factor | I51: Chain Ladder ultimate (£000) | J51: Trended ultimate (£000) | K51: Include in indication
B52: 2020 | C52: ='Data Validation'!M67 -> 0.015 | D52: =1+C52 -> 1.015 | E52: =$D$57/D52 -> 1.22275 | F52: ='Raw Data'!E63 -> 1800 | G52: =F52*E52 -> 2200.95 | H52: =(1+Loss_trend)^($B$57-B52) -> 1.30696 | I52: ='S1 Chain Ladder'!F33 -> 1300.2 | J52: =I52*H52 -> 1699.3094 | K52: =IF(B52<=$B$52+INDEX(Cred_mature,3)-1,1,0) -> 1
B53: 2021 | C53: ='Data Validation'!M68 -> -0.03 | D53: =D52*(1+C53) -> 0.98455 | E53: =$D$57/D53 -> 1.260567 | F53: ='Raw Data'!E64 -> 1900 | G53: =F53*E53 -> 2395.0773 | H53: =(1+Loss_trend)^($B$57-B53) -> 1.2388247 | I53: ='S1 Chain Ladder'!F34 -> 1476.4433 | J53: =I53*H53 -> 1829.0543 | K53: =IF(B53<=$B$52+INDEX(Cred_mature,3)-1,1,0) -> 1
B54: 2022 | C54: ='Data Validation'!M69 -> 0.02 | D54: =D53*(1+C54) -> 1.004241 | E54: =$D$57/D54 -> 1.23585 | F54: ='Raw Data'!E65 -> 2000 | G54: =F54*E54 -> 2471.7 | H54: =(1+Loss_trend)^($B$57-B54) -> 1.1742414 | I54: ='S1 Chain Ladder'!F35 -> 1788.7108 | J54: =I54*H54 -> 2100.3782 | K54: =IF(B54<=$B$52+INDEX(Cred_mature,3)-1,1,0) -> 1
B55: 2023 | C55: ='Data Validation'!M70 -> 0.07 | D55: =D54*(1+C55) -> 1.0745379 | E55: =$D$57/D55 -> 1.155 | F55: ='Raw Data'!E66 -> 2150 | G55: =F55*E55 -> 2483.25 | H55: =(1+Loss_trend)^($B$57-B55) -> 1.113025 | I55: ='S1 Chain Ladder'!F36 -> 1727.4114 | J55: =I55*H55 -> 1922.6521 | K55: =IF(B55<=$B$52+INDEX(Cred_mature,3)-1,1,0) -> 0
B56: 2024 | C56: ='Data Validation'!M71 -> 0.1 | D56: =D55*(1+C56) -> 1.1819917 | E56: =$D$57/D56 -> 1.05 | F56: ='Raw Data'!E67 -> 2400 | G56: =F56*E56 -> 2520 | H56: =(1+Loss_trend)^($B$57-B56) -> 1.055 | I56: ='S1 Chain Ladder'!F37 -> 1822.6225 | J56: =I56*H56 -> 1922.8667 | K56: =IF(B56<=$B$52+INDEX(Cred_mature,3)-1,1,0) -> 0
B57: 2025 | C57: ='Data Validation'!M72 -> 0.05 | D57: =D56*(1+C57) -> 1.2410912 | E57: =$D$57/D57 -> 1 | F57: ='Raw Data'!E68 -> 2650 | G57: =F57*E57 -> 2650 | H57: =(1+Loss_trend)^($B$57-B57) -> 1 | I57: ='S1 Chain Ladder'!F38 -> 1804.5311 | J57: =I57*H57 -> 1804.5311 | K57: =IF(B57<=$B$52+INDEX(Cred_mature,3)-1,1,0) -> 0
B58: Derivation of the a priori loss ratio (at 2025 rate and cost level)
B59: Accident years used for the experience indication (oldest first) | C59: =SUM(K52:K57) -> 3
B60: Trended ultimate claims over those years (£000) | C60: =SUMPRODUCT($K$52:$K$57,$J$52:$J$57) -> 5628.7419
B61: On-level earned premium over those years (£000) | C61: =SUMPRODUCT($K$52:$K$57,$G$52:$G$57) -> 7067.7273
B62: Experience indication - on-level ultimate loss ratio | C62: =C60/C61 -> 0.79640056
B63: Reported claims over those years | C63: =SUMPRODUCT($K$52:$K$57,'Raw Data'!E41:E46) -> 192
B64: Full credibility standard (claims) | C64: =INDEX(Cred_full,3) -> 1082
B65: Credibility factor Z = min(1, sqrt(n / n_full)) | C65: =MIN(1,SQRT(C63/C64)) -> 0.42124716
B66: Business plan loss ratio (complement of credibility) | C66: =INDEX(Plan_LR,3) -> 0.76
B67: A priori loss ratio = Z x indication + (1-Z) x plan | C67: =C65*C62+(1-C65)*C66 -> 0.77533363
B68: Check: Z lies in [0,1] and the a priori lies between the indication and the plan | C68: =IF(AND(C65>=0,C65<=1,C67>=MIN(C62,C66)-0.0001,C67<=MAX(C62,C66)+0.0001),"OK","REVIEW") -> OK
B69: Check: the latest accident year on-level factor equals 1.0000 | C69: =IF(ABS(E57-1)<0.000001,"OK","REVIEW") -> OK

Sheet S2 Expected Claims
B1: Base Scenario 2 - Expected Claims
B2: Ultimate claims are the a priori loss ratio applied to on-level earned premium and then restated to the cost level of the accident year. The method ignores the claims reported to date and therefore gives a stable answer for immature years but can conflict with actual experience for mature years.
B3: Expected ultimate = On-level premium x A priori loss ratio / Trend factor.
B6: Group A - Light commercial vehicles
B7: Accident year | C7: On-level premium (£000) | D7: Trend factor | E7: Expected loss ratio | F7: Ultimate claims (£000) | G7: Paid to date (£000) | H7: Implied reserve (£000)
B8: 2020 | C8: ='On-Level & Cred'!G8 -> 4904.6517 | D8: ='On-Level & Cred'!H8 -> 1.30696 | E8: ='On-Level & Cred'!$C$23*'On-Level & Cred'!E8/D8 -> 0.57137986 | F8: =C8*'On-Level & Cred'!$C$23/D8 -> 2399.7954 | G8: ='S1 Chain Ladder'!D7 -> 2432.5 | H8: =F8-G8 -> -32.704599
B9: 2021 | C9: ='On-Level & Cred'!G9 -> 5275.7312 | D9: ='On-Level & Cred'!H9 -> 1.2388247 | E9: ='On-Level & Cred'!$C$23*'On-Level & Cred'!E9/D9 -> 0.61198553 | F9: =C9*'On-Level & Cred'!$C$23/D9 -> 2723.3356 | G9: ='S1 Chain Ladder'!D8 -> 2437.7 | H9: =F9-G9 -> 285.63562
B10: 2022 | C10: ='On-Level & Cred'!G10 -> 5399.5691 | D10: ='On-Level & Cred'!H10 -> 1.1742414 | E10: ='On-Level & Cred'!$C$23*'On-Level & Cred'!E10/D10 -> 0.63925221 | F10: =C10*'On-Level & Cred'!$C$23/D10 -> 2940.5602 | G10: ='S1 Chain Ladder'!D9 -> 2898.3299 | H10: =F10-G10 -> 42.230301
B11: 2023 | C11: ='On-Level & Cred'!G11 -> 5451.8625 | D11: ='On-Level & Cred'!H11 -> 1.113025 | E11: ='On-Level & Cred'!$C$23*'On-Level & Cred'!E11/D11 -> 0.63925221 | F11: =C11*'On-Level & Cred'!$C$23/D11 -> 3132.3359 | G11: ='S1 Chain Ladder'!D10 -> 2705.1 | H11: =F11-G11 -> 427.23585
B12: 2024 | C12: ='On-Level & Cred'!G12 -> 5537.25 | D12: ='On-Level & Cred'!H12 -> 1.055 | E12: ='On-Level & Cred'!$C$23*'On-Level & Cred'!E12/D12 -> 0.62735915 | F12: =C12*'On-Level & Cred'!$C$23/D12 -> 3356.3715 | G12: ='S1 Chain Ladder'!D11 -> 2305.4 | H12: =F12-G12 -> 1050.9715
B13: 2025 | C13: ='On-Level & Cred'!G13 -> 5700 | D13: ='On-Level & Cred'!H13 -> 1 | E13: ='On-Level & Cred'!$C$23*'On-Level & Cred'!E13/D13 -> 0.63948203 | F13: =C13*'On-Level & Cred'!$C$23/D13 -> 3645.0476 | G13: ='S1 Chain Ladder'!D12 -> 1525.9 | H13: =F13-G13 -> 2119.1476
B14: Total | F14: =SUM(F8:F13) -> 18197.446 | G14: =SUM(G8:G13) -> 14304.93 | H14: =SUM(H8:H13) -> 3892.5162
B15: Check: any accident year where the expected ultimate falls below the paid to date | F15: =IF(SUMPRODUCT(--(H8:H13<0))=0,"OK","SEE NOTE") -> SEE NOTE
B16: A negative implied reserve is a genuine feature of this method, not an error: it means actual paid claims have already exceeded the premium-based expectation. It is reported rather than floored, and is discussed in the Audit Trail.
B19: Group B - Heavy goods vehicles
B20: Accident year | C20: On-level premium (£000) | D20: Trend factor | E20: Expected loss ratio | F20: Ultimate claims (£000) | G20: Paid to date (£000) | H20: Implied reserve (£000)
B21: 2020 | C21: ='On-Level & Cred'!G30 -> 3684.892 | D21: ='On-Level & Cred'!H30 -> 1.30696 | E21: ='On-Level & Cred'!$C$45*'On-Level & Cred'!E30/D21 -> 0.61996103 | F21: =C21*'On-Level & Cred'!$C$45/D21 -> 1921.8792 | G21: ='S1 Chain Ladder'!D20 -> 1851.3 | H21: =F21-G21 -> 70.579183
B22: 2021 | C22: ='On-Level & Cred'!G31 -> 3962.2495 | D22: ='On-Level & Cred'!H31 -> 1.2388247 | E22: ='On-Level & Cred'!$C$45*'On-Level & Cred'!E31/D22 -> 0.67082962 | F22: =C22*'On-Level & Cred'!$C$45/D22 -> 2180.1963 | G22: ='S1 Chain Ladder'!D21 -> 2106.4 | H22: =F22-G22 -> 73.796277
B23: 2022 | C23: ='On-Level & Cred'!G32 -> 4003.1912 | D23: ='On-Level & Cred'!H32 -> 1.1742414 | E23: ='On-Level & Cred'!$C$45*'On-Level & Cred'!E32/D23 -> 0.70420423 | F23: =C23*'On-Level & Cred'!$C$45/D23 -> 2323.874 | G23: ='S1 Chain Ladder'!D22 -> 2119.6 | H23: =F23-G23 -> 204.27397
B24: 2023 | C24: ='On-Level & Cred'!G33 -> 3986.675 | D24: ='On-Level & Cred'!H33 -> 1.113025 | E24: ='On-Level & Cred'!$C$45*'On-Level & Cred'!E33/D24 -> 0.69759199 | F24: =C24*'On-Level & Cred'!$C$45/D24 -> 2441.5719 | G24: ='S1 Chain Ladder'!D23 -> 1982.1 | H24: =F24-G24 -> 459.47195
B25: 2024 | C25: ='On-Level & Cred'!G34 -> 4023.25 | D25: ='On-Level & Cred'!H34 -> 1.055 | E25: ='On-Level & Cred'!$C$45*'On-Level & Cred'!E34/D25 -> 0.67519224 | F25: =C25*'On-Level & Cred'!$C$45/D25 -> 2599.4901 | G25: ='S1 Chain Ladder'!D24 -> 1694.4 | H25: =F25-G25 -> 905.09014
B26: 2025 | C26: ='On-Level & Cred'!G35 -> 4150 | D26: ='On-Level & Cred'!H35 -> 1 | E26: ='On-Level & Cred'!$C$45*'On-Level & Cred'!E35/D26 -> 0.68165341 | F26: =C26*'On-Level & Cred'!$C$45/D26 -> 2828.8617 | G26: ='S1 Chain Ladder'!D25 -> 907 | H26: =F26-G26 -> 1921.8617
B27: Total | F27: =SUM(F21:F26) -> 14295.873 | G27: =SUM(G21:G26) -> 10660.8 | H27: =SUM(H21:H26) -> 3635.0732
B28: Check: any accident year where the expected ultimate falls below the paid to date | F28: =IF(SUMPRODUCT(--(H21:H26<0))=0,"OK","SEE NOTE") -> OK
B29: A negative implied reserve is a genuine feature of this method, not an error: it means actual paid claims have already exceeded the premium-based expectation. It is reported rather than floored, and is discussed in the Audit Trail.
B32: Group C - Specialist haulage
B33: Accident year | C33: On-level premium (£000) | D33: Trend factor | E33: Expected loss ratio | F33: Ultimate claims (£000) | G33: Paid to date (£000) | H33: Implied reserve (£000)
B34: 2020 | C34: ='On-Level & Cred'!G52 -> 2200.95 | D34: ='On-Level & Cred'!H52 -> 1.30696 | E34: ='On-Level & Cred'!$C$67*'On-Level & Cred'!E52/D34 -> 0.72537735 | F34: =C34*'On-Level & Cred'!$C$67/D34 -> 1305.6792 | G34: ='S1 Chain Ladder'!D33 -> 1300.2 | H34: =F34-G34 -> 5.4792351
B35: 2021 | C35: ='On-Level & Cred'!G53 -> 2395.0773 | D35: ='On-Level & Cred'!H53 -> 1.2388247 | E35: ='On-Level & Cred'!$C$67*'On-Level & Cred'!E53/D35 -> 0.78894135 | F35: =C35*'On-Level & Cred'!$C$67/D35 -> 1498.9886 | G35: ='S1 Chain Ladder'!D34 -> 1409.9 | H35: =F35-G35 -> 89.088561
B36: 2022 | C36: ='On-Level & Cred'!G54 -> 2471.7 | D36: ='On-Level & Cred'!H54 -> 1.1742414 | E36: ='On-Level & Cred'!$C$67*'On-Level & Cred'!E54/D36 -> 0.81601286 | F36: =C36*'On-Level & Cred'!$C$67/D36 -> 1632.0257 | G36: ='S1 Chain Ladder'!D35 -> 1598 | H36: =F36-G36 -> 34.025729
B37: 2023 | C37: ='On-Level & Cred'!G55 -> 2483.25 | D37: ='On-Level & Cred'!H55 -> 1.113025 | E37: ='On-Level & Cred'!$C$67*'On-Level & Cred'!E55/D37 -> 0.80457343 | F37: =C37*'On-Level & Cred'!$C$67/D37 -> 1729.8329 | G37: ='S1 Chain Ladder'!D36 -> 1260.1 | H37: =F37-G37 -> 469.73288
B38: 2024 | C38: ='On-Level & Cred'!G56 -> 2520 | D38: ='On-Level & Cred'!H56 -> 1.055 | E38: ='On-Level & Cred'!$C$67*'On-Level & Cred'!E56/D38 -> 0.77165906 | F38: =C38*'On-Level & Cred'!$C$67/D38 -> 1851.9818 | G38: ='S1 Chain Ladder'!D37 -> 991.2 | H38: =F38-G38 -> 860.78175
B39: 2025 | C39: ='On-Level & Cred'!G57 -> 2650 | D39: ='On-Level & Cred'!H57 -> 1 | E39: ='On-Level & Cred'!$C$67*'On-Level & Cred'!E57/D39 -> 0.77533363 | F39: =C39*'On-Level & Cred'!$C$67/D39 -> 2054.6341 | G39: ='S1 Chain Ladder'!D38 -> 469 | H39: =F39-G39 -> 1585.6341
B40: Total | F40: =SUM(F34:F39) -> 10073.142 | G40: =SUM(G34:G39) -> 7028.4 | H40: =SUM(H34:H39) -> 3044.7423
B41: Check: any accident year where the expected ultimate falls below the paid to date | F41: =IF(SUMPRODUCT(--(H34:H39<0))=0,"OK","SEE NOTE") -> OK
B42: A negative implied reserve is a genuine feature of this method, not an error: it means actual paid claims have already exceeded the premium-based expectation. It is reported rather than floored, and is discussed in the Audit Trail.
B45: Portfolio total - all rating groups
F46: Ultimate claims (£000) | G46: Paid to date (£000) | H46: Reserve (£000)
B47: Total | F47: =F14+F27+F40 -> 42566.462 | G47: =G14+G27+G40 -> 31994.13 | H47: =H14+H27+H40 -> 10572.332

Sheet S3 BF
B1: Base Scenario 3 - Bornhuetter-Ferguson
B2: The Bornhuetter-Ferguson ultimate accepts the claims already paid and adds the unpaid portion implied by the development pattern applied to the expected claims from Scenario 2. It therefore behaves like the Chain Ladder for mature years and like the Expected Claims method for immature years.
B3: BF ultimate = Paid to date + Expected ultimate x (1 - 1 / CDF).
B6: Group A - Light commercial vehicles
B7: Accident year | C7: Paid to date (£000) | D7: CDF | E7: % unpaid (1 - 1/CDF) | F7: Expected ultimate (£000) | G7: Ultimate claims (£000) | H7: Reserve (£000)
B8: 2020 | C8: ='S1 Chain Ladder'!D7 -> 2432.5 | D8: ='S1 Chain Ladder'!E7 -> 1 | E8: =1-1/D8 -> 0 | F8: ='S2 Expected Claims'!F8 -> 2399.7954 | G8: =C8+F8*E8 -> 2432.5 | H8: =G8-C8 -> 0
B9: 2021 | C9: ='S1 Chain Ladder'!D8 -> 2437.7 | D9: ='S1 Chain Ladder'!E8 -> 1.0374904 | E9: =1-1/D9 -> 0.036135663 | F9: ='S2 Expected Claims'!F9 -> 2723.3356 | G9: =C9+F9*E9 -> 2536.1095 | H9: =G9-C9 -> 98.409538
B10: 2022 | C10: ='S1 Chain Ladder'!D9 -> 2898.3299 | D10: ='S1 Chain Ladder'!E9 -> 1.0792166 | E10: =1-1/D10 -> 0.07340194 | F10: ='S2 Expected Claims'!F10 -> 2940.5602 | G10: =C10+F10*E10 -> 3114.1727 | H10: =G10-C10 -> 215.84282
B11: 2023 | C11: ='S1 Chain Ladder'!D10 -> 2705.1 | D11: ='S1 Chain Ladder'!E10 -> 1.1831621 | E11: =1-1/D11 -> 0.15480729 | F11: ='S2 Expected Claims'!F11 -> 3132.3359 | G11: =C11+F11*E11 -> 3190.0084 | H11: =G11-C11 -> 484.90842
B12: 2024 | C12: ='S1 Chain Ladder'!D11 -> 2305.4 | D12: ='S1 Chain Ladder'!E11 -> 1.443042 | E12: =1-1/D12 -> 0.3070195 | F12: ='S2 Expected Claims'!F12 -> 3356.3715 | G12: =C12+F12*E12 -> 3335.8715 | H12: =G12-C12 -> 1030.4715
B13: 2025 | C13: ='S1 Chain Ladder'!D12 -> 1525.9 | D13: ='S1 Chain Ladder'!E12 -> 2.395581 | E13: =1-1/D13 -> 0.58256473 | F13: ='S2 Expected Claims'!F13 -> 3645.0476 | G13: =C13+F13*E13 -> 3649.3762 | H13: =G13-C13 -> 2123.4762
B14: Total | C14: =SUM(C8:C13) -> 14304.93 | G14: =SUM(G8:G13) -> 18258.038 | H14: =SUM(H8:H13) -> 3953.1084
B15: Check: in every accident year the BF ultimate lies between the Chain Ladder and Expected Claims ultimates | G15: =IF(SUMPRODUCT(--(G8:G13<MIN(0)+0))+SUMPRODUCT(--(G8:G13<'S1 Chain Ladder'!F7:F12-0.001)*--(G8:G13<F8:F13-0.001))+SUMPRODUCT(--(G8:G13>'S1 Chain Ladder'!F7:F12+0.001)*--(G8:G13>F8:F13+0.001))=0,"OK","REVIEW") -> OK
B16: This test is applied accident year by accident year. It need not hold for the column totals, because the ordering of the two comparators changes between years.
B19: Group B - Heavy goods vehicles
B20: Accident year | C20: Paid to date (£000) | D20: CDF | E20: % unpaid (1 - 1/CDF) | F20: Expected ultimate (£000) | G20: Ultimate claims (£000) | H20: Reserve (£000)
B21: 2020 | C21: ='S1 Chain Ladder'!D20 -> 1851.3 | D21: ='S1 Chain Ladder'!E20 -> 1 | E21: =1-1/D21 -> 0 | F21: ='S2 Expected Claims'!F21 -> 1921.8792 | G21: =C21+F21*E21 -> 1851.3 | H21: =G21-C21 -> 0
B22: 2021 | C22: ='S1 Chain Ladder'!D21 -> 2106.4 | D22: ='S1 Chain Ladder'!E21 -> 1.02 | E22: =1-1/D22 -> 0.019607843 | F22: ='S2 Expected Claims'!F22 -> 2180.1963 | G22: =C22+F22*E22 -> 2149.1489 | H22: =G22-C22 -> 42.748947
B23: 2022 | C23: ='S1 Chain Ladder'!D22 -> 2119.6 | D23: ='S1 Chain Ladder'!E22 -> 1.1019113 | E23: =1-1/D23 -> 0.092485977 | F23: ='S2 Expected Claims'!F23 -> 2323.874 | G23: =C23+F23*E23 -> 2334.5258 | H23: =G23-C23 -> 214.92575
B24: 2023 | C24: ='S1 Chain Ladder'!D23 -> 1982.1 | D24: ='S1 Chain Ladder'!E23 -> 1.2254031 | E24: =1-1/D24 -> 0.18394199 | F24: ='S2 Expected Claims'!F24 -> 2441.5719 | G24: =C24+F24*E24 -> 2431.2076 | H24: =G24-C24 -> 449.10761
B25: 2024 | C25: ='S1 Chain Ladder'!D24 -> 1694.4 | D25: ='S1 Chain Ladder'!E24 -> 1.5673225 | E25: =1-1/D25 -> 0.36196922 | F25: ='S2 Expected Claims'!F25 -> 2599.4901 | G25: =C25+F25*E25 -> 2635.3354 | H25: =G25-C25 -> 940.93542
B26: 2025 | C26: ='S1 Chain Ladder'!D25 -> 907 | D26: ='S1 Chain Ladder'!E25 -> 2.9980001 | E26: =1-1/D26 -> 0.66644431 | F26: ='S2 Expected Claims'!F26 -> 2828.8617 | G26: =C26+F26*E26 -> 2792.2788 | H26: =G26-C26 -> 1885.2788
B27: Total | C27: =SUM(C21:C26) -> 10660.8 | G27: =SUM(G21:G26) -> 14193.796 | H27: =SUM(H21:H26) -> 3532.9965
B28: Check: in every accident year the BF ultimate lies between the Chain Ladder and Expected Claims ultimates | G28: =IF(SUMPRODUCT(--(G21:G26<MIN(0)+0))+SUMPRODUCT(--(G21:G26<'S1 Chain Ladder'!F20:F25-0.001)*--(G21:G26<F21:F26-0.001))+SUMPRODUCT(--(G21:G26>'S1 Chain Ladder'!F20:F25+0.001)*--(G21:G26>F21:F26+0.001))=0,"OK","REVIEW") -> OK
B29: This test is applied accident year by accident year. It need not hold for the column totals, because the ordering of the two comparators changes between years.
B32: Group C - Specialist haulage
B33: Accident year | C33: Paid to date (£000) | D33: CDF | E33: % unpaid (1 - 1/CDF) | F33: Expected ultimate (£000) | G33: Ultimate claims (£000) | H33: Reserve (£000)
B34: 2020 | C34: ='S1 Chain Ladder'!D33 -> 1300.2 | D34: ='S1 Chain Ladder'!E33 -> 1 | E34: =1-1/D34 -> 0 | F34: ='S2 Expected Claims'!F34 -> 1305.6792 | G34: =C34+F34*E34 -> 1300.2 | H34: =G34-C34 -> 0
B35: 2021 | C35: ='S1 Chain Ladder'!D34 -> 1409.9 | D35: ='S1 Chain Ladder'!E34 -> 1.0471972 | E35: =1-1/D35 -> 0.045069989 | F35: ='S2 Expected Claims'!F35 -> 1498.9886 | G35: =C35+F35*E35 -> 1477.4594 | H35: =G35-C35 -> 67.559398
B36: 2022 | C36: ='S1 Chain Ladder'!D35 -> 1598 | D36: ='S1 Chain Ladder'!E35 -> 1.1193434 | E36: =1-1/D36 -> 0.10661913 | F36: ='S2 Expected Claims'!F36 -> 1632.0257 | G36: =C36+F36*E36 -> 1772.0052 | H36: =G36-C36 -> 174.00516
B37: 2023 | C37: ='S1 Chain Ladder'!D36 -> 1260.1 | D37: ='S1 Chain Ladder'!E36 -> 1.3708526 | E37: =1-1/D37 -> 0.27052699 | F37: ='S2 Expected Claims'!F37 -> 1729.8329 | G37: =C37+F37*E37 -> 1728.0665 | H37: =G37-C37 -> 467.96647
B38: 2024 | C38: ='S1 Chain Ladder'!D37 -> 991.2 | D38: ='S1 Chain Ladder'!E37 -> 1.838804 | E38: =1-1/D38 -> 0.45616824 | F38: ='S2 Expected Claims'!F38 -> 1851.9818 | G38: =C38+F38*E38 -> 1836.0153 | H38: =G38-C38 -> 844.81525
B39: 2025 | C39: ='S1 Chain Ladder'!D38 -> 469 | D39: ='S1 Chain Ladder'!E38 -> 3.8476142 | E39: =1-1/D39 -> 0.74009868 | F39: ='S2 Expected Claims'!F39 -> 2054.6341 | G39: =C39+F39*E39 -> 1989.632 | H39: =G39-C39 -> 1520.632
B40: Total | C40: =SUM(C34:C39) -> 7028.4 | G40: =SUM(G34:G39) -> 10103.378 | H40: =SUM(H34:H39) -> 3074.9783
B41: Check: in every accident year the BF ultimate lies between the Chain Ladder and Expected Claims ultimates | G41: =IF(SUMPRODUCT(--(G34:G39<MIN(0)+0))+SUMPRODUCT(--(G34:G39<'S1 Chain Ladder'!F33:F38-0.001)*--(G34:G39<F34:F39-0.001))+SUMPRODUCT(--(G34:G39>'S1 Chain Ladder'!F33:F38+0.001)*--(G34:G39>F34:F39+0.001))=0,"OK","REVIEW") -> OK
B42: This test is applied accident year by accident year. It need not hold for the column totals, because the ordering of the two comparators changes between years.
B45: Portfolio total - all rating groups
C46: Paid to date (£000) | G46: Ultimate claims (£000) | H46: Reserve (£000)
B47: Total | C47: =C14+C27+C40 -> 31994.13 | G47: =G14+G27+G40 -> 42555.213 | H47: =H14+H27+H40 -> 10561.083

Sheet Extension
B1: Extension Scenario - tail factor and claims inflation shock
B2: Instruction of the Chief Actuary dated 12 February 2026: recognise claims development beyond the observed 72 months by way of a tail factor, and apply an additional rate of claims inflation to all amounts still unpaid at the reserving date. The instruction is applied to all three base scenarios so that the effect can be compared on a consistent footing.
B3: Setting Ext_shock to zero and every Ext_tail to 1.0000 on the Parameters sheet reproduces the base scenarios exactly; check C7 on the Checks sheet relies on this.
B6: Group A - Light commercial vehicles
B7: Step E1 - revised development factors
B8: Development age (months) | C8: 12 | D8: 24 | E8: 36 | F8: 48 | G8: 60 | H8: 72 | I8: Tail
B9: Base CDF (no tail) | C9: ='Dev Factors'!C15 -> 2.395581 | D9: ='Dev Factors'!D15 -> 1.443042 | E9: ='Dev Factors'!E15 -> 1.1831621 | F9: ='Dev Factors'!F15 -> 1.0792166 | G9: ='Dev Factors'!G15 -> 1.0374904 | H9: ='Dev Factors'!H15 -> 1
B10: Tail factor beyond 72 months | C10: =INDEX(Ext_tail,1) -> 1.012
B11: Revised CDF (base x tail) | C11: =C9*$C$10 -> 2.424328 | D11: =D9*$C$10 -> 1.4603586 | E11: =E9*$C$10 -> 1.1973601 | F11: =F9*$C$10 -> 1.0921672 | G11: =G9*$C$10 -> 1.0499403 | H11: =H9*$C$10 -> 1.012
B12: % of ultimate paid - revised | C12: =1/C11 -> 0.41248544 | D12: =1/D11 -> 0.68476334 | E12: =1/E11 -> 0.83517066 | F12: =1/F11 -> 0.91561073 | G12: =1/G11 -> 0.95243512 | H12: =1/H11 -> 0.98814229
B13: Incremental % paid in the period | D13: =D12-C12 -> 0.2722779 | E13: =E12-D12 -> 0.15040732 | F13: =F12-E12 -> 0.080440069 | G13: =G12-F12 -> 0.036824384 | H13: =H12-G12 -> 0.035707177 | I13: =1-H12 -> 0.011857708
B15: Step E2 - average lag of the remaining payments and the resulting inflation uplift
B16: Contribution of each future period to the weighted average lag, measured in years from the reserving date. Payments are assumed to fall at the end of each development period.
B17: Accident year | C17: Dev age (months) | D17: % paid to date | E17: % still unpaid | F17: Lag wt 24 | G17: Lag wt 36 | H17: Lag wt 48 | I17: Lag wt 60 | J17: Lag wt 72 | K17: Lag wt tail | L17: Weighted total | M17: Average lag (yrs) | N17: Uplift factor
B18: 2020 | C18: 72 | D18: =H$12 -> 0.98814229 | E18: =1-D18 -> 0.011857708 | F18: 0 | G18: 0 | H18: 0 | I18: 0 | J18: 0 | K18: =$I$13*(0+Ext_taillag) -> 0.035573123 | L18: =SUM(F18:K18) -> 0.035573123 | M18: =L18/E18 -> 3 | N18: =(1+Ext_shock)^M18 -> 1.124864
B19: 2021 | C19: 60 | D19: =G$12 -> 0.95243512 | E19: =1-D19 -> 0.047564884 | F19: 0 | G19: 0 | H19: 0 | I19: 0 | J19: =H$13*1 -> 0.035707177 | K19: =$I$13*(1+Ext_taillag) -> 0.04743083 | L19: =SUM(F19:K19) -> 0.083138007 | M19: =L19/E19 -> 1.7478862 | N19: =(1+Ext_shock)^M19 -> 1.0709578
B20: 2022 | C20: 48 | D20: =F$12 -> 0.91561073 | E20: =1-D20 -> 0.084389269 | F20: 0 | G20: 0 | H20: 0 | I20: =G$13*1 -> 0.036824384 | J20: =H$13*2 -> 0.071414354 | K20: =$I$13*(2+Ext_taillag) -> 0.059288538 | L20: =SUM(F20:K20) -> 0.16752728 | M20: =L20/E20 -> 1.9851727 | N20: =(1+Ext_shock)^M20 -> 1.0809712
B21: 2023 | C21: 36 | D21: =E$12 -> 0.83517066 | E21: =1-D21 -> 0.16482934 | F21: 0 | G21: 0 | H21: =F$13*1 -> 0.080440069 | I21: =G$13*2 -> 0.073648769 | J21: =H$13*3 -> 0.10712153 | K21: =$I$13*(3+Ext_taillag) -> 0.071146245 | L21: =SUM(F21:K21) -> 0.33235661 | M21: =L21/E21 -> 2.0163681 | N21: =(1+Ext_shock)^M21 -> 1.0822946
B22: 2024 | C22: 24 | D22: =D$12 -> 0.68476334 | E22: =1-D22 -> 0.31523666 | F22: 0 | G22: =E$13*1 -> 0.15040732 | H22: =F$13*2 -> 0.16088014 | I22: =G$13*3 -> 0.11047315 | J22: =H$13*4 -> 0.14282871 | K22: =$I$13*(4+Ext_taillag) -> 0.083003953 | L22: =SUM(F22:K22) -> 0.64759327 | M22: =L22/E22 -> 2.0543083 | N22: =(1+Ext_shock)^M22 -> 1.0839063
B23: 2025 | C23: 12 | D23: =C$12 -> 0.41248544 | E23: =1-D23 -> 0.58751456 | F23: =D$13*1 -> 0.2722779 | G23: =E$13*2 -> 0.30081465 | H23: =F$13*3 -> 0.24132021 | I23: =G$13*4 -> 0.14729754 | J23: =H$13*5 -> 0.17853588 | K23: =$I$13*(5+Ext_taillag) -> 0.09486166 | L23: =SUM(F23:K23) -> 1.2351078 | M23: =L23/E23 -> 2.1022591 | N23: =(1+Ext_shock)^M23 -> 1.0859467
B26: Step E3 - revised a priori loss ratio (the tail also raises the ultimates that feed the experience indication)
B27: Accident year | C27: Paid to date (£000) | D27: Revised CDF | E27: Revised CL ultimate (£000) | F27: Trend factor | G27: Trended ultimate (£000) | H27: On-level premium (£000) | I27: Include
B28: 2020 | C28: ='S1 Chain Ladder'!D7 -> 2432.5 | D28: =H$11 -> 1.012 | E28: =C28*D28 -> 2461.69 | F28: ='On-Level & Cred'!H8 -> 1.30696 | G28: =E28*F28 -> 3217.3304 | H28: ='On-Level & Cred'!G8 -> 4904.6517 | I28: ='On-Level & Cred'!K8 -> 1
B29: 2021 | C29: ='S1 Chain Ladder'!D8 -> 2437.7 | D29: =G$11 -> 1.0499403 | E29: =C29*D29 -> 2559.4394 | F29: ='On-Level & Cred'!H9 -> 1.2388247 | G29: =E29*F29 -> 3170.6967 | H29: ='On-Level & Cred'!G9 -> 5275.7312 | I29: ='On-Level & Cred'!K9 -> 1
B30: 2022 | C30: ='S1 Chain Ladder'!D9 -> 2898.3299 | D30: =F$11 -> 1.0921672 | E30: =C30*D30 -> 3165.4608 | F30: ='On-Level & Cred'!H10 -> 1.1742414 | G30: =E30*F30 -> 3717.0151 | H30: ='On-Level & Cred'!G10 -> 5399.5691 | I30: ='On-Level & Cred'!K10 -> 1
B31: 2023 | C31: ='S1 Chain Ladder'!D10 -> 2705.1 | D31: =E$11 -> 1.1973601 | E31: =C31*D31 -> 3238.9787 | F31: ='On-Level & Cred'!H11 -> 1.113025 | G31: =E31*F31 -> 3605.0643 | H31: ='On-Level & Cred'!G11 -> 5451.8625 | I31: ='On-Level & Cred'!K11 -> 0
B32: 2024 | C32: ='S1 Chain Ladder'!D11 -> 2305.4 | D32: =D$11 -> 1.4603586 | E32: =C32*D32 -> 3366.7106 | F32: ='On-Level & Cred'!H12 -> 1.055 | G32: =E32*F32 -> 3551.8797 | H32: ='On-Level & Cred'!G12 -> 5537.25 | I32: ='On-Level & Cred'!K12 -> 0
B33: 2025 | C33: ='S1 Chain Ladder'!D12 -> 1525.9 | D33: =C$11 -> 2.424328 | E33: =C33*D33 -> 3699.2821 | F33: ='On-Level & Cred'!H13 -> 1 | G33: =E33*F33 -> 3699.2821 | H33: ='On-Level & Cred'!G13 -> 5700 | I33: ='On-Level & Cred'!K13 -> 0
B35: Revised experience indication | C35: =SUMPRODUCT($I$28:$I$33,$G$28:$G$33)/SUMPRODUCT($I$28:$I$33,$H$28:$H$33) -> 0.64859264
B36: Credibility factor Z (unchanged - claim counts are unaffected) | C36: ='On-Level & Cred'!C21 -> 0.93207379
B37: Business plan loss ratio | C37: ='On-Level & Cred'!C22 -> 0.62
B38: Revised a priori loss ratio | C38: =C36*C35+(1-C36)*C37 -> 0.64665045
B41: Step E4 - revised ultimates under all three base scenarios
B42: The tail factor is applied first, then the inflation uplift is applied to the amount still unpaid. Where a method already implies a negative unpaid amount the uplift is not applied, since inflating a negative balance would be meaningless.
B43: Accident year | C43: Paid to date (£000) | D43: Uplift factor | E43: CL after tail | F43: EC after tail | G43: BF after tail | H43: CL final (£000) | I43: EC final (£000) | J43: BF final (£000) | K43: CL reserve | L43: EC reserve | M43: BF reserve
B44: 2020 | C44: =C28 -> 2432.5 | D44: =N18 -> 1.124864 | E44: =E28 -> 2461.69 | F44: ='On-Level & Cred'!G8*$C$38/'On-Level & Cred'!H8 -> 2426.6964 | G44: =C44+F44*(1-1/D28) -> 2461.2751 | H44: =C44+(E44-C44)*IF(E44>C44,$D44,1) -> 2465.3348 | I44: =C44+(F44-C44)*IF(F44>C44,$D44,1) -> 2426.6964 | J44: =C44+(G44-C44)*IF(G44>C44,$D44,1) -> 2464.868 | K44: =H44-C44 -> 32.83478 | L44: =I44-C44 -> -5.8035683 | M44: =J44-C44 -> 32.368025
B45: 2021 | C45: =C29 -> 2437.7 | D45: =N19 -> 1.0709578 | E45: =E29 -> 2559.4394 | F45: ='On-Level & Cred'!G9*$C$38/'On-Level & Cred'!H9 -> 2753.8634 | G45: =C45+F45*(1-1/D29) -> 2568.6872 | H45: =C45+(E45-C45)*IF(E45>C45,$D45,1) -> 2568.0778 | I45: =C45+(F45-C45)*IF(F45>C45,$D45,1) -> 2776.2977 | J45: =C45+(G45-C45)*IF(G45>C45,$D45,1) -> 2577.9818 | K45: =H45-C45 -> 130.3778 | L45: =I45-C45 -> 338.59769 | M45: =J45-C45 -> 140.28175
B46: 2022 | C46: =C30 -> 2898.3299 | D46: =N20 -> 1.0809712 | E46: =E30 -> 3165.4608 | F46: ='On-Level & Cred'!G10*$C$38/'On-Level & Cred'!H10 -> 2973.523 | G46: =C46+F46*(1-1/D30) -> 3149.2633 | H46: =C46+(E46-C46)*IF(E46>C46,$D46,1) -> 3187.0907 | I46: =C46+(F46-C46)*IF(F46>C46,$D46,1) -> 2979.6115 | J46: =C46+(G46-C46)*IF(G46>C46,$D46,1) -> 3169.5817 | K46: =H46-C46 -> 288.76083 | L46: =I46-C46 -> 81.281632 | M46: =J46-C46 -> 271.25181
B47: 2023 | C47: =C31 -> 2705.1 | D47: =N21 -> 1.0822946 | E47: =E31 -> 3238.9787 | F47: ='On-Level & Cred'!G11*$C$38/'On-Level & Cred'!H11 -> 3167.4485 | G47: =C47+F47*(1-1/D31) -> 3227.1884 | H47: =C47+(E47-C47)*IF(E47>C47,$D47,1) -> 3282.914 | I47: =C47+(F47-C47)*IF(F47>C47,$D47,1) -> 3205.4972 | J47: =C47+(G47-C47)*IF(G47>C47,$D47,1) -> 3270.1535 | K47: =H47-C47 -> 577.81404 | L47: =I47-C47 -> 500.39722 | M47: =J47-C47 -> 565.05348
B48: 2024 | C48: =C32 -> 2305.4 | D48: =N22 -> 1.0839063 | E48: =E32 -> 3366.7106 | F48: ='On-Level & Cred'!G12*$C$38/'On-Level & Cred'!H12 -> 3393.9954 | G48: =C48+F48*(1-1/D32) -> 3375.3118 | H48: =C48+(E48-C48)*IF(E48>C48,$D48,1) -> 3455.7612 | I48: =C48+(F48-C48)*IF(F48>C48,$D48,1) -> 3485.3354 | J48: =C48+(G48-C48)*IF(G48>C48,$D48,1) -> 3465.0841 | K48: =H48-C48 -> 1150.3612 | L48: =I48-C48 -> 1179.9354 | M48: =J48-C48 -> 1159.6841
B49: 2025 | C49: =C33 -> 1525.9 | D49: =N23 -> 1.0859467 | E49: =E33 -> 3699.2821 | F49: ='On-Level & Cred'!G13*$C$38/'On-Level & Cred'!H13 -> 3685.9075 | G49: =C49+F49*(1-1/D33) -> 3691.4243 | H49: =C49+(E49-C49)*IF(E49>C49,$D49,1) -> 3886.077 | I49: =C49+(F49-C49)*IF(F49>C49,$D49,1) -> 3871.553 | J49: =C49+(G49-C49)*IF(G49>C49,$D49,1) -> 3877.5439 | K49: =H49-C49 -> 2360.177 | L49: =I49-C49 -> 2345.653 | M49: =J49-C49 -> 2351.6439
B50: Total | C50: =SUM(C44:C49) -> 14304.93 | H50: =SUM(H44:H49) -> 18845.256 | I50: =SUM(I44:I49) -> 18744.991 | J50: =SUM(J44:J49) -> 18825.213 | K50: =SUM(K44:K49) -> 4540.3257 | L50: =SUM(L44:L49) -> 4440.0614 | M50: =SUM(M44:M49) -> 4520.2831
B51: Check: every extension ultimate is at least the corresponding base ultimate | H51: =IF(SUMPRODUCT(--(H44:H49<'S1 Chain Ladder'!F7:F12-0.001))+SUMPRODUCT(--(I44:I49<'S2 Expected Claims'!F8:F13-0.001))+SUMPRODUCT(--(J44:J49<'S3 BF'!G8:G13-0.001))=0,"OK","REVIEW") -> OK
B55: Group B - Heavy goods vehicles
B56: Step E1 - revised development factors
B57: Development age (months) | C57: 12 | D57: 24 | E57: 36 | F57: 48 | G57: 60 | H57: 72 | I57: Tail
B58: Base CDF (no tail) | C58: ='Dev Factors'!C30 -> 2.9980001 | D58: ='Dev Factors'!D30 -> 1.5673225 | E58: ='Dev Factors'!E30 -> 1.2254031 | F58: ='Dev Factors'!F30 -> 1.1019113 | G58: ='Dev Factors'!G30 -> 1.02 | H58: ='Dev Factors'!H30 -> 1
B59: Tail factor beyond 72 months | C59: =INDEX(Ext_tail,2) -> 1.034
B60: Revised CDF (base x tail) | C60: =C58*$C$59 -> 3.0999321 | D60: =D58*$C$59 -> 1.6206115 | E60: =E58*$C$59 -> 1.2670668 | F60: =F58*$C$59 -> 1.1393763 | G60: =G58*$C$59 -> 1.05468 | H60: =H58*$C$59 -> 1.034
B61: % of ultimate paid - revised | C61: =1/C60 -> 0.32258771 | D61: =1/D60 -> 0.61705104 | E61: =1/E60 -> 0.78922438 | F61: =1/F60 -> 0.87767314 | G61: =1/G60 -> 0.94815489 | H61: =1/H60 -> 0.96711799
B62: Incremental % paid in the period | D62: =D61-C61 -> 0.29446333 | E62: =E61-D61 -> 0.17217334 | F62: =F61-E61 -> 0.088448759 | G62: =G61-F61 -> 0.070481754 | H62: =H61-G61 -> 0.018963098 | I62: =1-H61 -> 0.032882012
B64: Step E2 - average lag of the remaining payments and the resulting inflation uplift
B65: Contribution of each future period to the weighted average lag, measured in years from the reserving date. Payments are assumed to fall at the end of each development period.
B66: Accident year | C66: Dev age (months) | D66: % paid to date | E66: % still unpaid | F66: Lag wt 24 | G66: Lag wt 36 | H66: Lag wt 48 | I66: Lag wt 60 | J66: Lag wt 72 | K66: Lag wt tail | L66: Weighted total | M66: Average lag (yrs) | N66: Uplift factor
B67: 2020 | C67: 72 | D67: =H$61 -> 0.96711799 | E67: =1-D67 -> 0.032882012 | F67: 0 | G67: 0 | H67: 0 | I67: 0 | J67: 0 | K67: =$I$62*(0+Ext_taillag) -> 0.098646035 | L67: =SUM(F67:K67) -> 0.098646035 | M67: =L67/E67 -> 3 | N67: =(1+Ext_shock)^M67 -> 1.124864
B68: 2021 | C68: 60 | D68: =G$61 -> 0.94815489 | E68: =1-D68 -> 0.051845109 | F68: 0 | G68: 0 | H68: 0 | I68: 0 | J68: =H$62*1 -> 0.018963098 | K68: =$I$62*(1+Ext_taillag) -> 0.13152805 | L68: =SUM(F68:K68) -> 0.15049114 | M68: =L68/E68 -> 2.9027067 | N68: =(1+Ext_shock)^M68 -> 1.1205798
B69: 2022 | C69: 48 | D69: =F$61 -> 0.87767314 | E69: =1-D69 -> 0.12232686 | F69: 0 | G69: 0 | H69: 0 | I69: =G$62*1 -> 0.070481754 | J69: =H$62*2 -> 0.037926196 | K69: =$I$62*(2+Ext_taillag) -> 0.16441006 | L69: =SUM(F69:K69) -> 0.27281801 | M69: =L69/E69 -> 2.2302379 | N69: =(1+Ext_shock)^M69 -> 1.0914112
B70: 2023 | C70: 36 | D70: =E$61 -> 0.78922438 | E70: =1-D70 -> 0.21077562 | F70: 0 | G70: 0 | H70: =F$62*1 -> 0.088448759 | I70: =G$62*2 -> 0.14096351 | J70: =H$62*3 -> 0.056889293 | K70: =$I$62*(3+Ext_taillag) -> 0.19729207 | L70: =SUM(F70:K70) -> 0.48359363 | M70: =L70/E70 -> 2.2943528 | N70: =(1+Ext_shock)^M70 -> 1.0941591
B71: 2024 | C71: 24 | D71: =D$61 -> 0.61705104 | E71: =1-D71 -> 0.38294896 | F71: 0 | G71: =E$62*1 -> 0.17217334 | H71: =F$62*2 -> 0.17689752 | I71: =G$62*3 -> 0.21144526 | J71: =H$62*4 -> 0.075852391 | K71: =$I$62*(4+Ext_taillag) -> 0.23017408 | L71: =SUM(F71:K71) -> 0.86654259 | M71: =L71/E71 -> 2.2628148 | N71: =(1+Ext_shock)^M71 -> 1.0928066
B72: 2025 | C72: 12 | D72: =C$61 -> 0.32258771 | E72: =1-D72 -> 0.67741229 | F72: =D$62*1 -> 0.29446333 | G72: =E$62*2 -> 0.34434667 | H72: =F$62*3 -> 0.26534628 | I72: =G$62*4 -> 0.28192702 | J72: =H$62*5 -> 0.094815489 | K72: =$I$62*(5+Ext_taillag) -> 0.26305609 | L72: =SUM(F72:K72) -> 1.5439549 | M72: =L72/E72 -> 2.2791953 | N72: =(1+Ext_shock)^M72 -> 1.0935089
B75: Step E3 - revised a priori loss ratio (the tail also raises the ultimates that feed the experience indication)
B76: Accident year | C76: Paid to date (£000) | D76: Revised CDF | E76: Revised CL ultimate (£000) | F76: Trend factor | G76: Trended ultimate (£000) | H76: On-level premium (£000) | I76: Include
B77: 2020 | C77: ='S1 Chain Ladder'!D20 -> 1851.3 | D77: =H$60 -> 1.034 | E77: =C77*D77 -> 1914.2442 | F77: ='On-Level & Cred'!H30 -> 1.30696 | G77: =E77*F77 -> 2501.8406 | H77: ='On-Level & Cred'!G30 -> 3684.892 | I77: ='On-Level & Cred'!K30 -> 1
B78: 2021 | C78: ='S1 Chain Ladder'!D21 -> 2106.4 | D78: =G$60 -> 1.05468 | E78: =C78*D78 -> 2221.578 | F78: ='On-Level & Cred'!H31 -> 1.2388247 | G78: =E78*F78 -> 2752.1455 | H78: ='On-Level & Cred'!G31 -> 3962.2495 | I78: ='On-Level & Cred'!K31 -> 1
B79: 2022 | C79: ='S1 Chain Ladder'!D22 -> 2119.6 | D79: =F$60 -> 1.1393763 | E79: =C79*D79 -> 2415.0221 | F79: ='On-Level & Cred'!H32 -> 1.1742414 | G79: =E79*F79 -> 2835.8188 | H79: ='On-Level & Cred'!G32 -> 4003.1912 | I79: ='On-Level & Cred'!K32 -> 1
B80: 2023 | C80: ='S1 Chain Ladder'!D23 -> 1982.1 | D80: =E$60 -> 1.2670668 | E80: =C80*D80 -> 2511.4531 | F80: ='On-Level & Cred'!H33 -> 1.113025 | G80: =E80*F80 -> 2795.3101 | H80: ='On-Level & Cred'!G33 -> 3986.675 | I80: ='On-Level & Cred'!K33 -> 0
B81: 2024 | C81: ='S1 Chain Ladder'!D24 -> 1694.4 | D81: =D$60 -> 1.6206115 | E81: =C81*D81 -> 2745.9641 | F81: ='On-Level & Cred'!H34 -> 1.055 | G81: =E81*F81 -> 2896.9921 | H81: ='On-Level & Cred'!G34 -> 4023.25 | I81: ='On-Level & Cred'!K34 -> 0
B82: 2025 | C82: ='S1 Chain Ladder'!D25 -> 907 | D82: =C$60 -> 3.0999321 | E82: =C82*D82 -> 2811.6384 | F82: ='On-Level & Cred'!H35 -> 1 | G82: =E82*F82 -> 2811.6384 | H82: ='On-Level & Cred'!G35 -> 4150 | I82: ='On-Level & Cred'!K35 -> 0
B84: Revised experience indication | C84: =SUMPRODUCT($I$77:$I$82,$G$77:$G$82)/SUMPRODUCT($I$77:$I$82,$H$77:$H$82) -> 0.69438403
B85: Credibility factor Z (unchanged - claim counts are unaffected) | C85: ='On-Level & Cred'!C43 -> 0.64490037
B86: Business plan loss ratio | C86: ='On-Level & Cred'!C44 -> 0.7
B87: Revised a priori loss ratio | C87: =C85*C84+(1-C85)*C86 -> 0.69637826
B90: Step E4 - revised ultimates under all three base scenarios
B91: The tail factor is applied first, then the inflation uplift is applied to the amount still unpaid. Where a method already implies a negative unpaid amount the uplift is not applied, since inflating a negative balance would be meaningless.
B92: Accident year | C92: Paid to date (£000) | D92: Uplift factor | E92: CL after tail | F92: EC after tail | G92: BF after tail | H92: CL final (£000) | I92: EC final (£000) | J92: BF final (£000) | K92: CL reserve | L92: EC reserve | M92: BF reserve
B93: 2020 | C93: =C77 -> 1851.3 | D93: =N67 -> 1.124864 | E93: =E77 -> 1914.2442 | F93: ='On-Level & Cred'!G30*$C$87/'On-Level & Cred'!H30 -> 1963.395 | G93: =C93+F93*(1-1/D77) -> 1915.8604 | H93: =C93+(E93-C93)*IF(E93>C93,$D93,1) -> 1922.1037 | I93: =C93+(F93-C93)*IF(F93>C93,$D93,1) -> 1977.3916 | J93: =C93+(G93-C93)*IF(G93>C93,$D93,1) -> 1923.9216 | K93: =H93-C93 -> 70.803665 | L93: =I93-C93 -> 126.09159 | M93: =J93-C93 -> 72.621643
B94: 2021 | C94: =C78 -> 2106.4 | D94: =N68 -> 1.1205798 | E94: =E78 -> 2221.578 | F94: ='On-Level & Cred'!G31*$C$87/'On-Level & Cred'!H31 -> 2227.2921 | G94: =C94+F94*(1-1/D78) -> 2221.8742 | H94: =C94+(E94-C94)*IF(E94>C94,$D94,1) -> 2235.4661 | I94: =C94+(F94-C94)*IF(F94>C94,$D94,1) -> 2241.8693 | J94: =C94+(G94-C94)*IF(G94>C94,$D94,1) -> 2235.7981 | K94: =H94-C94 -> 129.06609 | L94: =I94-C94 -> 135.46928 | M94: =J94-C94 -> 129.39806
B95: 2022 | C95: =C79 -> 2119.6 | D95: =N69 -> 1.0914112 | E95: =E79 -> 2415.0221 | F95: ='On-Level & Cred'!G32*$C$87/'On-Level & Cred'!H32 -> 2374.0735 | G95: =C95+F95*(1-1/D79) -> 2410.013 | H95: =C95+(E95-C95)*IF(E95>C95,$D95,1) -> 2442.027 | I95: =C95+(F95-C95)*IF(F95>C95,$D95,1) -> 2397.3352 | J95: =C95+(G95-C95)*IF(G95>C95,$D95,1) -> 2436.56 | K95: =H95-C95 -> 322.42696 | L95: =I95-C95 -> 277.73522 | M95: =J95-C95 -> 316.95996
B96: 2023 | C96: =C80 -> 1982.1 | D96: =N70 -> 1.0941591 | E96: =E80 -> 2511.4531 | F96: ='On-Level & Cred'!G33*$C$87/'On-Level & Cred'!H33 -> 2494.314 | G96: =C96+F96*(1-1/D80) -> 2507.8406 | H96: =C96+(E96-C96)*IF(E96>C96,$D96,1) -> 2561.2965 | I96: =C96+(F96-C96)*IF(F96>C96,$D96,1) -> 2542.5436 | J96: =C96+(G96-C96)*IF(G96>C96,$D96,1) -> 2557.3439 | K96: =H96-C96 -> 579.19652 | L96: =I96-C96 -> 560.44358 | M96: =J96-C96 -> 575.24385
B97: 2024 | C97: =C81 -> 1694.4 | D97: =N71 -> 1.0928066 | E97: =E81 -> 2745.9641 | F97: ='On-Level & Cred'!G34*$C$87/'On-Level & Cred'!H34 -> 2655.6434 | G97: =C97+F97*(1-1/D81) -> 2711.3759 | H97: =C97+(E97-C97)*IF(E97>C97,$D97,1) -> 2843.5561 | I97: =C97+(F97-C97)*IF(F97>C97,$D97,1) -> 2744.8531 | J97: =C97+(G97-C97)*IF(G97>C97,$D97,1) -> 2805.7579 | K97: =H97-C97 -> 1149.1561 | L97: =I97-C97 -> 1050.4531 | M97: =J97-C97 -> 1111.3579
B98: 2025 | C98: =C82 -> 907 | D98: =N72 -> 1.0935089 | E98: =E82 -> 2811.6384 | F98: ='On-Level & Cred'!G35*$C$87/'On-Level & Cred'!H35 -> 2889.9698 | G98: =C98+F98*(1-1/D82) -> 2864.701 | H98: =C98+(E98-C98)*IF(E98>C98,$D98,1) -> 2989.739 | I98: =C98+(F98-C98)*IF(F98>C98,$D98,1) -> 3075.395 | J98: =C98+(G98-C98)*IF(G98>C98,$D98,1) -> 3047.7634 | K98: =H98-C98 -> 2082.739 | L98: =I98-C98 -> 2168.395 | M98: =J98-C98 -> 2140.7634
B99: Total | C99: =SUM(C93:C98) -> 10660.8 | H99: =SUM(H93:H98) -> 14994.188 | I99: =SUM(I93:I98) -> 14979.388 | J99: =SUM(J93:J98) -> 15007.145 | K99: =SUM(K93:K98) -> 4333.3883 | L99: =SUM(L93:L98) -> 4318.5878 | M99: =SUM(M93:M98) -> 4346.3449
B100: Check: every extension ultimate is at least the corresponding base ultimate | H100: =IF(SUMPRODUCT(--(H93:H98<'S1 Chain Ladder'!F20:F25-0.001))+SUMPRODUCT(--(I93:I98<'S2 Expected Claims'!F21:F26-0.001))+SUMPRODUCT(--(J93:J98<'S3 BF'!G21:G26-0.001))=0,"OK","REVIEW") -> OK
B104: Group C - Specialist haulage
B105: Step E1 - revised development factors
B106: Development age (months) | C106: 12 | D106: 24 | E106: 36 | F106: 48 | G106: 60 | H106: 72 | I106: Tail
B107: Base CDF (no tail) | C107: ='Dev Factors'!C45 -> 3.8476142 | D107: ='Dev Factors'!D45 -> 1.838804 | E107: ='Dev Factors'!E45 -> 1.3708526 | F107: ='Dev Factors'!F45 -> 1.1193434 | G107: ='Dev Factors'!G45 -> 1.0471972 | H107: ='Dev Factors'!H45 -> 1
B108: Tail factor beyond 72 months | C108: =INDEX(Ext_tail,3) -> 1.055
B109: Revised CDF (base x tail) | C109: =C107*$C$108 -> 4.059233 | D109: =D107*$C$108 -> 1.9399382 | E109: =E107*$C$108 -> 1.4462495 | F109: =F107*$C$108 -> 1.1809073 | G109: =G107*$C$108 -> 1.104793 | H109: =H107*$C$108 -> 1.055
B110: % of ultimate paid - revised | C110: =1/C109 -> 0.24635196 | D110: =1/D109 -> 0.51548034 | E110: =1/E109 -> 0.69144362 | F110: =1/F109 -> 0.84680651 | G110: =1/G109 -> 0.90514693 | H110: =1/H109 -> 0.9478673
B111: Incremental % paid in the period | D111: =D110-C110 -> 0.26912839 | E111: =E110-D110 -> 0.17596327 | F111: =F110-E110 -> 0.1553629 | G111: =G110-F110 -> 0.058340415 | H111: =H110-G110 -> 0.042720369 | I111: =1-H110 -> 0.052132701
B113: Step E2 - average lag of the remaining payments and the resulting inflation uplift
B114: Contribution of each future period to the weighted average lag, measured in years from the reserving date. Payments are assumed to fall at the end of each development period.
B115: Accident year | C115: Dev age (months) | D115: % paid to date | E115: % still unpaid | F115: Lag wt 24 | G115: Lag wt 36 | H115: Lag wt 48 | I115: Lag wt 60 | J115: Lag wt 72 | K115: Lag wt tail | L115: Weighted total | M115: Average lag (yrs) | N115: Uplift factor
B116: 2020 | C116: 72 | D116: =H$110 -> 0.9478673 | E116: =1-D116 -> 0.052132701 | F116: 0 | G116: 0 | H116: 0 | I116: 0 | J116: 0 | K116: =$I$111*(0+Ext_taillag) -> 0.1563981 | L116: =SUM(F116:K116) -> 0.1563981 | M116: =L116/E116 -> 3 | N116: =(1+Ext_shock)^M116 -> 1.124864
B117: 2021 | C117: 60 | D117: =G$110 -> 0.90514693 | E117: =1-D117 -> 0.09485307 | F117: 0 | G117: 0 | H117: 0 | I117: 0 | J117: =H$111*1 -> 0.042720369 | K117: =$I$111*(1+Ext_taillag) -> 0.20853081 | L117: =SUM(F117:K117) -> 0.25125117 | M117: =L117/E117 -> 2.648846 | N117: =(1+Ext_shock)^M117 -> 1.109478
B118: 2022 | C118: 48 | D118: =F$110 -> 0.84680651 | E118: =1-D118 -> 0.15319349 | F118: 0 | G118: 0 | H118: 0 | I118: =G$111*1 -> 0.058340415 | J118: =H$111*2 -> 0.085440738 | K118: =$I$111*(2+Ext_taillag) -> 0.26066351 | L118: =SUM(F118:K118) -> 0.40444466 | M118: =L118/E118 -> 2.6400905 | N118: =(1+Ext_shock)^M118 -> 1.1090971
B119: 2023 | C119: 36 | D119: =E$110 -> 0.69144362 | E119: =1-D119 -> 0.30855638 | F119: 0 | G119: 0 | H119: =F$111*1 -> 0.1553629 | I119: =G$111*2 -> 0.11668083 | J119: =H$111*3 -> 0.12816111 | K119: =$I$111*(3+Ext_taillag) -> 0.31279621 | L119: =SUM(F119:K119) -> 0.71300104 | M119: =L119/E119 -> 2.3107642 | N119: =(1+Ext_shock)^M119 -> 1.0948636
B120: 2024 | C120: 24 | D120: =D$110 -> 0.51548034 | E120: =1-D120 -> 0.48451966 | F120: 0 | G120: =E$111*1 -> 0.17596327 | H120: =F$111*2 -> 0.3107258 | I120: =G$111*3 -> 0.17502124 | J120: =H$111*4 -> 0.17088148 | K120: =$I$111*(4+Ext_taillag) -> 0.36492891 | L120: =SUM(F120:K120) -> 1.1975207 | M120: =L120/E120 -> 2.4715627 | N120: =(1+Ext_shock)^M120 -> 1.1017904
B121: 2025 | C121: 12 | D121: =C$110 -> 0.24635196 | E121: =1-D121 -> 0.75364804 | F121: =D$111*1 -> 0.26912839 | G121: =E$111*2 -> 0.35192654 | H121: =F$111*3 -> 0.4660887 | I121: =G$111*4 -> 0.23336166 | J121: =H$111*5 -> 0.21360184 | K121: =$I$111*(5+Ext_taillag) -> 0.41706161 | L121: =SUM(F121:K121) -> 1.9511687 | M121: =L121/E121 -> 2.5889654 | N121: =(1+Ext_shock)^M121 -> 1.1068754
...

Sheet ADC
B1: Adverse Development Cover - layer analysis and break-even claims inflation
B2: The reinsurer has offered an Adverse Development Cover attaching above the booked reserve for the whole account, sized to whichever reserving basis is booked. Because the three bases produce different reserves, each would in practice be attached by a differently sized cover. This sheet values the cover under all three bases side by side, so the reserving committee can see how the choice of basis itself changes the reinsurance economics, and then highlights the figures for whichever basis is recommended.
B5: Layer structure and outcome, by reserving basis
B6: Each column is self-contained: its own booked reserve, its own attachment and exhaustion points, and its own outcome against the extension scenario. Figures are not comparable to a single shared layer, because each basis would in practice be reinsured on its own terms.
C8: Chain Ladder | D8: Expected Claims | E8: Bornhuetter-Ferguson
B9: Booked reserve, base scenario (£000) | C9: ='S1 Chain Ladder'!G46 -> 10337.251 | D9: ='S2 Expected Claims'!H47 -> 10572.332 | E9: ='S3 BF'!H47 -> 10561.083
B10: Attachment point (£000) | C10: =C9*ADC_att -> 10854.114 | D10: =D9*ADC_att -> 11100.948 | E10: =E9*ADC_att -> 11089.137
B11: Exhaustion point (£000) | C11: =C9*ADC_exh -> 13438.427 | D11: =D9*ADC_exh -> 13744.031 | E11: =E9*ADC_exh -> 13729.408
B12: Limit of cover (£000) | C12: =C11-C10 -> 2584.3128 | D12: =D11-D10 -> 2643.0829 | E12: =E11-E10 -> 2640.2708
B13: Reinsurance premium payable (£000) | C13: =C12*ADC_rol -> 310.11754 | D13: =D12*ADC_rol -> 317.16995 | E13: =E12*ADC_rol -> 316.8325
B14: Extension scenario reserve (£000) | C14: =Extension!K155 -> 12668.993 | D14: =Extension!L155 -> 12384.548 | E14: =Extension!M155 -> 12755.646
B15: Recovery under the extension scenario (£000) | C15: =MIN(MAX(C14-C10,0),C12) -> 1814.8788 | D15: =MIN(MAX(D14-D10,0),D12) -> 1283.5995 | E15: =MIN(MAX(E14-E10,0),E12) -> 1666.509
B16: Net benefit of the cover (£000) | C16: =C15-C13 -> 1504.7612 | D16: =D15-D13 -> 966.42953 | E16: =E15-E13 -> 1349.6765
B17: Check: recovery does not exceed the limit of cover, and is not negative, for any basis | C17: =IF(SUMPRODUCT(--(C15:E15>C12:E12+0.001))+SUMPRODUCT(--(C15:E15<-0.001))=0,"OK","REVIEW") -> OK
B20: Recommended basis for booking
B21: Recommended basis for booking | C21: Bornhuetter-Ferguson
B22: Enter one of: Chain Ladder / Expected Claims / Bornhuetter-Ferguson
B23: The figures below look up the matching column from the table above using INDEX and MATCH: MATCH finds which row of the table the metric named in column B corresponds to, and separately which column matches the basis named above; INDEX then returns the single cell where that row and column intersect.
B25: Booked reserve, base scenario (£000) | C25: =INDEX($C$9:$E$16,MATCH($B25,$B$9:$B$16,0),MATCH($C$21,$C$8:$E$8,0)) -> 10561.083
B26: Attachment point (£000) | C26: =INDEX($C$9:$E$16,MATCH($B26,$B$9:$B$16,0),MATCH($C$21,$C$8:$E$8,0)) -> 11089.137
B27: Exhaustion point (£000) | C27: =INDEX($C$9:$E$16,MATCH($B27,$B$9:$B$16,0),MATCH($C$21,$C$8:$E$8,0)) -> 13729.408
B28: Limit of cover (£000) | C28: =INDEX($C$9:$E$16,MATCH($B28,$B$9:$B$16,0),MATCH($C$21,$C$8:$E$8,0)) -> 2640.2708
B29: Reinsurance premium payable (£000) | C29: =INDEX($C$9:$E$16,MATCH($B29,$B$9:$B$16,0),MATCH($C$21,$C$8:$E$8,0)) -> 316.8325
B30: Extension scenario reserve (£000) | C30: =INDEX($C$9:$E$16,MATCH($B30,$B$9:$B$16,0),MATCH($C$21,$C$8:$E$8,0)) -> 12755.646
B31: Recovery under the extension scenario (£000) | C31: =INDEX($C$9:$E$16,MATCH($B31,$B$9:$B$16,0),MATCH($C$21,$C$8:$E$8,0)) -> 1666.509
B32: Net benefit of the cover (£000) | C32: =INDEX($C$9:$E$16,MATCH($B32,$B$9:$B$16,0),MATCH($C$21,$C$8:$E$8,0)) -> 1349.6765
B35: Sensitivity of the reserve to the rate of additional claims inflation, by basis
B36: Neither the a priori loss ratio nor the tail factor depends on the inflation shock, and nor does the average payment lag. The reserve at any shock rate can therefore be written directly, for each basis, as the sum across accident years and rating groups of the unpaid amount after the tail (floored at zero, since a method that already implies a negative unpaid balance is not inflated further) accumulated at one plus the shock raised to the average lag. This is evaluated for all three bases in parallel, so the guard against a negative unpaid balance is applied uniformly rather than relying on it never binding for one basis only.
B38: Additional claims inflation | C38: Chain Ladder reserve (£000) | D38: Expected Claims reserve (£000) | E38: Bornhuetter-Ferguson reserve (£000) | J38: Recommended attachment | K38: Recommended exhaustion
B39: 0 | C39: =SUMPRODUCT((Extension!E44:E49-Extension!C44:C49>0)*(Extension!E44:E49-Extension!C44:C49)*(1+$B39)^Extension!M18:M23)+SUMPRODUCT((Extension!E93:E98-Extension!C93:C98>0)*(Extension!E93:E98-Extension!C93:C98)*(1+$B39)^Extension!M67:M72)+SUMPRODUCT((Extension!E142:E147-Extension!C142:C147>0)*(Extension!E142:E147-Extension!C142:C147)*(1+$B39)^Extension!M116:M121) -> 11582.846 | D39: =SUMPRODUCT((Extension!F44:F49-Extension!C44:C49>0)*(Extension!F44:F49-Extension!C44:C49)*(1+$B39)^Extension!M18:M23)+SUMPRODUCT((Extension!F93:F98-Extension!C93:C98>0)*(Extension!F93:F98-Extension!C93:C98)*(1+$B39)^Extension!M67:M72)+SUMPRODUCT((Extension!F142:F147-Extension!C142:C147>0)*(Extension!F142:F147-Extension!C142:C147)*(1+$B39)^Extension!M116:M121) -> 11330.66 | E39: =SUMPRODUCT((Extension!G44:G49-Extension!C44:C49>0)*(Extension!G44:G49-Extension!C44:C49)*(1+$B39)^Extension!M18:M23)+SUMPRODUCT((Extension!G93:G98-Extension!C93:C98>0)*(Extension!G93:G98-Extension!C93:C98)*(1+$B39)^Extension!M67:M72)+SUMPRODUCT((Extension!G142:G147-Extension!C142:C147>0)*(Extension!G142:G147-Extension!C142:C147)*(1+$B39)^Extension!M116:M121) -> 11660.758 | J39: =$C$26 -> 11089.137 | K39: =$C$27 -> 13729.408
B40: 0.0025 | C40: =SUMPRODUCT((Extension!E44:E49-Extension!C44:C49>0)*(Extension!E44:E49-Extension!C44:C49)*(1+$B40)^Extension!M18:M23)+SUMPRODUCT((Extension!E93:E98-Extension!C93:C98>0)*(Extension!E93:E98-Extension!C93:C98)*(1+$B40)^Extension!M67:M72)+SUMPRODUCT((Extension!E142:E147-Extension!C142:C147>0)*(Extension!E142:E147-Extension!C142:C147)*(1+$B40)^Extension!M116:M121) -> 11649.102 | D40: =SUMPRODUCT((Extension!F44:F49-Extension!C44:C49>0)*(Extension!F44:F49-Extension!C44:C49)*(1+$B40)^Extension!M18:M23)+SUMPRODUCT((Extension!F93:F98-Extension!C93:C98>0)*(Extension!F93:F98-Extension!C93:C98)*(1+$B40)^Extension!M67:M72)+SUMPRODUCT((Extension!F142:F147-Extension!C142:C147>0)*(Extension!F142:F147-Extension!C142:C147)*(1+$B40)^Extension!M116:M121) -> 11395.308 | E40: =SUMPRODUCT((Extension!G44:G49-Extension!C44:C49>0)*(Extension!G44:G49-Extension!C44:C49)*(1+$B40)^Extension!M18:M23)+SUMPRODUCT((Extension!G93:G98-Extension!C93:C98>0)*(Extension!G93:G98-Extension!C93:C98)*(1+$B40)^Extension!M67:M72)+SUMPRODUCT((Extension!G142:G147-Extension!C142:C147>0)*(Extension!G142:G147-Extension!C142:C147)*(1+$B40)^Extension!M116:M121) -> 11727.544 | J40: =$C$26 -> 11089.137 | K40: =$C$27 -> 13729.408
B41: 0.005 | C41: =SUMPRODUCT((Extension!E44:E49-Extension!C44:C49>0)*(Extension!E44:E49-Extension!C44:C49)*(1+$B41)^Extension!M18:M23)+SUMPRODUCT((Extension!E93:E98-Extension!C93:C98>0)*(Extension!E93:E98-Extension!C93:C98)*(1+$B41)^Extension!M67:M72)+SUMPRODUCT((Extension!E142:E147-Extension!C142:C147>0)*(Extension!E142:E147-Extension!C142:C147)*(1+$B41)^Extension!M116:M121) -> 11715.575 | D41: =SUMPRODUCT((Extension!F44:F49-Extension!C44:C49>0)*(Extension!F44:F49-Extension!C44:C49)*(1+$B41)^Extension!M18:M23)+SUMPRODUCT((Extension!F93:F98-Extension!C93:C98>0)*(Extension!F93:F98-Extension!C93:C98)*(1+$B41)^Extension!M67:M72)+SUMPRODUCT((Extension!F142:F147-Extension!C142:C147>0)*(Extension!F142:F147-Extension!C142:C147)*(1+$B41)^Extension!M116:M121) -> 11460.166 | E41: =SUMPRODUCT((Extension!G44:G49-Extension!C44:C49>0)*(Extension!G44:G49-Extension!C44:C49)*(1+$B41)^Extension!M18:M23)+SUMPRODUCT((Extension!G93:G98-Extension!C93:C98>0)*(Extension!G93:G98-Extension!C93:C98)*(1+$B41)^Extension!M67:M72)+SUMPRODUCT((Extension!G142:G147-Extension!C142:C147>0)*(Extension!G142:G147-Extension!C142:C147)*(1+$B41)^Extension!M116:M121) -> 11794.548 | J41: =$C$26 -> 11089.137 | K41: =$C$27 -> 13729.408
B42: 0.0075 | C42: =SUMPRODUCT((Extension!E44:E49-Extension!C44:C49>0)*(Extension!E44:E49-Extension!C44:C49)*(1+$B42)^Extension!M18:M23)+SUMPRODUCT((Extension!E93:E98-Extension!C93:C98>0)*(Extension!E93:E98-Extension!C93:C98)*(1+$B42)^Extension!M67:M72)+SUMPRODUCT((Extension!E142:E147-Extension!C142:C147>0)*(Extension!E142:E147-Extension!C142:C147)*(1+$B42)^Extension!M116:M121) -> 11782.264 | D42: =SUMPRODUCT((Extension!F44:F49-Extension!C44:C49>0)*(Extension!F44:F49-Extension!C44:C49)*(1+$B42)^Extension!M18:M23)+SUMPRODUCT((Extension!F93:F98-Extension!C93:C98>0)*(Extension!F93:F98-Extension!C93:C98)*(1+$B42)^Extension!M67:M72)+SUMPRODUCT((Extension!F142:F147-Extension!C142:C147>0)*(Extension!F142:F147-Extension!C142:C147)*(1+$B42)^Extension!M116:M121) -> 11525.235 | E42: =SUMPRODUCT((Extension!G44:G49-Extension!C44:C49>0)*(Extension!G44:G49-Extension!C44:C49)*(1+$B42)^Extension!M18:M23)+SUMPRODUCT((Extension!G93:G98-Extension!C93:C98>0)*(Extension!G93:G98-Extension!C93:C98)*(1+$B42)^Extension!M67:M72)+SUMPRODUCT((Extension!G142:G147-Extension!C142:C147>0)*(Extension!G142:G147-Extension!C142:C147)*(1+$B42)^Extension!M116:M121) -> 11861.77 | J42: =$C$26 -> 11089.137 | K42: =$C$27 -> 13729.408
B43: 0.01 | C43: =SUMPRODUCT((Extension!E44:E49-Extension!C44:C49>0)*(Extension!E44:E49-Extension!C44:C49)*(1+$B43)^Extension!M18:M23)+SUMPRODUCT((Extension!E93:E98-Extension!C93:C98>0)*(Extension!E93:E98-Extension!C93:C98)*(1+$B43)^Extension!M67:M72)+SUMPRODUCT((Extension!E142:E147-Extension!C142:C147>0)*(Extension!E142:E147-Extension!C142:C147)*(1+$B43)^Extension!M116:M121) -> 11849.169 | D43: =SUMPRODUCT((Extension!F44:F49-Extension!C44:C49>0)*(Extension!F44:F49-Extension!C44:C49)*(1+$B43)^Extension!M18:M23)+SUMPRODUCT((Extension!F93:F98-Extension!C93:C98>0)*(Extension!F93:F98-Extension!C93:C98)*(1+$B43)^Extension!M67:M72)+SUMPRODUCT((Extension!F142:F147-Extension!C142:C147>0)*(Extension!F142:F147-Extension!C142:C147)*(1+$B43)^Extension!M116:M121) -> 11590.514 | E43: =SUMPRODUCT((Extension!G44:G49-Extension!C44:C49>0)*(Extension!G44:G49-Extension!C44:C49)*(1+$B43)^Extension!M18:M23)+SUMPRODUCT((Extension!G93:G98-Extension!C93:C98>0)*(Extension!G93:G98-Extension!C93:C98)*(1+$B43)^Extension!M67:M72)+SUMPRODUCT((Extension!G142:G147-Extension!C142:C147>0)*(Extension!G142:G147-Extension!C142:C147)*(1+$B43)^Extension!M116:M121) -> 11929.212 | J43: =$C$26 -> 11089.137 | K43: =$C$27 -> 13729.408
B44: 0.0125 | C44: =SUMPRODUCT((Extension!E44:E49-Extension!C44:C49>0)*(Extension!E44:E49-Extension!C44:C49)*(1+$B44)^Extension!M18:M23)+SUMPRODUCT((Extension!E93:E98-Extension!C93:C98>0)*(Extension!E93:E98-Extension!C93:C98)*(1+$B44)^Extension!M67:M72)+SUMPRODUCT((Extension!E142:E147-Extension!C142:C147>0)*(Extension!E142:E147-Extension!C142:C147)*(1+$B44)^Extension!M116:M121) -> 11916.291 | D44: =SUMPRODUCT((Extension!F44:F49-Extension!C44:C49>0)*(Extension!F44:F49-Extension!C44:C49)*(1+$B44)^Extension!M18:M23)+SUMPRODUCT((Extension!F93:F98-Extension!C93:C98>0)*(Extension!F93:F98-Extension!C93:C98)*(1+$B44)^Extension!M67:M72)+SUMPRODUCT((Extension!F142:F147-Extension!C142:C147>0)*(Extension!F142:F147-Extension!C142:C147)*(1+$B44)^Extension!M116:M121) -> 11656.004 | E44: =SUMPRODUCT((Extension!G44:G49-Extension!C44:C49>0)*(Extension!G44:G49-Extension!C44:C49)*(1+$B44)^Extension!M18:M23)+SUMPRODUCT((Extension!G93:G98-Extension!C93:C98>0)*(Extension!G93:G98-Extension!C93:C98)*(1+$B44)^Extension!M67:M72)+SUMPRODUCT((Extension!G142:G147-Extension!C142:C147>0)*(Extension!G142:G147-Extension!C142:C147)*(1+$B44)^Extension!M116:M121) -> 11996.873 | J44: =$C$26 -> 11089.137 | K44: =$C$27 -> 13729.408
B45: 0.015 | C45: =SUMPRODUCT((Extension!E44:E49-Extension!C44:C49>0)*(Extension!E44:E49-Extension!C44:C49)*(1+$B45)^Extension!M18:M23)+SUMPRODUCT((Extension!E93:E98-Extension!C93:C98>0)*(Extension!E93:E98-Extension!C93:C98)*(1+$B45)^Extension!M67:M72)+SUMPRODUCT((Extension!E142:E147-Extension!C142:C147>0)*(Extension!E142:E147-Extension!C142:C147)*(1+$B45)^Extension!M116:M121) -> 11983.63 | D45: =SUMPRODUCT((Extension!F44:F49-Extension!C44:C49>0)*(Extension!F44:F49-Extension!C44:C49)*(1+$B45)^Extension!M18:M23)+SUMPRODUCT((Extension!F93:F98-Extension!C93:C98>0)*(Extension!F93:F98-Extension!C93:C98)*(1+$B45)^Extension!M67:M72)+SUMPRODUCT((Extension!F142:F147-Extension!C142:C147>0)*(Extension!F142:F147-Extension!C142:C147)*(1+$B45)^Extension!M116:M121) -> 11721.705 | E45: =SUMPRODUCT((Extension!G44:G49-Extension!C44:C49>0)*(Extension!G44:G49-Extension!C44:C49)*(1+$B45)^Extension!M18:M23)+SUMPRODUCT((Extension!G93:G98-Extension!C93:C98>0)*(Extension!G93:G98-Extension!C93:C98)*(1+$B45)^Extension!M67:M72)+SUMPRODUCT((Extension!G142:G147-Extension!C142:C147>0)*(Extension!G142:G147-Extension!C142:C147)*(1+$B45)^Extension!M116:M121) -> 12064.752 | J45: =$C$26 -> 11089.137 | K45: =$C$27 -> 13729.408
B46: 0.0175 | C46: =SUMPRODUCT((Extension!E44:E49-Extension!C44:C49>0)*(Extension!E44:E49-Extension!C44:C49)*(1+$B46)^Extension!M18:M23)+SUMPRODUCT((Extension!E93:E98-Extension!C93:C98>0)*(Extension!E93:E98-Extension!C93:C98)*(1+$B46)^Extension!M67:M72)+SUMPRODUCT((Extension!E142:E147-Extension!C142:C147>0)*(Extension!E142:E147-Extension!C142:C147)*(1+$B46)^Extension!M116:M121) -> 12051.186 | D46: =SUMPRODUCT((Extension!F44:F49-Extension!C44:C49>0)*(Extension!F44:F49-Extension!C44:C49)*(1+$B46)^Extension!M18:M23)+SUMPRODUCT((Extension!F93:F98-Extension!C93:C98>0)*(Extension!F93:F98-Extension!C93:C98)*(1+$B46)^Extension!M67:M72)+SUMPRODUCT((Extension!F142:F147-Extension!C142:C147>0)*(Extension!F142:F147-Extension!C142:C147)*(1+$B46)^Extension!M116:M121) -> 11787.616 | E46: =SUMPRODUCT((Extension!G44:G49-Extension!C44:C49>0)*(Extension!G44:G49-Extension!C44:C49)*(1+$B46)^Extension!M18:M23)+SUMPRODUCT((Extension!G93:G98-Extension!C93:C98>0)*(Extension!G93:G98-Extension!C93:C98)*(1+$B46)^Extension!M67:M72)+SUMPRODUCT((Extension!G142:G147-Extension!C142:C147>0)*(Extension!G142:G147-Extension!C142:C147)*(1+$B46)^Extension!M116:M121) -> 12132.851 | J46: =$C$26 -> 11089.137 | K46: =$C$27 -> 13729.408
B47: 0.02 | C47: =SUMPRODUCT((Extension!E44:E49-Extension!C44:C49>0)*(Extension!E44:E49-Extension!C44:C49)*(1+$B47)^Extension!M18:M23)+SUMPRODUCT((Extension!E93:E98-Extension!C93:C98>0)*(Extension!E93:E98-Extension!C93:C98)*(1+$B47)^Extension!M67:M72)+SUMPRODUCT((Extension!E142:E147-Extension!C142:C147>0)*(Extension!E142:E147-Extension!C142:C147)*(1+$B47)^Extension!M116:M121) -> 12118.96 | D47: =SUMPRODUCT((Extension!F44:F49-Extension!C44:C49>0)*(Extension!F44:F49-Extension!C44:C49)*(1+$B47)^Extension!M18:M23)+SUMPRODUCT((Extension!F93:F98-Extension!C93:C98>0)*(Extension!F93:F98-Extension!C93:C98)*(1+$B47)^Extension!M67:M72)+SUMPRODUCT((Extension!F142:F147-Extension!C142:C147>0)*(Extension!F142:F147-Extension!C142:C147)*(1+$B47)^Extension!M116:M121) -> 11853.74 | E47: =SUMPRODUCT((Extension!G44:G49-Extension!C44:C49>0)*(Extension!G44:G49-Extension!C44:C49)*(1+$B47)^Extension!M18:M23)+SUMPRODUCT((Extension!G93:G98-Extension!C93:C98>0)*(Extension!G93:G98-Extension!C93:C98)*(1+$B47)^Extension!M67:M72)+SUMPRODUCT((Extension!G142:G147-Extension!C142:C147>0)*(Extension!G142:G147-Extension!C142:C147)*(1+$B47)^Extension!M116:M121) -> 12201.17 | J47: =$C$26 -> 11089.137 | K47: =$C$27 -> 13729.408
B48: 0.0225 | C48: =SUMPRODUCT((Extension!E44:E49-Extension!C44:C49>0)*(Extension!E44:E49-Extension!C44:C49)*(1+$B48)^Extension!M18:M23)+SUMPRODUCT((Extension!E93:E98-Extension!C93:C98>0)*(Extension!E93:E98-Extension!C93:C98)*(1+$B48)^Extension!M67:M72)+SUMPRODUCT((Extension!E142:E147-Extension!C142:C147>0)*(Extension!E142:E147-Extension!C142:C147)*(1+$B48)^Extension!M116:M121) -> 12186.951 | D48: =SUMPRODUCT((Extension!F44:F49-Extension!C44:C49>0)*(Extension!F44:F49-Extension!C44:C49)*(1+$B48)^Extension!M18:M23)+SUMPRODUCT((Extension!F93:F98-Extension!C93:C98>0)*(Extension!F93:F98-Extension!C93:C98)*(1+$B48)^Extension!M67:M72)+SUMPRODUCT((Extension!F142:F147-Extension!C142:C147>0)*(Extension!F142:F147-Extension!C142:C147)*(1+$B48)^Extension!M116:M121) -> 11920.074 | E48: =SUMPRODUCT((Extension!G44:G49-Extension!C44:C49>0)*(Extension!G44:G49-Extension!C44:C49)*(1+$B48)^Extension!M18:M23)+SUMPRODUCT((Extension!G93:G98-Extension!C93:C98>0)*(Extension!G93:G98-Extension!C93:C98)*(1+$B48)^Extension!M67:M72)+SUMPRODUCT((Extension!G142:G147-Extension!C142:C147>0)*(Extension!G142:G147-Extension!C142:C147)*(1+$B48)^Extension!M116:M121) -> 12269.708 | J48: =$C$26 -> 11089.137 | K48: =$C$27 -> 13729.408
B49: 0.025 | C49: =SUMPRODUCT((Extension!E44:E49-Extension!C44:C49>0)*(Extension!E44:E49-Extension!C44:C49)*(1+$B49)^Extension!M18:M23)+SUMPRODUCT((Extension!E93:E98-Extension!C93:C98>0)*(Extension!E93:E98-Extension!C93:C98)*(1+$B49)^Extension!M67:M72)+SUMPRODUCT((Extension!E142:E147-Extension!C142:C147>0)*(Extension!E142:E147-Extension!C142:C147)*(1+$B49)^Extension!M116:M121) -> 12255.159 | D49: =SUMPRODUCT((Extension!F44:F49-Extension!C44:C49>0)*(Extension!F44:F49-Extension!C44:C49)*(1+$B49)^Extension!M18:M23)+SUMPRODUCT((Extension!F93:F98-Extension!C93:C98>0)*(Extension!F93:F98-Extension!C93:C98)*(1+$B49)^Extension!M67:M72)+SUMPRODUCT((Extension!F142:F147-Extension!C142:C147>0)*(Extension!F142:F147-Extension!C142:C147)*(1+$B49)^Extension!M116:M121) -> 11986.62 | E49: =SUMPRODUCT((Extension!G44:G49-Extension!C44:C49>0)*(Extension!G44:G49-Extension!C44:C49)*(1+$B49)^Extension!M18:M23)+SUMPRODUCT((Extension!G93:G98-Extension!C93:C98>0)*(Extension!G93:G98-Extension!C93:C98)*(1+$B49)^Extension!M67:M72)+SUMPRODUCT((Extension!G142:G147-Extension!C142:C147>0)*(Extension!G142:G147-Extension!C142:C147)*(1+$B49)^Extension!M116:M121) -> 12338.467 | J49: =$C$26 -> 11089.137 | K49: =$C$27 -> 13729.408
B50: 0.0275 | C50: =SUMPRODUCT((Extension!E44:E49-Extension!C44:C49>0)*(Extension!E44:E49-Extension!C44:C49)*(1+$B50)^Extension!M18:M23)+SUMPRODUCT((Extension!E93:E98-Extension!C93:C98>0)*(Extension!E93:E98-Extension!C93:C98)*(1+$B50)^Extension!M67:M72)+SUMPRODUCT((Extension!E142:E147-Extension!C142:C147>0)*(Extension!E142:E147-Extension!C142:C147)*(1+$B50)^Extension!M116:M121) -> 12323.586 | D50: =SUMPRODUCT((Extension!F44:F49-Extension!C44:C49>0)*(Extension!F44:F49-Extension!C44:C49)*(1+$B50)^Extension!M18:M23)+SUMPRODUCT((Extension!F93:F98-Extension!C93:C98>0)*(Extension!F93:F98-Extension!C93:C98)*(1+$B50)^Extension!M67:M72)+SUMPRODUCT((Extension!F142:F147-Extension!C142:C147>0)*(Extension!F142:F147-Extension!C142:C147)*(1+$B50)^Extension!M116:M121) -> 12053.378 | E50: =SUMPRODUCT((Extension!G44:G49-Extension!C44:C49>0)*(Extension!G44:G49-Extension!C44:C49)*(1+$B50)^Extension!M18:M23)+SUMPRODUCT((Extension!G93:G98-Extension!C93:C98>0)*(Extension!G93:G98-Extension!C93:C98)*(1+$B50)^Extension!M67:M72)+SUMPRODUCT((Extension!G142:G147-Extension!C142:C147>0)*(Extension!G142:G147-Extension!C142:C147)*(1+$B50)^Extension!M116:M121) -> 12407.445 | J50: =$C$26 -> 11089.137 | K50: =$C$27 -> 13729.408
B51: 0.03 | C51: =SUMPRODUCT((Extension!E44:E49-Extension!C44:C49>0)*(Extension!E44:E49-Extension!C44:C49)*(1+$B51)^Extension!M18:M23)+SUMPRODUCT((Extension!E93:E98-Extension!C93:C98>0)*(Extension!E93:E98-Extension!C93:C98)*(1+$B51)^Extension!M67:M72)+SUMPRODUCT((Extension!E142:E147-Extension!C142:C147>0)*(Extension!E142:E147-Extension!C142:C147)*(1+$B51)^Extension!M116:M121) -> 12392.23 | D51: =SUMPRODUCT((Extension!F44:F49-Extension!C44:C49>0)*(Extension!F44:F49-Extension!C44:C49)*(1+$B51)^Extension!M18:M23)+SUMPRODUCT((Extension!F93:F98-Extension!C93:C98>0)*(Extension!F93:F98-Extension!C93:C98)*(1+$B51)^Extension!M67:M72)+SUMPRODUCT((Extension!F142:F147-Extension!C142:C147>0)*(Extension!F142:F147-Extension!C142:C147)*(1+$B51)^Extension!M116:M121) -> 12120.348 | E51: =SUMPRODUCT((Extension!G44:G49-Extension!C44:C49>0)*(Extension!G44:G49-Extension!C44:C49)*(1+$B51)^Extension!M18:M23)+SUMPRODUCT((Extension!G93:G98-Extension!C93:C98>0)*(Extension!G93:G98-Extension!C93:C98)*(1+$B51)^Extension!M67:M72)+SUMPRODUCT((Extension!G142:G147-Extension!C142:C147>0)*(Extension!G142:G147-Extension!C142:C147)*(1+$B51)^Extension!M116:M121) -> 12476.644 | J51: =$C$26 -> 11089.137 | K51: =$C$27 -> 13729.408
B52: 0.0325 | C52: =SUMPRODUCT((Extension!E44:E49-Extension!C44:C49>0)*(Extension!E44:E49-Extension!C44:C49)*(1+$B52)^Extension!M18:M23)+SUMPRODUCT((Extension!E93:E98-Extension!C93:C98>0)*(Extension!E93:E98-Extension!C93:C98)*(1+$B52)^Extension!M67:M72)+SUMPRODUCT((Extension!E142:E147-Extension!C142:C147>0)*(Extension!E142:E147-Extension!C142:C147)*(1+$B52)^Extension!M116:M121) -> 12461.093 | D52: =SUMPRODUCT((Extension!F44:F49-Extension!C44:C49>0)*(Extension!F44:F49-Extension!C44:C49)*(1+$B52)^Extension!M18:M23)+SUMPRODUCT((Extension!F93:F98-Extension!C93:C98>0)*(Extension!F93:F98-Extension!C93:C98)*(1+$B52)^Extension!M67:M72)+SUMPRODUCT((Extension!F142:F147-Extension!C142:C147>0)*(Extension!F142:F147-Extension!C142:C147)*(1+$B52)^Extension!M116:M121) -> 12187.53 | E52: =SUMPRODUCT((Extension!G44:G49-Extension!C44:C49>0)*(Extension!G44:G49-Extension!C44:C49)*(1+$B52)^Extension!M18:M23)+SUMPRODUCT((Extension!G93:G98-Extension!C93:C98>0)*(Extension!G93:G98-Extension!C93:C98)*(1+$B52)^Extension!M67:M72)+SUMPRODUCT((Extension!G142:G147-Extension!C142:C147>0)*(Extension!G142:G147-Extension!C142:C147)*(1+$B52)^Extension!M116:M121) -> 12546.063 | J52: =$C$26 -> 11089.137 | K52: =$C$27 -> 13729.408
B53: 0.035 | C53: =SUMPRODUCT((Extension!E44:E49-Extension!C44:C49>0)*(Extension!E44:E49-Extension!C44:C49)*(1+$B53)^Extension!M18:M23)+SUMPRODUCT((Extension!E93:E98-Extension!C93:C98>0)*(Extension!E93:E98-Extension!C93:C98)*(1+$B53)^Extension!M67:M72)+SUMPRODUCT((Extension!E142:E147-Extension!C142:C147>0)*(Extension!E142:E147-Extension!C142:C147)*(1+$B53)^Extension!M116:M121) -> 12530.174 | D53: =SUMPRODUCT((Extension!F44:F49-Extension!C44:C49>0)*(Extension!F44:F49-Extension!C44:C49)*(1+$B53)^Extension!M18:M23)+SUMPRODUCT((Extension!F93:F98-Extension!C93:C98>0)*(Extension!F93:F98-Extension!C93:C98)*(1+$B53)^Extension!M67:M72)+SUMPRODUCT((Extension!F142:F147-Extension!C142:C147>0)*(Extension!F142:F147-Extension!C142:C147)*(1+$B53)^Extension!M116:M121) -> 12254.925 | E53: =SUMPRODUCT((Extension!G44:G49-Extension!C44:C49>0)*(Extension!G44:G49-Extension!C44:C49)*(1+$B53)^Extension!M18:M23)+SUMPRODUCT((Extension!G93:G98-Extension!C93:C98>0)*(Extension!G93:G98-Extension!C93:C98)*(1+$B53)^Extension!M67:M72)+SUMPRODUCT((Extension!G142:G147-Extension!C142:C147>0)*(Extension!G142:G147-Extension!C142:C147)*(1+$B53)^Extension!M116:M121) -> 12615.703 | J53: =$C$26 -> 11089.137 | K53: =$C$27 -> 13729.408
B54: 0.0375 | C54: =SUMPRODUCT((Extension!E44:E49-Extension!C44:C49>0)*(Extension!E44:E49-Extension!C44:C49)*(1+$B54)^Extension!M18:M23)+SUMPRODUCT((Extension!E93:E98-Extension!C93:C98>0)*(Extension!E93:E98-Extension!C93:C98)*(1+$B54)^Extension!M67:M72)+SUMPRODUCT((Extension!E142:E147-Extension!C142:C147>0)*(Extension!E142:E147-Extension!C142:C147)*(1+$B54)^Extension!M116:M121) -> 12599.474 | D54: =SUMPRODUCT((Extension!F44:F49-Extension!C44:C49>0)*(Extension!F44:F49-Extension!C44:C49)*(1+$B54)^Extension!M18:M23)+SUMPRODUCT((Extension!F93:F98-Extension!C93:C98>0)*(Extension!F93:F98-Extension!C93:C98)*(1+$B54)^Extension!M67:M72)+SUMPRODUCT((Extension!F142:F147-Extension!C142:C147>0)*(Extension!F142:F147-Extension!C142:C147)*(1+$B54)^Extension!M116:M121) -> 12322.532 | E54: =SUMPRODUCT((Extension!G44:G49-Extension!C44:C49>0)*(Extension!G44:G49-Extension!C44:C49)*(1+$B54)^Extension!M18:M23)+SUMPRODUCT((Extension!G93:G98-Extension!C93:C98>0)*(Extension!G93:G98-Extension!C93:C98)*(1+$B54)^Extension!M67:M72)+SUMPRODUCT((Extension!G142:G147-Extension!C142:C147>0)*(Extension!G142:G147-Extension!C142:C147)*(1+$B54)^Extension!M116:M121) -> 12685.564 | J54: =$C$26 -> 11089.137 | K54: =$C$27 -> 13729.408
B55: 0.04 | C55: =SUMPRODUCT((Extension!E44:E49-Extension!C44:C49>0)*(Extension!E44:E49-Extension!C44:C49)*(1+$B55)^Extension!M18:M23)+SUMPRODUCT((Extension!E93:E98-Extension!C93:C98>0)*(Extension!E93:E98-Extension!C93:C98)*(1+$B55)^Extension!M67:M72)+SUMPRODUCT((Extension!E142:E147-Extension!C142:C147>0)*(Extension!E142:E147-Extension!C142:C147)*(1+$B55)^Extension!M116:M121) -> 12668.993 | D55: =SUMPRODUCT((Extension!F44:F49-Extension!C44:C49>0)*(Extension!F44:F49-Extension!C44:C49)*(1+$B55)^Extension!M18:M23)+SUMPRODUCT((Extension!F93:F98-Extension!C93:C98>0)*(Extension!F93:F98-Extension!C93:C98)*(1+$B55)^Extension!M67:M72)+SUMPRODUCT((Extension!F142:F147-Extension!C142:C147>0)*(Extension!F142:F147-Extension!C142:C147)*(1+$B55)^Extension!M116:M121) -> 12390.351 | E55: =SUMPRODUCT((Extension!G44:G49-Extension!C44:C49>0)*(Extension!G44:G49-Extension!C44:C49)*(1+$B55)^Extension!M18:M23)+SUMPRODUCT((Extension!G93:G98-Extension!C93:C98>0)*(Extension!G93:G98-Extension!C93:C98)*(1+$B55)^Extension!M67:M72)+SUMPRODUCT((Extension!G142:G147-Extension!C142:C147>0)*(Extension!G142:G147-Extension!C142:C147)*(1+$B55)^Extension!M116:M121) -> 12755.646 | J55: =$C$26 -> 11089.137 | K55: =$C$27 -> 13729.408
B56: 0.0425 | C56: =SUMPRODUCT((Extension!E44:E49-Extension!C44:C49>0)*(Extension!E44:E49-Extension!C44:C49)*(1+$B56)^Extension!M18:M23)+SUMPRODUCT((Extension!E93:E98-Extension!C93:C98>0)*(Extension!E93:E98-Extension!C93:C98)*(1+$B56)^Extension!M67:M72)+SUMPRODUCT((Extension!E142:E147-Extension!C142:C147>0)*(Extension!E142:E147-Extension!C142:C147)*(1+$B56)^Extension!M116:M121) -> 12738.73 | D56: =SUMPRODUCT((Extension!F44:F49-Extension!C44:C49>0)*(Extension!F44:F49-Extension!C44:C49)*(1+$B56)^Extension!M18:M23)+SUMPRODUCT((Extension!F93:F98-Extension!C93:C98>0)*(Extension!F93:F98-Extension!C93:C98)*(1+$B56)^Extension!M67:M72)+SUMPRODUCT((Extension!F142:F147-Extension!C142:C147>0)*(Extension!F142:F147-Extension!C142:C147)*(1+$B56)^Extension!M116:M121) -> 12458.384 | E56: =SUMPRODUCT((Extension!G44:G49-Extension!C44:C49>0)*(Extension!G44:G49-Extension!C44:C49)*(1+$B56)^Extension!M18:M23)+SUMPRODUCT((Extension!G93:G98-Extension!C93:C98>0)*(Extension!G93:G98-Extension!C93:C98)*(1+$B56)^Extension!M67:M72)+SUMPRODUCT((Extension!G142:G147-Extension!C142:C147>0)*(Extension!G142:G147-Extension!C142:C147)*(1+$B56)^Extension!M116:M121) -> 12825.95 | J56: =$C$26 -> 11089.137 | K56: =$C$27 -> 13729.408
B57: 0.045 | C57: =SUMPRODUCT((Extension!E44:E49-Extension!C44:C49>0)*(Extension!E44:E49-Extension!C44:C49)*(1+$B57)^Extension!M18:M23)+SUMPRODUCT((Extension!E93:E98-Extension!C93:C98>0)*(Extension!E93:E98-Extension!C93:C98)*(1+$B57)^Extension!M67:M72)+SUMPRODUCT((Extension!E142:E147-Extension!C142:C147>0)*(Extension!E142:E147-Extension!C142:C147)*(1+$B57)^Extension!M116:M121) -> 12808.687 | D57: =SUMPRODUCT((Extension!F44:F49-Extension!C44:C49>0)*(Extension!F44:F49-Extension!C44:C49)*(1+$B57)^Extension!M18:M23)+SUMPRODUCT((Extension!F93:F98-Extension!C93:C98>0)*(Extension!F93:F98-Extension!C93:C98)*(1+$B57)^Extension!M67:M72)+SUMPRODUCT((Extension!F142:F147-Extension!C142:C147>0)*(Extension!F142:F147-Extension!C142:C147)*(1+$B57)^Extension!M116:M121) -> 12526.629 | E57: =SUMPRODUCT((Extension!G44:G49-Extension!C44:C49>0)*(Extension!G44:G49-Extension!C44:C49)*(1+$B57)^Extension!M18:M23)+SUMPRODUCT((Extension!G93:G98-Extension!C93:C98>0)*(Extension!G93:G98-Extension!C93:C98)*(1+$B57)^Extension!M67:M72)+SUMPRODUCT((Extension!G142:G147-Extension!C142:C147>0)*(Extension!G142:G147-Extension!C142:C147)*(1+$B57)^Extension!M116:M121) -> 12896.474 | J57: =$C$26 -> 11089.137 | K57: =$C$27 -> 13729.408
B58: 0.0475 | C58: =SUMPRODUCT((Extension!E44:E49-Extension!C44:C49>0)*(Extension!E44:E49-Extension!C44:C49)*(1+$B58)^Extension!M18:M23)+SUMPRODUCT((Extension!E93:E98-Extension!C93:C98>0)*(Extension!E93:E98-Extension!C93:C98)*(1+$B58)^Extension!M67:M72)+SUMPRODUCT((Extension!E142:E147-Extension!C142:C147>0)*(Extension!E142:E147-Extension!C142:C147)*(1+$B58)^Extension!M116:M121) -> 12878.863 | D58: =SUMPRODUCT((Extension!F44:F49-Extension!C44:C49>0)*(Extension!F44:F49-Extension!C44:C49)*(1+$B58)^Extension!M18:M23)+SUMPRODUCT((Extension!F93:F98-Extension!C93:C98>0)*(Extension!F93:F98-Extension!C93:C98)*(1+$B58)^Extension!M67:M72)+SUMPRODUCT((Extension!F142:F147-Extension!C142:C147>0)*(Extension!F142:F147-Extension!C142:C147)*(1+$B58)^Extension!M116:M121) -> 12595.088 | E58: =SUMPRODUCT((Extension!G44:G49-Extension!C44:C49>0)*(Extension!G44:G49-Extension!C44:C49)*(1+$B58)^Extension!M18:M23)+SUMPRODUCT((Extension!G93:G98-Extension!C93:C98>0)*(Extension!G93:G98-Extension!C93:C98)*(1+$B58)^Extension!M67:M72)+SUMPRODUCT((Extension!G142:G147-Extension!C142:C147>0)*(Extension!G142:G147-Extension!C142:C147)*(1+$B58)^Extension!M116:M121) -> 12967.221 | J58: =$C$26 -> 11089.137 | K58: =$C$27 -> 13729.408
B59: 0.05 | C59: =SUMPRODUCT((Extension!E44:E49-Extension!C44:C49>0)*(Extension!E44:E49-Extension!C44:C49)*(1+$B59)^Extension!M18:M23)+SUMPRODUCT((Extension!E93:E98-Extension!C93:C98>0)*(Extension!E93:E98-Extension!C93:C98)*(1+$B59)^Extension!M67:M72)+SUMPRODUCT((Extension!E142:E147-Extension!C142:C147>0)*(Extension!E142:E147-Extension!C142:C147)*(1+$B59)^Extension!M116:M121) -> 12949.258 | D59: =SUMPRODUCT((Extension!F44:F49-Extension!C44:C49>0)*(Extension!F44:F49-Extension!C44:C49)*(1+$B59)^Extension!M18:M23)+SUMPRODUCT((Extension!F93:F98-Extension!C93:C98>0)*(Extension!F93:F98-Extension!C93:C98)*(1+$B59)^Extension!M67:M72)+SUMPRODUCT((Extension!F142:F147-Extension!C142:C147>0)*(Extension!F142:F147-Extension!C142:C147)*(1+$B59)^Extension!M116:M121) -> 12663.76 | E59: =SUMPRODUCT((Extension!G44:G49-Extension!C44:C49>0)*(Extension!G44:G49-Extension!C44:C49)*(1+$B59)^Extension!M18:M23)+SUMPRODUCT((Extension!G93:G98-Extension!C93:C98>0)*(Extension!G93:G98-Extension!C93:C98)*(1+$B59)^Extension!M67:M72)+SUMPRODUCT((Extension!G142:G147-Extension!C142:C147>0)*(Extension!G142:G147-Extension!C142:C147)*(1+$B59)^Extension!M116:M121) -> 13038.189 | J59: =$C$26 -> 11089.137 | K59: =$C$27 -> 13729.408
B60: 0.0525 | C60: =SUMPRODUCT((Extension!E44:E49-Extension!C44:C49>0)*(Extension!E44:E49-Extension!C44:C49)*(1+$B60)^Extension!M18:M23)+SUMPRODUCT((Extension!E93:E98-Extension!C93:C98>0)*(Extension!E93:E98-Extension!C93:C98)*(1+$B60)^Extension!M67:M72)+SUMPRODUCT((Extension!E142:E147-Extension!C142:C147>0)*(Extension!E142:E147-Extension!C142:C147)*(1+$B60)^Extension!M116:M121) -> 13019.874 | D60: =SUMPRODUCT((Extension!F44:F49-Extension!C44:C49>0)*(Extension!F44:F49-Extension!C44:C49)*(1+$B60)^Extension!M18:M23)+SUMPRODUCT((Extension!F93:F98-Extension!C93:C98>0)*(Extension!F93:F98-Extension!C93:C98)*(1+$B60)^Extension!M67:M72)+SUMPRODUCT((Extension!F142:F147-Extension!C142:C147>0)*(Extension!F142:F147-Extension!C142:C147)*(1+$B60)^Extension!M116:M121) -> 12732.646 | E60: =SUMPRODUCT((Extension!G44:G49-Extension!C44:C49>0)*(Extension!G44:G49-Extension!C44:C49)*(1+$B60)^Extension!M18:M23)+SUMPRODUCT((Extension!G93:G98-Extension!C93:C98>0)*(Extension!G93:G98-Extension!C93:C98)*(1+$B60)^Extension!M67:M72)+SUMPRODUCT((Extension!G142:G147-Extension!C142:C147>0)*(Extension!G142:G147-Extension!C142:C147)*(1+$B60)^Extension!M116:M121) -> 13109.379 | J60: =$C$26 -> 11089.137 | K60: =$C$27 -> 13729.408
B61: 0.055 | C61: =SUMPRODUCT((Extension!E44:E49-Extension!C44:C49>0)*(Extension!E44:E49-Extension!C44:C49)*(1+$B61)^Extension!M18:M23)+SUMPRODUCT((Extension!E93:E98-Extension!C93:C98>0)*(Extension!E93:E98-Extension!C93:C98)*(1+$B61)^Extension!M67:M72)+SUMPRODUCT((Extension!E142:E147-Extension!C142:C147>0)*(Extension!E142:E147-Extension!C142:C147)*(1+$B61)^Extension!M116:M121) -> 13090.709 | D61: =SUMPRODUCT((Extension!F44:F49-Extension!C44:C49>0)*(Extension!F44:F49-Extension!C44:C49)*(1+$B61)^Extension!M18:M23)+SUMPRODUCT((Extension!F93:F98-Extension!C93:C98>0)*(Extension!F93:F98-Extension!C93:C98)*(1+$B61)^Extension!M67:M72)+SUMPRODUCT((Extension!F142:F147-Extension!C142:C147>0)*(Extension!F142:F147-Extension!C142:C147)*(1+$B61)^Extension!M116:M121) -> 12801.745 | E61: =SUMPRODUCT((Extension!G44:G49-Extension!C44:C49>0)*(Extension!G44:G49-Extension!C44:C49)*(1+$B61)^Extension!M18:M23)+SUMPRODUCT((Extension!G93:G98-Extension!C93:C98>0)*(Extension!G93:G98-Extension!C93:C98)*(1+$B61)^Extension!M67:M72)+SUMPRODUCT((Extension!G142:G147-Extension!C142:C147>0)*(Extension!G142:G147-Extension!C142:C147)*(1+$B61)^Extension!M116:M121) -> 13180.791 | J61: =$C$26 -> 11089.137 | K61: =$C$27 -> 13729.408
B62: 0.0575 | C62: =SUMPRODUCT((Extension!E44:E49-Extension!C44:C49>0)*(Extension!E44:E49-Extension!C44:C49)*(1+$B62)^Extension!M18:M23)+SUMPRODUCT((Extension!E93:E98-Extension!C93:C98>0)*(Extension!E93:E98-Extension!C93:C98)*(1+$B62)^Extension!M67:M72)+SUMPRODUCT((Extension!E142:E147-Extension!C142:C147>0)*(Extension!E142:E147-Extension!C142:C147)*(1+$B62)^Extension!M116:M121) -> 13161.764 | D62: =SUMPRODUCT((Extension!F44:F49-Extension!C44:C49>0)*(Extension!F44:F49-Extension!C44:C49)*(1+$B62)^Extension!M18:M23)+SUMPRODUCT((Extension!F93:F98-Extension!C93:C98>0)*(Extension!F93:F98-Extension!C93:C98)*(1+$B62)^Extension!M67:M72)+SUMPRODUCT((Extension!F142:F147-Extension!C142:C147>0)*(Extension!F142:F147-Extension!C142:C147)*(1+$B62)^Extension!M116:M121) -> 12871.059 | E62: =SUMPRODUCT((Extension!G44:G49-Extension!C44:C49>0)*(Extension!G44:G49-Extension!C44:C49)*(1+$B62)^Extension!M18:M23)+SUMPRODUCT((Extension!G93:G98-Extension!C93:C98>0)*(Extension!G93:G98-Extension!C93:C98)*(1+$B62)^Extension!M67:M72)+SUMPRODUCT((Extension!G142:G147-Extension!C142:C147>0)*(Extension!G142:G147-Extension!C142:C147)*(1+$B62)^Extension!M116:M121) -> 13252.426 | J62: =$C$26 -> 11089.137 | K62: =$C$27 -> 13729.408
B63: 0.06 | C63: =SUMPRODUCT((Extension!E44:E49-Extension!C44:C49>0)*(Extension!E44:E49-Extension!C44:C49)*(1+$B63)^Extension!M18:M23)+SUMPRODUCT((Extension!E93:E98-Extension!C93:C98>0)*(Extension!E93:E98-Extension!C93:C98)*(1+$B63)^Extension!M67:M72)+SUMPRODUCT((Extension!E142:E147-Extension!C142:C147>0)*(Extension!E142:E147-Extension!C142:C147)*(1+$B63)^Extension!M116:M121) -> 13233.039 | D63: =SUMPRODUCT((Extension!F44:F49-Extension!C44:C49>0)*(Extension!F44:F49-Extension!C44:C49)*(1+$B63)^Extension!M18:M23)+SUMPRODUCT((Extension!F93:F98-Extension!C93:C98>0)*(Extension!F93:F98-Extension!C93:C98)*(1+$B63)^Extension!M67:M72)+SUMPRODUCT((Extension!F142:F147-Extension!C142:C147>0)*(Extension!F142:F147-Extension!C142:C147)*(1+$B63)^Extension!M116:M121) -> 12940.586 | E63: =SUMPRODUCT((Extension!G44:G49-Extension!C44:C49>0)*(Extension!G44:G49-Extension!C44:C49)*(1+$B63)^Extension!M18:M23)+SUMPRODUCT((Extension!G93:G98-Extension!C93:C98>0)*(Extension!G93:G98-Extension!C93:C98)*(1+$B63)^Extension!M67:M72)+SUMPRODUCT((Extension!G142:G147-Extension!C142:C147>0)*(Extension!G142:G147-Extension!C142:C147)*(1+$B63)^Extension!M116:M121) -> 13324.283 | J63: =$C$26 -> 11089.137 | K63: =$C$27 -> 13729.408
B64: 0.0625 | C64: =SUMPRODUCT((Extension!E44:E49-Extension!C44:C49>0)*(Extension!E44:E49-Extension!C44:C49)*(1+$B64)^Extension!M18:M23)+SUMPRODUCT((Extension!E93:E98-Extension!C93:C98>0)*(Extension!E93:E98-Extension!C93:C98)*(1+$B64)^Extension!M67:M72)+SUMPRODUCT((Extension!E142:E147-Extension!C142:C147>0)*(Extension!E142:E147-Extension!C142:C147)*(1+$B64)^Extension!M116:M121) -> 13304.535 | D64: =SUMPRODUCT((Extension!F44:F49-Extension!C44:C49>0)*(Extension!F44:F49-Extension!C44:C49)*(1+$B64)^Extension!M18:M23)+SUMPRODUCT((Extension!F93:F98-Extension!C93:C98>0)*(Extension!F93:F98-Extension!C93:C98)*(1+$B64)^Extension!M67:M72)+SUMPRODUCT((Extension!F142:F147-Extension!C142:C147>0)*(Extension!F142:F147-Extension!C142:C147)*(1+$B64)^Extension!M116:M121) -> 13010.328 | E64: =SUMPRODUCT((Extension!G44:G49-Extension!C44:C49>0)*(Extension!G44:G49-Extension!C44:C49)*(1+$B64)^Extension!M18:M23)+SUMPRODUCT((Extension!G93:G98-Extension!C93:C98>0)*(Extension!G93:G98-Extension!C93:C98)*(1+$B64)^Extension!M67:M72)+SUMPRODUCT((Extension!G142:G147-Extension!C142:C147>0)*(Extension!G142:G147-Extension!C142:C147)*(1+$B64)^Extension!M116:M121) -> 13396.363 | J64: =$C$26 -> 11089.137 | K64: =$C$27 -> 13729.408
B65: 0.065 | C65: =SUMPRODUCT((Extension!E44:E49-Extension!C44:C49>0)*(Extension!E44:E49-Extension!C44:C49)*(1+$B65)^Extension!M18:M23)+SUMPRODUCT((Extension!E93:E98-Extension!C93:C98>0)*(Extension!E93:E98-Extension!C93:C98)*(1+$B65)^Extension!M67:M72)+SUMPRODUCT((Extension!E142:E147-Extension!C142:C147>0)*(Extension!E142:E147-Extension!C142:C147)*(1+$B65)^Extension!M116:M121) -> 13376.252 | D65: =SUMPRODUCT((Extension!F44:F49-Extension!C44:C49>0)*(Extension!F44:F49-Extension!C44:C49)*(1+$B65)^Extension!M18:M23)+SUMPRODUCT((Extension!F93:F98-Extension!C93:C98>0)*(Extension!F93:F98-Extension!C93:C98)*(1+$B65)^Extension!M67:M72)+SUMPRODUCT((Extension!F142:F147-Extension!C142:C147>0)*(Extension!F142:F147-Extension!C142:C147)*(1+$B65)^Extension!M116:M121) -> 13080.284 | E65: =SUMPRODUCT((Extension!G44:G49-Extension!C44:C49>0)*(Extension!G44:G49-Extension!C44:C49)*(1+$B65)^Extension!M18:M23)+SUMPRODUCT((Extension!G93:G98-Extension!C93:C98>0)*(Extension!G93:G98-Extension!C93:C98)*(1+$B65)^Extension!M67:M72)+SUMPRODUCT((Extension!G142:G147-Extension!C142:C147>0)*(Extension!G142:G147-Extension!C142:C147)*(1+$B65)^Extension!M116:M121) -> 13468.666 | J65: =$C$26 -> 11089.137 | K65: =$C$27 -> 13729.408
B66: 0.0675 | C66: =SUMPRODUCT((Extension!E44:E49-Extension!C44:C49>0)*(Extension!E44:E49-Extension!C44:C49)*(1+$B66)^Extension!M18:M23)+SUMPRODUCT((Extension!E93:E98-Extension!C93:C98>0)*(Extension!E93:E98-Extension!C93:C98)*(1+$B66)^Extension!M67:M72)+SUMPRODUCT((Extension!E142:E147-Extension!C142:C147>0)*(Extension!E142:E147-Extension!C142:C147)*(1+$B66)^Extension!M116:M121) -> 13448.189 | D66: =SUMPRODUCT((Extension!F44:F49-Extension!C44:C49>0)*(Extension!F44:F49-Extension!C44:C49)*(1+$B66)^Extension!M18:M23)+SUMPRODUCT((Extension!F93:F98-Extension!C93:C98>0)*(Extension!F93:F98-Extension!C93:C98)*(1+$B66)^Extension!M67:M72)+SUMPRODUCT((Extension!F142:F147-Extension!C142:C147>0)*(Extension!F142:F147-Extension!C142:C147)*(1+$B66)^Extension!M116:M121) -> 13150.455 | E66: =SUMPRODUCT((Extension!G44:G49-Extension!C44:C49>0)*(Extension!G44:G49-Extension!C44:C49)*(1+$B66)^Extension!M18:M23)+SUMPRODUCT((Extension!G93:G98-Extension!C93:C98>0)*(Extension!G93:G98-Extension!C93:C98)*(1+$B66)^Extension!M67:M72)+SUMPRODUCT((Extension!G142:G147-Extension!C142:C147>0)*(Extension!G142:G147-Extension!C142:C147)*(1+$B66)^Extension!M116:M121) -> 13541.192 | J66: =$C$26 -> 11089.137 | K66: =$C$27 -> 13729.408
B67: 0.07 | C67: =SUMPRODUCT((Extension!E44:E49-Extension!C44:C49>0)*(Extension!E44:E49-Extension!C44:C49)*(1+$B67)^Extension!M18:M23)+SUMPRODUCT((Extension!E93:E98-Extension!C93:C98>0)*(Extension!E93:E98-Extension!C93:C98)*(1+$B67)^Extension!M67:M72)+SUMPRODUCT((Extension!E142:E147-Extension!C142:C147>0)*(Extension!E142:E147-Extension!C142:C147)*(1+$B67)^Extension!M116:M121) -> 13520.347 | D67: =SUMPRODUCT((Extension!F44:F49-Extension!C44:C49>0)*(Extension!F44:F49-Extension!C44:C49)*(1+$B67)^Extension!M18:M23)+SUMPRODUCT((Extension!F93:F98-Extension!C93:C98>0)*(Extension!F93:F98-Extension!C93:C98)*(1+$B67)^Extension!M67:M72)+SUMPRODUCT((Extension!F142:F147-Extension!C142:C147>0)*(Extension!F142:F147-Extension!C142:C147)*(1+$B67)^Extension!M116:M121) -> 13220.841 | E67: =SUMPRODUCT((Extension!G44:G49-Extension!C44:C49>0)*(Extension!G44:G49-Extension!C44:C49)*(1+$B67)^Extension!M18:M23)+SUMPRODUCT((Extension!G93:G98-Extension!C93:C98>0)*(Extension!G93:G98-Extension!C93:C98)*(1+$B67)^Extension!M67:M72)+SUMPRODUCT((Extension!G142:G147-Extension!C142:C147>0)*(Extension!G142:G147-Extension!C142:C147)*(1+$B67)^Extension!M116:M121) -> 13613.941 | J67: =$C$26 -> 11089.137 | K67: =$C$27 -> 13729.408
B68: 0.0725 | C68: =SUMPRODUCT((Extension!E44:E49-Extension!C44:C49>0)*(Extension!E44:E49-Extension!C44:C49)*(1+$B68)^Extension!M18:M23)+SUMPRODUCT((Extension!E93:E98-Extension!C93:C98>0)*(Extension!E93:E98-Extension!C93:C98)*(1+$B68)^Extension!M67:M72)+SUMPRODUCT((Extension!E142:E147-Extension!C142:C147>0)*(Extension!E142:E147-Extension!C142:C147)*(1+$B68)^Extension!M116:M121) -> 13592.727 | D68: =SUMPRODUCT((Extension!F44:F49-Extension!C44:C49>0)*(Extension!F44:F49-Extension!C44:C49)*(1+$B68)^Extension!M18:M23)+SUMPRODUCT((Extension!F93:F98-Extension!C93:C98>0)*(Extension!F93:F98-Extension!C93:C98)*(1+$B68)^Extension!M67:M72)+SUMPRODUCT((Extension!F142:F147-Extension!C142:C147>0)*(Extension!F142:F147-Extension!C142:C147)*(1+$B68)^Extension!M116:M121) -> 13291.441 | E68: =SUMPRODUCT((Extension!G44:G49-Extension!C44:C49>0)*(Extension!G44:G49-Extension!C44:C49)*(1+$B68)^Extension!M18:M23)+SUMPRODUCT((Extension!G93:G98-Extension!C93:C98>0)*(Extension!G93:G98-Extension!C93:C98)*(1+$B68)^Extension!M67:M72)+SUMPRODUCT((Extension!G142:G147-Extension!C142:C147>0)*(Extension!G142:G147-Extension!C142:C147)*(1+$B68)^Extension!M116:M121) -> 13686.914 | J68: =$C$26 -> 11089.137 | K68: =$C$27 -> 13729.408
B69: 0.075 | C69: =SUMPRODUCT((Extension!E44:E49-Extension!C44:C49>0)*(Extension!E44:E49-Extension!C44:C49)*(1+$B69)^Extension!M18:M23)+SUMPRODUCT((Extension!E93:E98-Extension!C93:C98>0)*(Extension!E93:E98-Extension!C93:C98)*(1+$B69)^Extension!M67:M72)+SUMPRODUCT((Extension!E142:E147-Extension!C142:C147>0)*(Extension!E142:E147-Extension!C142:C147)*(1+$B69)^Extension!M116:M121) -> 13665.328 | D69: =SUMPRODUCT((Extension!F44:F49-Extension!C44:C49>0)*(Extension!F44:F49-Extension!C44:C49)*(1+$B69)^Extension!M18:M23)+SUMPRODUCT((Extension!F93:F98-Extension!C93:C98>0)*(Extension!F93:F98-Extension!C93:C98)*(1+$B69)^Extension!M67:M72)+SUMPRODUCT((Extension!F142:F147-Extension!C142:C147>0)*(Extension!F142:F147-Extension!C142:C147)*(1+$B69)^Extension!M116:M121) -> 13362.257 | E69: =SUMPRODUCT((Extension!G44:G49-Extension!C44:C49>0)*(Extension!G44:G49-Extension!C44:C49)*(1+$B69)^Extension!M18:M23)+SUMPRODUCT((Extension!G93:G98-Extension!C93:C98>0)*(Extension!G93:G98-Extension!C93:C98)*(1+$B69)^Extension!M67:M72)+SUMPRODUCT((Extension!G142:G147-Extension!C142:C147>0)*(Extension!G142:G147-Extension!C142:C147)*(1+$B69)^Extension!M116:M121) -> 13760.111 | J69: =$C$26 -> 11089.137 | K69: =$C$27 -> 13729.408
B70: 0.0775 | C70: =SUMPRODUCT((Extension!E44:E49-Extension!C44:C49>0)*(Extension!E44:E49-Extension!C44:C49)*(1+$B70)^Extension!M18:M23)+SUMPRODUCT((Extension!E93:E98-Extension!C93:C98>0)*(Extension!E93:E98-Extension!C93:C98)*(1+$B70)^Extension!M67:M72)+SUMPRODUCT((Extension!E142:E147-Extension!C142:C147>0)*(Extension!E142:E147-Extension!C142:C147)*(1+$B70)^Extension!M116:M121) -> 13738.15 | D70: =SUMPRODUCT((Extension!F44:F49-Extension!C44:C49>0)*(Extension!F44:F49-Extension!C44:C49)*(1+$B70)^Extension!M18:M23)+SUMPRODUCT((Extension!F93:F98-Extension!C93:C98>0)*(Extension!F93:F98-Extension!C93:C98)*(1+$B70)^Extension!M67:M72)+SUMPRODUCT((Extension!F142:F147-Extension!C142:C147>0)*(Extension!F142:F147-Extension!C142:C147)*(1+$B70)^Extension!M116:M121) -> 13433.288 | E70: =SUMPRODUCT((Extension!G44:G49-Extension!C44:C49>0)*(Extension!G44:G49-Extension!C44:C49)*(1+$B70)^Extension!M18:M23)+SUMPRODUCT((Extension!G93:G98-Extension!C93:C98>0)*(Extension!G93:G98-Extension!C93:C98)*(1+$B70)^Extension!M67:M72)+SUMPRODUCT((Extension!G142:G147-Extension!C142:C147>0)*(Extension!G142:G147-Extension!C142:C147)*(1+$B70)^Extension!M116:M121) -> 13833.531 | J70: =$C$26 -> 11089.137 | K70: =$C$27 -> 13729.408
B71: 0.08 | C71: =SUMPRODUCT((Extension!E44:E49-Extension!C44:C49>0)*(Extension!E44:E49-Extension!C44:C49)*(1+$B71)^Extension!M18:M23)+SUMPRODUCT((Extension!E93:E98-Extension!C93:C98>0)*(Extension!E93:E98-Extension!C93:C98)*(1+$B71)^Extension!M67:M72)+SUMPRODUCT((Extension!E142:E147-Extension!C142:C147>0)*(Extension!E142:E147-Extension!C142:C147)*(1+$B71)^Extension!M116:M121) -> 13811.194 | D71: =SUMPRODUCT((Extension!F44:F49-Extension!C44:C49>0)*(Extension!F44:F49-Extension!C44:C49)*(1+$B71)^Extension!M18:M23)+SUMPRODUCT((Extension!F93:F98-Extension!C93:C98>0)*(Extension!F93:F98-Extension!C93:C98)*(1+$B71)^Extension!M67:M72)+SUMPRODUCT((Extension!F142:F147-Extension!C142:C147>0)*(Extension!F142:F147-Extension!C142:C147)*(1+$B71)^Extension!M116:M121) -> 13504.534 | E71: =SUMPRODUCT((Extension!G44:G49-Extension!C44:C49>0)*(Extension!G44:G49-Extension!C44:C49)*(1+$B71)^Extension!M18:M23)+SUMPRODUCT((Extension!G93:G98-Extension!C93:C98>0)*(Extension!G93:G98-Extension!C93:C98)*(1+$B71)^Extension!M67:M72)+SUMPRODUCT((Extension!G142:G147-Extension!C142:C147>0)*(Extension!G142:G147-Extension!C142:C147)*(1+$B71)^Extension!M116:M121) -> 13907.175 | J71: =$C$26 -> 11089.137 | K71: =$C$27 -> 13729.408
B72: 0.0825 | C72: =SUMPRODUCT((Extension!E44:E49-Extension!C44:C49>0)*(Extension!E44:E49-Extension!C44:C49)*(1+$B72)^Extension!M18:M23)+SUMPRODUCT((Extension!E93:E98-Extension!C93:C98>0)*(Extension!E93:E98-Extension!C93:C98)*(1+$B72)^Extension!M67:M72)+SUMPRODUCT((Extension!E142:E147-Extension!C142:C147>0)*(Extension!E142:E147-Extension!C142:C147)*(1+$B72)^Extension!M116:M121) -> 13884.46 | D72: =SUMPRODUCT((Extension!F44:F49-Extension!C44:C49>0)*(Extension!F44:F49-Extension!C44:C49)*(1+$B72)^Extension!M18:M23)+SUMPRODUCT((Extension!F93:F98-Extension!C93:C98>0)*(Extension!F93:F98-Extension!C93:C98)*(1+$B72)^Extension!M67:M72)+SUMPRODUCT((Extension!F142:F147-Extension!C142:C147>0)*(Extension!F142:F147-Extension!C142:C147)*(1+$B72)^Extension!M116:M121) -> 13575.997 | E72: =SUMPRODUCT((Extension!G44:G49-Extension!C44:C49>0)*(Extension!G44:G49-Extension!C44:C49)*(1+$B72)^Extension!M18:M23)+SUMPRODUCT((Extension!G93:G98-Extension!C93:C98>0)*(Extension!G93:G98-Extension!C93:C98)*(1+$B72)^Extension!M67:M72)+SUMPRODUCT((Extension!G142:G147-Extension!C142:C147>0)*(Extension!G142:G147-Extension!C142:C147)*(1+$B72)^Extension!M116:M121) -> 13981.044 | J72: =$C$26 -> 11089.137 | K72: =$C$27 -> 13729.408
B73: 0.085 | C73: =SUMPRODUCT((Extension!E44:E49-Extension!C44:C49>0)*(Extension!E44:E49-Extension!C44:C49)*(1+$B73)^Extension!M18:M23)+SUMPRODUCT((Extension!E93:E98-Extension!C93:C98>0)*(Extension!E93:E98-Extension!C93:C98)*(1+$B73)^Extension!M67:M72)+SUMPRODUCT((Extension!E142:E147-Extension!C142:C147>0)*(Extension!E142:E147-Extension!C142:C147)*(1+$B73)^Extension!M116:M121) -> 13957.947 | D73: =SUMPRODUCT((Extension!F44:F49-Extension!C44:C49>0)*(Extension!F44:F49-Extension!C44:C49)*(1+$B73)^Extension!M18:M23)+SUMPRODUCT((Extension!F93:F98-Extension!C93:C98>0)*(Extension!F93:F98-Extension!C93:C98)*(1+$B73)^Extension!M67:M72)+SUMPRODUCT((Extension!F142:F147-Extension!C142:C147>0)*(Extension!F142:F147-Extension!C142:C147)*(1+$B73)^Extension!M116:M121) -> 13647.675 | E73: =SUMPRODUCT((Extension!G44:G49-Extension!C44:C49>0)*(Extension!G44:G49-Extension!C44:C49)*(1+$B73)^Extension!M18:M23)+SUMPRODUCT((Extension!G93:G98-Extension!C93:C98>0)*(Extension!G93:G98-Extension!C93:C98)*(1+$B73)^Extension!M67:M72)+SUMPRODUCT((Extension!G142:G147-Extension!C142:C147>0)*(Extension!G142:G147-Extension!C142:C147)*(1+$B73)^Extension!M116:M121) -> 14055.137 | J73: =$C$26 -> 11089.137 | K73: =$C$27 -> 13729.408
B74: 0.0875 | C74: =SUMPRODUCT((Extension!E44:E49-Extension!C44:C49>0)*(Extension!E44:E49-Extension!C44:C49)*(1+$B74)^Extension!M18:M23)+SUMPRODUCT((Extension!E93:E98-Extension!C93:C98>0)*(Extension!E93:E98-Extension!C93:C98)*(1+$B74)^Extension!M67:M72)+SUMPRODUCT((Extension!E142:E147-Extension!C142:C147>0)*(Extension!E142:E147-Extension!C142:C147)*(1+$B74)^Extension!M116:M121) -> 14031.658 | D74: =SUMPRODUCT((Extension!F44:F49-Extension!C44:C49>0)*(Extension!F44:F49-Extension!C44:C49)*(1+$B74)^Extension!M18:M23)+SUMPRODUCT((Extension!F93:F98-Extension!C93:C98>0)*(Extension!F93:F98-Extension!C93:C98)*(1+$B74)^Extension!M67:M72)+SUMPRODUCT((Extension!F142:F147-Extension!C142:C147>0)*(Extension!F142:F147-Extension!C142:C147)*(1+$B74)^Extension!M116:M121) -> 13719.569 | E74: =SUMPRODUCT((Extension!G44:G49-Extension!C44:C49>0)*(Extension!G44:G49-Extension!C44:C49)*(1+$B74)^Extension!M18:M23)+SUMPRODUCT((Extension!G93:G98-Extension!C93:C98>0)*(Extension!G93:G98-Extension!C93:C98)*(1+$B74)^Extension!M67:M72)+SUMPRODUCT((Extension!G142:G147-Extension!C142:C147>0)*(Extension!G142:G147-Extension!C142:C147)*(1+$B74)^Extension!M116:M121) -> 14129.455 | J74: =$C$26 -> 11089.137 | K74: =$C$27 -> 13729.408
B75: 0.09 | C75: =SUMPRODUCT((Extension!E44:E49-Extension!C44:C49>0)*(Extension!E44:E49-Extension!C44:C49)*(1+$B75)^Extension!M18:M23)+SUMPRODUCT((Extension!E93:E98-Extension!C93:C98>0)*(Extension!E93:E98-Extension!C93:C98)*(1+$B75)^Extension!M67:M72)+SUMPRODUCT((Extension!E142:E147-Extension!C142:C147>0)*(Extension!E142:E147-Extension!C142:C147)*(1+$B75)^Extension!M116:M121) -> 14105.59 | D75: =SUMPRODUCT((Extension!F44:F49-Extension!C44:C49>0)*(Extension!F44:F49-Extension!C44:C49)*(1+$B75)^Extension!M18:M23)+SUMPRODUCT((Extension!F93:F98-Extension!C93:C98>0)*(Extension!F93:F98-Extension!C93:C98)*(1+$B75)^Extension!M67:M72)+SUMPRODUCT((Extension!F142:F147-Extension!C142:C147>0)*(Extension!F142:F147-Extension!C142:C147)*(1+$B75)^Extension!M116:M121) -> 13791.679 | E75: =SUMPRODUCT((Extension!G44:G49-Extension!C44:C49>0)*(Extension!G44:G49-Extension!C44:C49)*(1+$B75)^Extension!M18:M23)+SUMPRODUCT((Extension!G93:G98-Extension!C93:C98>0)*(Extension!G93:G98-Extension!C93:C98)*(1+$B75)^Extension!M67:M72)+SUMPRODUCT((Extension!G142:G147-Extension!C142:C147>0)*(Extension!G142:G147-Extension!C142:C147)*(1+$B75)^Extension!M116:M121) -> 14203.997 | J75: =$C$26 -> 11089.137 | K75: =$C$27 -> 13729.408
B76: 0.0925 | C76: =SUMPRODUCT((Extension!E44:E49-Extension!C44:C49>0)*(Extension!E44:E49-Extension!C44:C49)*(1+$B76)^Extension!M18:M23)+SUMPRODUCT((Extension!E93:E98-Extension!C93:C98>0)*(Extension!E93:E98-Extension!C93:C98)*(1+$B76)^Extension!M67:M72)+SUMPRODUCT((Extension!E142:E147-Extension!C142:C147>0)*(Extension!E142:E147-Extension!C142:C147)*(1+$B76)^Extension!M116:M121) -> 14179.745 | D76: =SUMPRODUCT((Extension!F44:F49-Extension!C44:C49>0)*(Extension!F44:F49-Extension!C44:C49)*(1+$B76)^Extension!M18:M23)+SUMPRODUCT((Extension!F93:F98-Extension!C93:C98>0)*(Extension!F93:F98-Extension!C93:C98)*(1+$B76)^Extension!M67:M72)+SUMPRODUCT((Extension!F142:F147-Extension!C142:C147>0)*(Extension!F142:F147-Extension!C142:C147)*(1+$B76)^Extension!M116:M121) -> 13864.005 | E76: =SUMPRODUCT((Extension!G44:G49-Extension!C44:C49>0)*(Extension!G44:G49-Extension!C44:C49)*(1+$B76)^Extension!M18:M23)+SUMPRODUCT((Extension!G93:G98-Extension!C93:C98>0)*(Extension!G93:G98-Extension!C93:C98)*(1+$B76)^Extension!M67:M72)+SUMPRODUCT((Extension!G142:G147-Extension!C142:C147>0)*(Extension!G142:G147-Extension!C142:C147)*(1+$B76)^Extension!M116:M121) -> 14278.765 | J76: =$C$26 -> 11089.137 | K76: =$C$27 -> 13729.408
B77: 0.095 | C77: =SUMPRODUCT((Extension!E44:E49-Extension!C44:C49>0)*(Extension!E44:E49-Extension!C44:C49)*(1+$B77)^Extension!M18:M23)+SUMPRODUCT((Extension!E93:E98-Extension!C93:C98>0)*(Extension!E93:E98-Extension!C93:C98)*(1+$B77)^Extension!M67:M72)+SUMPRODUCT((Extension!E142:E147-Extension!C142:C147>0)*(Extension!E142:E147-Extension!C142:C147)*(1+$B77)^Extension!M116:M121) -> 14254.123 | D77: =SUMPRODUCT((Extension!F44:F49-Extension!C44:C49>0)*(Extension!F44:F49-Extension!C44:C49)*(1+$B77)^Extension!M18:M23)+SUMPRODUCT((Extension!F93:F98-Extension!C93:C98>0)*(Extension!F93:F98-Extension!C93:C98)*(1+$B77)^Extension!M67:M72)+SUMPRODUCT((Extension!F142:F147-Extension!C142:C147>0)*(Extension!F142:F147-Extension!C142:C147)*(1+$B77)^Extension!M116:M121) -> 13936.549 | E77: =SUMPRODUCT((Extension!G44:G49-Extension!C44:C49>0)*(Extension!G44:G49-Extension!C44:C49)*(1+$B77)^Extension!M18:M23)+SUMPRODUCT((Extension!G93:G98-Extension!C93:C98>0)*(Extension!G93:G98-Extension!C93:C98)*(1+$B77)^Extension!M67:M72)+SUMPRODUCT((Extension!G142:G147-Extension!C142:C147>0)*(Extension!G142:G147-Extension!C142:C147)*(1+$B77)^Extension!M116:M121) -> 14353.757 | J77: =$C$26 -> 11089.137 | K77: =$C$27 -> 13729.408
B78: 0.0975 | C78: =SUMPRODUCT((Extension!E44:E49-Extension!C44:C49>0)*(Extension!E44:E49-Extension!C44:C49)*(1+$B78)^Extension!M18:M23)+SUMPRODUCT((Extension!E93:E98-Extension!C93:C98>0)*(Extension!E93:E98-Extension!C93:C98)*(1+$B78)^Extension!M67:M72)+SUMPRODUCT((Extension!E142:E147-Extension!C142:C147>0)*(Extension!E142:E147-Extension!C142:C147)*(1+$B78)^Extension!M116:M121) -> 14328.724 | D78: =SUMPRODUCT((Extension!F44:F49-Extension!C44:C49>0)*(Extension!F44:F49-Extension!C44:C49)*(1+$B78)^Extension!M18:M23)+SUMPRODUCT((Extension!F93:F98-Extension!C93:C98>0)*(Extension!F93:F98-Extension!C93:C98)*(1+$B78)^Extension!M67:M72)+SUMPRODUCT((Extension!F142:F147-Extension!C142:C147>0)*(Extension!F142:F147-Extension!C142:C147)*(1+$B78)^Extension!M116:M121) -> 14009.308 | E78: =SUMPRODUCT((Extension!G44:G49-Extension!C44:C49>0)*(Extension!G44:G49-Extension!C44:C49)*(1+$B78)^Extension!M18:M23)+SUMPRODUCT((Extension!G93:G98-Extension!C93:C98>0)*(Extension!G93:G98-Extension!C93:C98)*(1+$B78)^Extension!M67:M72)+SUMPRODUCT((Extension!G142:G147-Extension!C142:C147>0)*(Extension!G142:G147-Extension!C142:C147)*(1+$B78)^Extension!M116:M121) -> 14428.975 | J78: =$C$26 -> 11089.137 | K78: =$C$27 -> 13729.408
B79: 0.1 | C79: =SUMPRODUCT((Extension!E44:E49-Extension!C44:C49>0)*(Extension!E44:E49-Extension!C44:C49)*(1+$B79)^Extension!M18:M23)+SUMPRODUCT((Extension!E93:E98-Extension!C93:C98>0)*(Extension!E93:E98-Extension!C93:C98)*(1+$B79)^Extension!M67:M72)+SUMPRODUCT((Extension!E142:E147-Extension!C142:C147>0)*(Extension!E142:E147-Extension!C142:C147)*(1+$B79)^Extension!M116:M121) -> 14403.548 | D79: =SUMPRODUCT((Extension!F44:F49-Extension!C44:C49>0)*(Extension!F44:F49-Extension!C44:C49)*(1+$B79)^Extension!M18:M23)+SUMPRODUCT((Extension!F93:F98-Extension!C93:C98>0)*(Extension!F93:F98-Extension!C93:C98)*(1+$B79)^Extension!M67:M72)+SUMPRODUCT((Extension!F142:F147-Extension!C142:C147>0)*(Extension!F142:F147-Extension!C142:C147)*(1+$B79)^Extension!M116:M121) -> 14082.285 | E79: =SUMPRODUCT((Extension!G44:G49-Extension!C44:C49>0)*(Extension!G44:G49-Extension!C44:C49)*(1+$B79)^Extension!M18:M23)+SUMPRODUCT((Extension!G93:G98-Extension!C93:C98>0)*(Extension!G93:G98-Extension!C93:C98)*(1+$B79)^Extension!M67:M72)+SUMPRODUCT((Extension!G142:G147-Extension!C142:C147>0)*(Extension!G142:G147-Extension!C142:C147)*(1+$B79)^Extension!M116:M121) -> 14504.418 | J79: =$C$26 -> 11089.137 | K79: =$C$27 -> 13729.408
B80: 0.1025 | C80: =SUMPRODUCT((Extension!E44:E49-Extension!C44:C49>0)*(Extension!E44:E49-Extension!C44:C49)*(1+$B80)^Extension!M18:M23)+SUMPRODUCT((Extension!E93:E98-Extension!C93:C98>0)*(Extension!E93:E98-Extension!C93:C98)*(1+$B80)^Extension!M67:M72)+SUMPRODUCT((Extension!E142:E147-Extension!C142:C147>0)*(Extension!E142:E147-Extension!C142:C147)*(1+$B80)^Extension!M116:M121) -> 14478.595 | D80: =SUMPRODUCT((Extension!F44:F49-Extension!C44:C49>0)*(Extension!F44:F49-Extension!C44:C49)*(1+$B80)^Extension!M18:M23)+SUMPRODUCT((Extension!F93:F98-Extension!C93:C98>0)*(Extension!F93:F98-Extension!C93:C98)*(1+$B80)^Extension!M67:M72)+SUMPRODUCT((Extension!F142:F147-Extension!C142:C147>0)*(Extension!F142:F147-Extension!C142:C147)*(1+$B80)^Extension!M116:M121) -> 14155.479 | E80: =SUMPRODUCT((Extension!G44:G49-Extension!C44:C49>0)*(Extension!G44:G49-Extension!C44:C49)*(1+$B80)^Extension!M18:M23)+SUMPRODUCT((Extension!G93:G98-Extension!C93:C98>0)*(Extension!G93:G98-Extension!C93:C98)*(1+$B80)^Extension!M67:M72)+SUMPRODUCT((Extension!G142:G147-Extension!C142:C147>0)*(Extension!G142:G147-Extension!C142:C147)*(1+$B80)^Extension!M116:M121) -> 14580.087 | J80: =$C$26 -> 11089.137 | K80: =$C$27 -> 13729.408
B81: 0.105 | C81: =SUMPRODUCT((Extension!E44:E49-Extension!C44:C49>0)*(Extension!E44:E49-Extension!C44:C49)*(1+$B81)^Extension!M18:M23)+SUMPRODUCT((Extension!E93:E98-Extension!C93:C98>0)*(Extension!E93:E98-Extension!C93:C98)*(1+$B81)^Extension!M67:M72)+SUMPRODUCT((Extension!E142:E147-Extension!C142:C147>0)*(Extension!E142:E147-Extension!C142:C147)*(1+$B81)^Extension!M116:M121) -> 14553.866 | D81: =SUMPRODUCT((Extension!F44:F49-Extension!C44:C49>0)*(Extension!F44:F49-Extension!C44:C49)*(1+$B81)^Extension!M18:M23)+SUMPRODUCT((Extension!F93:F98-Extension!C93:C98>0)*(Extension!F93:F98-Extension!C93:C98)*(1+$B81)^Extension!M67:M72)+SUMPRODUCT((Extension!F142:F147-Extension!C142:C147>0)*(Extension!F142:F147-Extension!C142:C147)*(1+$B81)^Extension!M116:M121) -> 14228.89 | E81: =SUMPRODUCT((Extension!G44:G49-Extension!C44:C49>0)*(Extension!G44:G49-Extension!C44:C49)*(1+$B81)^Extension!M18:M23)+SUMPRODUCT((Extension!G93:G98-Extension!C93:C98>0)*(Extension!G93:G98-Extension!C93:C98)*(1+$B81)^Extension!M67:M72)+SUMPRODUCT((Extension!G142:G147-Extension!C142:C147>0)*(Extension!G142:G147-Extension!C142:C147)*(1+$B81)^Extension!M116:M121) -> 14655.982 | J81: =$C$26 -> 11089.137 | K81: =$C$27 -> 13729.408
B82: 0.1075 | C82: =SUMPRODUCT((Extension!E44:E49-Extension!C44:C49>0)*(Extension!E44:E49-Extension!C44:C49)*(1+$B82)^Extension!M18:M23)+SUMPRODUCT((Extension!E93:E98-Extension!C93:C98>0)*(Extension!E93:E98-Extension!C93:C98)*(1+$B82)^Extension!M67:M72)+SUMPRODUCT((Extension!E142:E147-Extension!C142:C147>0)*(Extension!E142:E147-Extension!C142:C147)*(1+$B82)^Extension!M116:M121) -> 14629.361 | D82: =SUMPRODUCT((Extension!F44:F49-Extension!C44:C49>0)*(Extension!F44:F49-Extension!C44:C49)*(1+$B82)^Extension!M18:M23)+SUMPRODUCT((Extension!F93:F98-Extension!C93:C98>0)*(Extension!F93:F98-Extension!C93:C98)*(1+$B82)^Extension!M67:M72)+SUMPRODUCT((Extension!F142:F147-Extension!C142:C147>0)*(Extension!F142:F147-Extension!C142:C147)*(1+$B82)^Extension!M116:M121) -> 14302.518 | E82: =SUMPRODUCT((Extension!G44:G49-Extension!C44:C49>0)*(Extension!G44:G49-Extension!C44:C49)*(1+$B82)^Extension!M18:M23)+SUMPRODUCT((Extension!G93:G98-Extension!C93:C98>0)*(Extension!G93:G98-Extension!C93:C98)*(1+$B82)^Extension!M67:M72)+SUMPRODUCT((Extension!G142:G147-Extension!C142:C147>0)*(Extension!G142:G147-Extension!C142:C147)*(1+$B82)^Extension!M116:M121) -> 14732.103 | J82: =$C$26 -> 11089.137 | K82: =$C$27 -> 13729.408
B83: 0.11 | C83: =SUMPRODUCT((Extension!E44:E49-Extension!C44:C49>0)*(Extension!E44:E49-Extension!C44:C49)*(1+$B83)^Extension!M18:M23)+SUMPRODUCT((Extension!E93:E98-Extension!C93:C98>0)*(Extension!E93:E98-Extension!C93:C98)*(1+$B83)^Extension!M67:M72)+SUMPRODUCT((Extension!E142:E147-Extension!C142:C147>0)*(Extension!E142:E147-Extension!C142:C147)*(1+$B83)^Extension!M116:M121) -> 14705.079 | D83: =SUMPRODUCT((Extension!F44:F49-Extension!C44:C49>0)*(Extension!F44:F49-Extension!C44:C49)*(1+$B83)^Extension!M18:M23)+SUMPRODUCT((Extension!F93:F98-Extension!C93:C98>0)*(Extension!F93:F98-Extension!C93:C98)*(1+$B83)^Extension!M67:M72)+SUMPRODUCT((Extension!F142:F147-Extension!C142:C147>0)*(Extension!F142:F147-Extension!C142:C147)*(1+$B83)^Extension!M116:M121) -> 14376.364 | E83: =SUMPRODUCT((Extension!G44:G49-Extension!C44:C49>0)*(Extension!G44:G49-Extension!C44:C49)*(1+$B83)^Extension!M18:M23)+SUMPRODUCT((Extension!G93:G98-Extension!C93:C98>0)*(Extension!G93:G98-Extension!C93:C98)*(1+$B83)^Extension!M67:M72)+SUMPRODUCT((Extension!G142:G147-Extension!C142:C147>0)*(Extension!G142:G147-Extension!C142:C147)*(1+$B83)^Extension!M116:M121) -> 14808.45 | J83: =$C$26 -> 11089.137 | K83: =$C$27 -> 13729.408
B84: 0.1125 | C84: =SUMPRODUCT((Extension!E44:E49-Extension!C44:C49>0)*(Extension!E44:E49-Extension!C44:C49)*(1+$B84)^Extension!M18:M23)+SUMPRODUCT((Extension!E93:E98-Extension!C93:C98>0)*(Extension!E93:E98-Extension!C93:C98)*(1+$B84)^Extension!M67:M72)+SUMPRODUCT((Extension!E142:E147-Extension!C142:C147>0)*(Extension!E142:E147-Extension!C142:C147)*(1+$B84)^Extension!M116:M121) -> 14781.022 | D84: =SUMPRODUCT((Extension!F44:F49-Extension!C44:C49>0)*(Extension!F44:F49-Extension!C44:C49)*(1+$B84)^Extension!M18:M23)+SUMPRODUCT((Extension!F93:F98-Extension!C93:C98>0)*(Extension!F93:F98-Extension!C93:C98)*(1+$B84)^Extension!M67:M72)+SUMPRODUCT((Extension!F142:F147-Extension!C142:C147>0)*(Extension!F142:F147-Extension!C142:C147)*(1+$B84)^Extension!M116:M121) -> 14450.428 | E84: =SUMPRODUCT((Extension!G44:G49-Extension!C44:C49>0)*(Extension!G44:G49-Extension!C44:C49)*(1+$B84)^Extension!M18:M23)+SUMPRODUCT((Extension!G93:G98-Extension!C93:C98>0)*(Extension!G93:G98-Extension!C93:C98)*(1+$B84)^Extension!M67:M72)+SUMPRODUCT((Extension!G142:G147-Extension!C142:C147>0)*(Extension!G142:G147-Extension!C142:C147)*(1+$B84)^Extension!M116:M121) -> 14885.024 | J84: =$C$26 -> 11089.137 | K84: =$C$27 -> 13729.408
B85: 0.115 | C85: =SUMPRODUCT((Extension!E44:E49-Extension!C44:C49>0)*(Extension!E44:E49-Extension!C44:C49)*(1+$B85)^Extension!M18:M23)+SUMPRODUCT((Extension!E93:E98-Extension!C93:C98>0)*(Extension!E93:E98-Extension!C93:C98)*(1+$B85)^Extension!M67:M72)+SUMPRODUCT((Extension!E142:E147-Extension!C142:C147>0)*(Extension!E142:E147-Extension!C142:C147)*(1+$B85)^Extension!M116:M121) -> 14857.188 | D85: =SUMPRODUCT((Extension!F44:F49-Extension!C44:C49>0)*(Extension!F44:F49-Extension!C44:C49)*(1+$B85)^Extension!M18:M23)+SUMPRODUCT((Extension!F93:F98-Extension!C93:C98>0)*(Extension!F93:F98-Extension!C93:C98)*(1+$B85)^Extension!M67:M72)+SUMPRODUCT((Extension!F142:F147-Extension!C142:C147>0)*(Extension!F142:F147-Extension!C142:C147)*(1+$B85)^Extension!M116:M121) -> 14524.709 | E85: =SUMPRODUCT((Extension!G44:G49-Extension!C44:C49>0)*(Extension!G44:G49-Extension!C44:C49)*(1+$B85)^Extension!M18:M23)+SUMPRODUCT((Extension!G93:G98-Extension!C93:C98>0)*(Extension!G93:G98-Extension!C93:C98)*(1+$B85)^Extension!M67:M72)+SUMPRODUCT((Extension!G142:G147-Extension!C142:C147>0)*(Extension!G142:G147-Extension!C142:C147)*(1+$B85)^Extension!M116:M121) -> 14961.824 | J85: =$C$26 -> 11089.137 | K85: =$C$27 -> 13729.408
B86: 0.1175 | C86: =SUMPRODUCT((Extension!E44:E49-Extension!C44:C49>0)*(Extension!E44:E49-Extension!C44:C49)*(1+$B86)^Extension!M18:M23)+SUMPRODUCT((Extension!E93:E98-Extension!C93:C98>0)*(Extension!E93:E98-Extension!C93:C98)*(1+$B86)^Extension!M67:M72)+SUMPRODUCT((Extension!E142:E147-Extension!C142:C147>0)*(Extension!E142:E147-Extension!C142:C147)*(1+$B86)^Extension!M116:M121) -> 14933.579 | D86: =SUMPRODUCT((Extension!F44:F49-Extension!C44:C49>0)*(Extension!F44:F49-Extension!C44:C49)*(1+$B86)^Extension!M18:M23)+SUMPRODUCT((Extension!F93:F98-Extension!C93:C98>0)*(Extension!F93:F98-Extension!C93:C98)*(1+$B86)^Extension!M67:M72)+SUMPRODUCT((Extension!F142:F147-Extension!C142:C147>0)*(Extension!F142:F147-Extension!C142:C147)*(1+$B86)^Extension!M116:M121) -> 14599.209 | E86: =SUMPRODUCT((Extension!G44:G49-Extension!C44:C49>0)*(Extension!G44:G49-Extension!C44:C49)*(1+$B86)^Extension!M18:M23)+SUMPRODUCT((Extension!G93:G98-Extension!C93:C98>0)*(Extension!G93:G98-Extension!C93:C98)*(1+$B86)^Extension!M67:M72)+SUMPRODUCT((Extension!G142:G147-Extension!C142:C147>0)*(Extension!G142:G147-Extension!C142:C147)*(1+$B86)^Extension!M116:M121) -> 15038.851 | J86: =$C$26 -> 11089.137 | K86: =$C$27 -> 13729.408
B87: 0.12 | C87: =SUMPRODUCT((Extension!E44:E49-Extension!C44:C49>0)*(Extension!E44:E49-Extension!C44:C49)*(1+$B87)^Extension!M18:M23)+SUMPRODUCT((Extension!E93:E98-Extension!C93:C98>0)*(Extension!E93:E98-Extension!C93:C98)*(1+$B87)^Extension!M67:M72)+SUMPRODUCT((Extension!E142:E147-Extension!C142:C147>0)*(Extension!E142:E147-Extension!C142:C147)*(1+$B87)^Extension!M116:M121) -> 15010.195 | D87: =SUMPRODUCT((Extension!F44:F49-Extension!C44:C49>0)*(Extension!F44:F49-Extension!C44:C49)*(1+$B87)^Extension!M18:M23)+SUMPRODUCT((Extension!F93:F98-Extension!C93:C98>0)*(Extension!F93:F98-Extension!C93:C98)*(1+$B87)^Extension!M67:M72)+SUMPRODUCT((Extension!F142:F147-Extension!C142:C147>0)*(Extension!F142:F147-Extension!C142:C147)*(1+$B87)^Extension!M116:M121) -> 14673.927 | E87: =SUMPRODUCT((Extension!G44:G49-Extension!C44:C49>0)*(Extension!G44:G49-Extension!C44:C49)*(1+$B87)^Extension!M18:M23)+SUMPRODUCT((Extension!G93:G98-Extension!C93:C98>0)*(Extension!G93:G98-Extension!C93:C98)*(1+$B87)^Extension!M67:M72)+SUMPRODUCT((Extension!G142:G147-Extension!C142:C147>0)*(Extension!G142:G147-Extension!C142:C147)*(1+$B87)^Extension!M116:M121) -> 15116.105 | J87: =$C$26 -> 11089.137 | K87: =$C$27 -> 13729.408
B89: Break-even rates of additional claims inflation, by basis
B90: For each basis, the break-even rate is read off that basis’s own column above by INDEX and MATCH, with linear interpolation between the two bracketing rows, and tested against that basis’s own attachment and exhaustion points.
C92: Chain Ladder | D92: Expected Claims | E92: Bornhuetter-Ferguson
B93: Shock at which the cover begins to respond (attachment) | C93: =IF(INDEX($C$39:$C$87,1)>=C$10,0,INDEX($B$39:$B$87,MATCH(C$10,$C$39:$C$87,1))+(C$10-INDEX($C$39:$C$87,MATCH(C$10,$C$39:$C$87,1)))/(INDEX($C$39:$C$87,MATCH(C$10,$C$39:$C$87,1)+1)-INDEX($C$39:$C$87,MATCH(C$10,$C$39:$C$87,1)))*(INDEX($B$39:$B$87,MATCH(C$10,$C$39:$C$87,1)+1)-INDEX($B$39:$B$87,MATCH(C$10,$C$39:$C$87,1)))) -> 0 | D93: =IF(INDEX($D$39:$D$87,1)>=D$10,0,INDEX($B$39:$B$87,MATCH(D$10,$D$39:$D$87,1))+(D$10-INDEX($D$39:$D$87,MATCH(D$10,$D$39:$D$87,1)))/(INDEX($D$39:$D$87,MATCH(D$10,$D$39:$D$87,1)+1)-INDEX($D$39:$D$87,MATCH(D$10,$D$39:$D$87,1)))*(INDEX($B$39:$B$87,MATCH(D$10,$D$39:$D$87,1)+1)-INDEX($B$39:$B$87,MATCH(D$10,$D$39:$D$87,1)))) -> 0 | E93: =IF(INDEX($E$39:$E$87,1)>=E$10,0,INDEX($B$39:$B$87,MATCH(E$10,$E$39:$E$87,1))+(E$10-INDEX($E$39:$E$87,MATCH(E$10,$E$39:$E$87,1)))/(INDEX($E$39:$E$87,MATCH(E$10,$E$39:$E$87,1)+1)-INDEX($E$39:$E$87,MATCH(E$10,$E$39:$E$87,1)))*(INDEX($B$39:$B$87,MATCH(E$10,$E$39:$E$87,1)+1)-INDEX($B$39:$B$87,MATCH(E$10,$E$39:$E$87,1)))) -> 0
B94: Shock at which the cover is exhausted | C94: =IF(INDEX($C$39:$C$87,1)>=C$11,0,INDEX($B$39:$B$87,MATCH(C$11,$C$39:$C$87,1))+(C$11-INDEX($C$39:$C$87,MATCH(C$11,$C$39:$C$87,1)))/(INDEX($C$39:$C$87,MATCH(C$11,$C$39:$C$87,1)+1)-INDEX($C$39:$C$87,MATCH(C$11,$C$39:$C$87,1)))*(INDEX($B$39:$B$87,MATCH(C$11,$C$39:$C$87,1)+1)-INDEX($B$39:$B$87,MATCH(C$11,$C$39:$C$87,1)))) -> 0.067160734 | D94: =IF(INDEX($D$39:$D$87,1)>=D$11,0,INDEX($B$39:$B$87,MATCH(D$11,$D$39:$D$87,1))+(D$11-INDEX($D$39:$D$87,MATCH(D$11,$D$39:$D$87,1)))/(INDEX($D$39:$D$87,MATCH(D$11,$D$39:$D$87,1)+1)-INDEX($D$39:$D$87,MATCH(D$11,$D$39:$D$87,1)))*(INDEX($B$39:$B$87,MATCH(D$11,$D$39:$D$87,1)+1)-INDEX($B$39:$B$87,MATCH(D$11,$D$39:$D$87,1)))) -> 0.088348096 | E94: =IF(INDEX($E$39:$E$87,1)>=E$11,0,INDEX($B$39:$B$87,MATCH(E$11,$E$39:$E$87,1))+(E$11-INDEX($E$39:$E$87,MATCH(E$11,$E$39:$E$87,1)))/(INDEX($E$39:$E$87,MATCH(E$11,$E$39:$E$87,1)+1)-INDEX($E$39:$E$87,MATCH(E$11,$E$39:$E$87,1)))*(INDEX($B$39:$B$87,MATCH(E$11,$E$39:$E$87,1)+1)-INDEX($B$39:$B$87,MATCH(E$11,$E$39:$E$87,1)))) -> 0.073951369
B95: Reserve with the tail factor but no inflation shock (£000) | C95: =C39 -> 11582.846 | D95: =D39 -> 11330.66 | E95: =E39 -> 11660.758
B96: Shock assumed in the extension scenario | C96: =Ext_shock -> 0.04
B97: Check: for every basis, the break-even rates lie inside the tabulated range and are correctly ordered | C97: =IF(SUMPRODUCT(--(C93:E93<$B$39))+SUMPRODUCT(--(C94:E94>$B$87))+SUMPRODUCT(--(C93:E93>C94:E94))=0,"OK","REVIEW") -> OK
B100: Recommended basis - break-even summary
B101: Shock at which the cover begins to respond (attachment) | C101: =INDEX($C$93:$E$94,MATCH($B101,$B$93:$B$94,0),MATCH($C$21,$C$8:$E$8,0)) -> 0
B102: Shock at which the cover is exhausted | C102: =INDEX($C$93:$E$94,MATCH($B102,$B$93:$B$94,0),MATCH($C$21,$C$8:$E$8,0)) -> 0.073951369

Sheet Summary
B1: Summary of Results
B2: All figures in GBP thousands unless shown as a percentage. Reserve means the total unpaid claim liability at 31 December 2025, being ultimate claims less claims paid to date.
B4: Table A: Reserve by rating group and basis - base scenarios (£000)
B5: Rating group | C5: Chain Ladder | D5: Expected Claims | E5: Bornhuetter-Ferguson
B6: Group A | C6: ='S1 Chain Ladder'!G13 -> 3967.3642 | D6: ='S2 Expected Claims'!H14 -> 3892.5162 | E6: ='S3 BF'!H14 -> 3953.1084
B7: Group B | C7: ='S1 Chain Ladder'!G26 -> 3478.3681 | D7: ='S2 Expected Claims'!H27 -> 3635.0732 | E7: ='S3 BF'!H27 -> 3532.9965
B8: Group C | C8: ='S1 Chain Ladder'!G39 -> 2891.519 | D8: ='S2 Expected Claims'!H40 -> 3044.7423 | E8: ='S3 BF'!H40 -> 3074.9783
B9: Portfolio total | C9: =SUM(C6:C8) -> 10337.251 | D9: =SUM(D6:D8) -> 10572.332 | E9: =SUM(E6:E8) -> 10561.083
B12: Table B: Reserve by rating group and basis - extension scenario (£000)
B13: Rating group | C13: Chain Ladder | D13: Expected Claims | E13: Bornhuetter-Ferguson
B14: Group A | C14: =Extension!K50 -> 4540.3257 | D14: =Extension!L50 -> 4440.0614 | E14: =Extension!M50 -> 4520.2831
B15: Group B | C15: =Extension!K99 -> 4333.3883 | D15: =Extension!L99 -> 4318.5878 | E15: =Extension!M99 -> 4346.3449
B16: Group C | C16: =Extension!K148 -> 3795.2787 | D16: =Extension!L148 -> 3625.8985 | E16: =Extension!M148 -> 3889.0184
B17: Portfolio total | C17: =SUM(C14:C16) -> 12668.993 | D17: =SUM(D14:D16) -> 12384.548 | E17: =SUM(E14:E16) -> 12755.646
B20: Table C: Effect of the extension scenario on the portfolio reserve
B21: Reserving basis | C21: Base reserve (£000) | D21: Extension reserve (£000) | E21: Increase (£000) | F21: Increase (%)
B22: Chain Ladder | C22: =C9 -> 10337.251 | D22: =C17 -> 12668.993 | E22: =D22-C22 -> 2331.7413 | F22: =E22/C22 -> 0.22556686
B23: Expected Claims | C23: =D9 -> 10572.332 | D23: =D17 -> 12384.548 | E23: =D23-C23 -> 1812.2161 | F23: =E23/C23 -> 0.1714112
B24: Bornhuetter-Ferguson | C24: =E9 -> 10561.083 | D24: =E17 -> 12755.646 | E24: =D24-C24 -> 2194.5631 | F24: =E24/C24 -> 0.20779716
B26: Range across the three bases (£000) | C26: =MAX(C22:C24)-MIN(C22:C24) -> 235.08031 | D26: =MAX(D22:D24)-MIN(D22:D24) -> 371.09861
B28: Table D: Ultimate loss ratio by accident year - Bornhuetter-Ferguson basis
B29: Ultimate claims divided by earned premium, at the rate level actually charged in each accident year.
B30: Accident year | C30: Group A base | D30: Group B base | E30: Group C base | F30: Group A extension | G30: Group B extension | H30: Group C extension
B31: 2020 | C31: ='S3 BF'!G8/'Raw Data'!C63 -> 0.57916667 | D31: ='S3 BF'!G21/'Raw Data'!D63 -> 0.59719355 | E31: ='S3 BF'!G34/'Raw Data'!E63 -> 0.72233333 | F31: =Extension!J44/'Raw Data'!C63 -> 0.58687334 | G31: =Extension!J93/'Raw Data'!D63 -> 0.62061988 | H31: =Extension!J142/'Raw Data'!E63 -> 0.76588337
B32: 2021 | C32: ='S3 BF'!G9/'Raw Data'!C64 -> 0.56991226 | D32: ='S3 BF'!G22/'Raw Data'!D64 -> 0.6612766 | E32: ='S3 BF'!G35/'Raw Data'!E64 -> 0.77761021 | F32: =Extension!J45/'Raw Data'!C64 -> 0.57932174 | G32: =Extension!J94/'Raw Data'!D64 -> 0.68793786 | H32: =Extension!J143/'Raw Data'!E64 -> 0.82705463
B33: 2022 | C33: ='S3 BF'!G10/'Raw Data'!C65 -> 0.67699407 | D33: ='S3 BF'!G23/'Raw Data'!D65 -> 0.70743205 | E33: ='S3 BF'!G36/'Raw Data'!E65 -> 0.88600258 | F33: =Extension!J46/'Raw Data'!C65 -> 0.6890395 | G33: =Extension!J95/'Raw Data'!D65 -> 0.7383515 | H33: =Extension!J144/'Raw Data'!E65 -> 0.94094536
B34: 2023 | C34: ='S3 BF'!G11/'Raw Data'!C66 -> 0.65102213 | D34: ='S3 BF'!G24/'Raw Data'!D66 -> 0.69463075 | E34: ='S3 BF'!G37/'Raw Data'!E66 -> 0.80375185 | F34: =Extension!J47/'Raw Data'!C66 -> 0.66737826 | G34: =Extension!J96/'Raw Data'!D66 -> 0.73066967 | H34: =Extension!J145/'Raw Data'!E66 -> 0.86436827
B35: 2024 | C35: ='S3 BF'!G12/'Raw Data'!C67 -> 0.62352738 | D35: ='S3 BF'!G25/'Raw Data'!D67 -> 0.68450271 | E35: ='S3 BF'!G38/'Raw Data'!E67 -> 0.76500635 | F35: =Extension!J48/'Raw Data'!C67 -> 0.64767927 | G35: =Extension!J97/'Raw Data'!D67 -> 0.72876829 | H35: =Extension!J146/'Raw Data'!E67 -> 0.83474521
B36: 2025 | C36: ='S3 BF'!G13/'Raw Data'!C68 -> 0.64024143 | D36: ='S3 BF'!G26/'Raw Data'!D68 -> 0.67283825 | E36: ='S3 BF'!G39/'Raw Data'!E68 -> 0.75080453 | F36: =Extension!J49/'Raw Data'!C68 -> 0.68027086 | G36: =Extension!J98/'Raw Data'!D68 -> 0.73440083 | H36: =Extension!J147/'Raw Data'!E68 -> 0.83915228
B38: Table E: Key metrics on the booked (Bornhuetter-Ferguson) basis
B39: Rating group | C39: Earned premium 2025 (£000) | D39: Reserve (£000) | E39: Reserve as % of 2025 premium | F39: Ultimate loss ratio 2025 | G39: Expense ratio | H39: Combined ratio 2025 | J39: 100% break-even
B40: Group A | C40: ='Raw Data'!C68 -> 5700 | D40: ='S3 BF'!H14 -> 3953.1084 | E40: =D40/C40 -> 0.6935278 | F40: ='S3 BF'!G13/C40 -> 0.64024143 | G40: =INDEX(Exp_ratio,1) -> 0.27 | H40: =F40+G40 -> 0.91024143 | J40: 1
B41: Group B | C41: ='Raw Data'!D68 -> 4150 | D41: ='S3 BF'!H27 -> 3532.9965 | E41: =D41/C41 -> 0.85132446 | F41: ='S3 BF'!G26/C41 -> 0.67283825 | G41: =INDEX(Exp_ratio,2) -> 0.255 | H41: =F41+G41 -> 0.92783825 | J41: 1
B42: Group C | C42: ='Raw Data'!E68 -> 2650 | D42: ='S3 BF'!H40 -> 3074.9783 | E42: =D42/C42 -> 1.1603692 | F42: ='S3 BF'!G39/C42 -> 0.75080453 | G42: =INDEX(Exp_ratio,3) -> 0.29 | H42: =F42+G42 -> 1.0408045 | J42: 1
B43: Portfolio | C43: =SUM(C40:C42) -> 12500 | D43: =SUM(D40:D42) -> 10561.083 | E43: =D43/C43 -> 0.84488666
B44: Check: the reserve on every basis is positive and below three times the 2025 earned premium | E44: =IF(AND(MIN(C9:E9)>0,MAX(C17:E17)<3*C43),"OK","REVIEW") -> OK
B47: Table F: Proportion of ultimate claims paid by development age - base scenarios
B48: Development age (months) | C48: Group A | D48: Group B | E48: Group C
B49: 12 | C49: ='Dev Factors'!C16 -> 0.41743527 | D49: ='Dev Factors'!C31 -> 0.33355569 | E49: ='Dev Factors'!C46 -> 0.25990132
B50: 24 | C50: ='Dev Factors'!D16 -> 0.6929805 | D50: ='Dev Factors'!D31 -> 0.63803078 | E50: ='Dev Factors'!D46 -> 0.54383176
B51: 36 | C51: ='Dev Factors'!E16 -> 0.84519271 | D51: ='Dev Factors'!E31 -> 0.81605801 | E51: ='Dev Factors'!E46 -> 0.72947301
B52: 48 | C52: ='Dev Factors'!F16 -> 0.92659806 | D52: ='Dev Factors'!F31 -> 0.90751402 | E52: ='Dev Factors'!F46 -> 0.89338087
B53: 60 | C53: ='Dev Factors'!G16 -> 0.96386434 | D53: ='Dev Factors'!G31 -> 0.98039216 | E53: ='Dev Factors'!G46 -> 0.95493001
B54: 72 | C54: ='Dev Factors'!H16 -> 1 | D54: ='Dev Factors'!H31 -> 1 | E54: ='Dev Factors'!H46 -> 1
B56: Table G: Adverse Development Cover, by reserving basis (each basis on its own layer terms)
B57: Metric | C57: Chain Ladder | D57: Expected Claims | E57: Bornhuetter-Ferguson
B58: Booked reserve, base scenario (£000) | C58: =ADC!C9 -> 10337.251 | D58: =ADC!D9 -> 10572.332 | E58: =ADC!E9 -> 10561.083
B59: Attachment point (£000) | C59: =ADC!C10 -> 10854.114 | D59: =ADC!D10 -> 11100.948 | E59: =ADC!E10 -> 11089.137
B60: Exhaustion point (£000) | C60: =ADC!C11 -> 13438.427 | D60: =ADC!D11 -> 13744.031 | E60: =ADC!E11 -> 13729.408
B61: Limit of cover (£000) | C61: =ADC!C12 -> 2584.3128 | D61: =ADC!D12 -> 2643.0829 | E61: =ADC!E12 -> 2640.2708
B62: Reinsurance premium payable (£000) | C62: =ADC!C13 -> 310.11754 | D62: =ADC!D13 -> 317.16995 | E62: =ADC!E13 -> 316.8325
B63: Extension scenario reserve (£000) | C63: =ADC!C14 -> 12668.993 | D63: =ADC!D14 -> 12384.548 | E63: =ADC!E14 -> 12755.646
B64: Recovery under the extension scenario (£000) | C64: =ADC!C15 -> 1814.8788 | D64: =ADC!D15 -> 1283.5995 | E64: =ADC!E15 -> 1666.509
B65: Net benefit of the cover (£000) | C65: =ADC!C16 -> 1504.7612 | D65: =ADC!D16 -> 966.42953 | E65: =ADC!E16 -> 1349.6765
B66: Additional claims inflation that would exhaust the cover | C66: =ADC!C94 -> 0.067160734 | D66: =ADC!D94 -> 0.088348096 | E66: =ADC!E94 -> 0.073951369
B67: Recommended basis for booking (see ADC sheet) | C67: =ADC!C21 -> Bornhuetter-Ferguson

Sheet Checks
B1: Consolidated Check Dashboard
B2: Every calculation stage in the model has at least one check. A check reads OK when it passes. The overall status below is the only cell that needs to be inspected before the model is relied upon; if it does not read ALL CHECKS PASS, the failing check is identified in the table.
B4: Overall status | C4: =IF(COUNTIF(E8:E42,"OK")+COUNTIF(E8:E42,"SEE NOTE")=35,"ALL CHECKS PASS","REVIEW REQUIRED - see table below") -> ALL CHECKS PASS
C5: =COUNTIF(E8:E42,"OK")&" of 35 checks read OK; "&COUNTIF(E8:E42,"SEE NOTE")&" flagged for narrative comment; "&(35-COUNTIF(E8:E42,"OK")-COUNTIF(E8:E42,"SEE NOTE"))&" require review." -> 34 of 35 checks read OK; 1 flagged for narrative comment; 0 require review.
B7: Ref | C7: Check | D7: Stage covered | E7: Result | F7: Source
B8: C1 | C8: Five cells are flagged in the paid triangles, arising from the four root defects documented in the Audit Trail: the order-of-magnitude error in Group C also causes the following cell to fail the monotonicity test | D8: Data validation | E8: =IF(SUM('Data Validation'!J18:O23)+SUM('Data Validation'!J34:O39)+SUM('Data Validation'!J50:O55)=5,"OK","REVIEW") -> OK | F8: Data Validation, flag grids
B9: C1b | C9: Exactly one defect is detected in the rate change history and a manual correction has been supplied for it | D9: Data validation | E9: =IF(AND(SUM('Data Validation'!G67:I72)=1,ISNUMBER('Data Validation'!D75)),"OK","REVIEW") -> OK | F9: Data Validation, rate table
B10: C2 | C10: No defect arises at 12 months development, where the correction rule cannot be applied | D10: Data validation | E10: =IF(SUM('Data Validation'!J18:J23)+SUM('Data Validation'!J34:J39)+SUM('Data Validation'!J50:J55)=0,"OK","REVIEW") -> OK | F10: Data Validation, flag grids
B11: C3 | C11: Every cell of the validated triangles holds a number | D11: Data validation | E11: =IF(COUNTIF('Data Validation'!X18:AC23,"CHECK C4")+COUNTIF('Data Validation'!X34:AC39,"CHECK C4")+COUNTIF('Data Validation'!X50:AC55,"CHECK C4")=0,"OK","REVIEW") -> OK | F11: Data Validation, validated triangles
B12: C4 | C12: Validated cumulative paid claims never fall as development age increases | D12: Data validation | E12: =IF(COUNTIF('Dev Factors'!C8:G12,"<1")+COUNTIF('Dev Factors'!C23:G27,"<1")+COUNTIF('Dev Factors'!C38:G42,"<1")=0,"OK","REVIEW") -> OK | F12: Dev Factors, factor grids
B13: C5 | C13: Every validated rate change lies within the plausible bounds | D13: Data validation | E13: =IF(COUNTIF('Data Validation'!K67:M72,"<"&Val_rate_min)+COUNTIF('Data Validation'!K67:M72,">"&Val_rate_max)=0,"OK","REVIEW") -> OK | F13: Data Validation, rate table
B14: C6A | C14: Group A: selected development factors are at least 1.0000 and non-increasing | D14: Development factors | E14: ='Dev Factors'!H17 -> OK | F14: Dev Factors H17
B15: C6B | C15: Group B: selected development factors are at least 1.0000 and non-increasing | D15: Development factors | E15: ='Dev Factors'!H32 -> OK | F15: Dev Factors H32
B16: C6C | C16: Group C: selected development factors are at least 1.0000 and non-increasing | D16: Development factors | E16: ='Dev Factors'!H47 -> OK | F16: Dev Factors H47
B17: C7A | C17: Group A: the on-level factor for the latest accident year equals 1.0000 | D17: On-levelling | E17: ='On-Level & Cred'!C25 -> OK | F17: On-Level & Cred C25
B18: C7B | C18: Group B: the on-level factor for the latest accident year equals 1.0000 | D18: On-levelling | E18: ='On-Level & Cred'!C47 -> OK | F18: On-Level & Cred C47
B19: C7C | C19: Group C: the on-level factor for the latest accident year equals 1.0000 | D19: On-levelling | E19: ='On-Level & Cred'!C69 -> OK | F19: On-Level & Cred C69
B20: C8A | C20: Group A: credibility factor lies in [0,1] and the a priori lies between the indication and the plan | D20: Credibility | E20: ='On-Level & Cred'!C24 -> OK | F20: On-Level & Cred C24
B21: C8B | C21: Group B: credibility factor lies in [0,1] and the a priori lies between the indication and the plan | D21: Credibility | E21: ='On-Level & Cred'!C46 -> OK | F21: On-Level & Cred C46
B22: C8C | C22: Group C: credibility factor lies in [0,1] and the a priori lies between the indication and the plan | D22: Credibility | E22: ='On-Level & Cred'!C68 -> OK | F22: On-Level & Cred C68
B23: C9A | C23: Group A: every Chain Ladder ultimate is at least the claims already paid | D23: Scenario 1 | E23: ='S1 Chain Ladder'!F14 -> OK | F23: S1 Chain Ladder F14
B24: C9B | C24: Group B: every Chain Ladder ultimate is at least the claims already paid | D24: Scenario 1 | E24: ='S1 Chain Ladder'!F27 -> OK | F24: S1 Chain Ladder F27
B25: C9C | C25: Group C: every Chain Ladder ultimate is at least the claims already paid | D25: Scenario 1 | E25: ='S1 Chain Ladder'!F40 -> OK | F25: S1 Chain Ladder F40
B26: C10A | C26: Group A: accident years where the Expected Claims ultimate falls below paid to date | D26: Scenario 2 | E26: ='S2 Expected Claims'!F15 -> SEE NOTE | F26: S2 Expected Claims F15
B27: C10B | C27: Group B: accident years where the Expected Claims ultimate falls below paid to date | D27: Scenario 2 | E27: ='S2 Expected Claims'!F28 -> OK | F27: S2 Expected Claims F28
B28: C10C | C28: Group C: accident years where the Expected Claims ultimate falls below paid to date | D28: Scenario 2 | E28: ='S2 Expected Claims'!F41 -> OK | F28: S2 Expected Claims F41
B29: C11A | C29: Group A: in every accident year the BF ultimate lies between the other two bases | D29: Scenario 3 | E29: ='S3 BF'!G15 -> OK | F29: S3 BF G15
B30: C11B | C30: Group B: in every accident year the BF ultimate lies between the other two bases | D30: Scenario 3 | E30: ='S3 BF'!G28 -> OK | F30: S3 BF G28
B31: C11C | C31: Group C: in every accident year the BF ultimate lies between the other two bases | D31: Scenario 3 | E31: ='S3 BF'!G41 -> OK | F31: S3 BF G41
B32: C12A | C32: Group A: every extension ultimate is at least the corresponding base ultimate | D32: Extension | E32: =Extension!H51 -> OK | F32: Extension H51
B33: C12B | C33: Group B: every extension ultimate is at least the corresponding base ultimate | D33: Extension | E33: =Extension!H100 -> OK | F33: Extension H100
B34: C12C | C34: Group C: every extension ultimate is at least the corresponding base ultimate | D34: Extension | E34: =Extension!H149 -> OK | F34: Extension H149
B35: C13 | C35: Reduction test: the extension Chain Ladder ultimate before the inflation uplift equals the base ultimate multiplied by the tail factor, so that setting the tail to 1.0000 and the shock to zero reproduces the base scenarios | D35: Extension | E35: =IF(SUMPRODUCT(--(ABS(Extension!E44:E49-'S1 Chain Ladder'!F7:F12*INDEX(Ext_tail,1))>0.001))+SUMPRODUCT(--(ABS(Extension!E93:E98-'S1 Chain Ladder'!F20:F25*INDEX(Ext_tail,2))>0.001))+SUMPRODUCT(--(ABS(Extension!E142:E147-'S1 Chain Ladder'!F33:F38*INDEX(Ext_tail,3))>0.001))=0,"OK","REVIEW") -> OK | F35: Extension, step E4
B36: C13b | C36: The revised payment pattern is complete: the proportion paid at 12 months, plus every later increment, plus the tail increment, sums to 100% in each group | D36: Extension | E36: =IF(SUMPRODUCT(--(ABS(Extension!C12+SUM(Extension!D13:I13)-1)>0.000001))+SUMPRODUCT(--(ABS(Extension!C61+SUM(Extension!D62:I62)-1)>0.000001))+SUMPRODUCT(--(ABS(Extension!C110+SUM(Extension!D111:I111)-1)>0.000001))=0,"OK","REVIEW") -> OK | F36: Extension, step E1
B37: C13c | C37: Average payment lags are positive and no longer than the modelled horizon, and every inflation uplift factor is at least 1.0000 | D37: Extension | E37: =IF(SUMPRODUCT(--(Extension!M18:M23<=0))+SUMPRODUCT(--(Extension!M18:M23>5+Ext_taillag))+SUMPRODUCT(--(Extension!N18:N23<1))+SUMPRODUCT(--(Extension!M67:M72<=0))+SUMPRODUCT(--(Extension!M67:M72>5+Ext_taillag))+SUMPRODUCT(--(Extension!N67:N72<1))+SUMPRODUCT(--(Extension!M116:M121<=0))+SUMPRODUCT(--(Extension!M116:M121>5+Ext_taillag))+SUMPRODUCT(--(Extension!N116:N121<1))=0,"OK","REVIEW") -> OK | F37: Extension, step E2
B38: C14 | C38: Claims paid to date agree across all four scenario sheets | D38: Cross-sheet consistency | E38: =IF(AND(ABS('S1 Chain Ladder'!D46-'S2 Expected Claims'!G47)<0.01,ABS('S1 Chain Ladder'!D46-'S3 BF'!C47)<0.01,ABS('S1 Chain Ladder'!D46-Extension!C155)<0.01),"OK","REVIEW") -> OK | F38: Portfolio total rows
B39: C15 | C39: Portfolio reserve equals portfolio ultimate less claims paid, on every basis and in both scenarios | D39: Cross-sheet consistency | E39: =IF(AND(ABS('S1 Chain Ladder'!G46-('S1 Chain Ladder'!F46-'S1 Chain Ladder'!D46))<0.01,ABS('S3 BF'!H47-('S3 BF'!G47-'S3 BF'!C47))<0.01,ABS(Extension!M155-(Extension!J155-Extension!C155))<0.01),"OK","REVIEW") -> OK | F39: Portfolio total rows
B40: C16 | C40: The reserve on every basis is positive and stays below three times the latest year premium | D40: Reasonableness | E40: =Summary!E44 -> OK | F40: Summary E44
B41: C17 | C41: No reinsurance recovery exceeds the limit of cover, and no recovery is negative, for any of the three bases | D41: Reinsurance | E41: =ADC!C17 -> OK | F41: ADC C17
B42: C18 | C42: For every basis, the break-even inflation rates lie inside the tabulated range and are correctly ordered | D42: Reinsurance | E42: =ADC!C97 -> OK | F42: ADC C97
B44: Note on C10
B45: C10 may read SEE NOTE rather than OK. That is not a modelling error: the Expected Claims method takes no account of claims already paid, so for a mature accident year whose experience has run above expectation the method can imply a negative unpaid amount. The result is reported as it stands and discussed in the Audit Trail and the Summary document.

Sheet Audit Trail
B1: Audit Trail
C3: This audit trail is written for two readers. A senior actuary approving the work should be able to follow the reasoning, see where judgement has been exercised and satisfy themselves that the result is defensible. A fellow student taking the model over should be able to find any number, understand why it is calculated the way it is and change it safely. Section references are to worksheet names; cell references are given wherever a formula would otherwise be hard to locate.
B6: 1. Purpose and objectives
B7: 1.1 | C7: Northgate Mutual Insurance Society writes a Commercial Motor account split into three rating groups. The model estimates the unpaid claim liability for that account at the reserving date of 31 December 2025 and supports three decisions.
B8: 1.2 | C8: First, which reserving basis the reserving committee should book. Three bases are calculated in full: Chain Ladder, Expected Claims and Bornhuetter-Ferguson. They are alternative answers to the same question and the spread between them measures the uncertainty in the booked figure.
B9: 1.3 | C9: Second, how the booked figure behaves under an adverse scenario. The Chief Actuary has instructed that development beyond the observed 72 months be recognised through a tail factor, and that an additional rate of claims inflation be applied to everything still unpaid. The instruction is applied to all three bases so the comparison stays like for like.
B10: 1.4 | C10: Third, whether to buy the Adverse Development Cover offered by the reinsurer, and what rate of claims inflation would exhaust it.
B11: 1.5 | C11: All monetary amounts are in GBP thousands. The reserve throughout means the total unpaid claim liability, that is ultimate claims less claims paid to date. Because only paid data is available, this figure covers both case reserves and claims incurred but not reported; it is not IBNR alone.
B14: 2. How the workbook is arranged
B15: 2.1 | C15: The workbook runs left to right in calculation order, so any figure can be traced back by moving leftwards. Raw Data holds the source figures exactly as received and is never edited by a calculation. Data Validation detects and corrects defects. Parameters holds every input that is not claims data. Dev Factors, S1 Chain Ladder, On-Level & Cred, S2 Expected Claims and S3 BF build the three base scenarios in sequence. Extension applies the Chief Actuary instruction. ADC values the reinsurance. Summary presents the comparison and the charts. Checks gathers every check into one dashboard.
B16: 2.2 | C16: Cell colours follow the convention set out on the Cover sheet: blue text is a hardcoded input, black text is a formula calculated on that sheet, green text is a link to another sheet, yellow fill marks a judgemental assumption and green fill marks a check.
B17: 2.3 | C17: The model contains no macros, no external links and no volatile functions. In particular OFFSET and INDIRECT have been avoided in favour of INDEX, so that the calculation chain is fully traceable and the file recalculates identically on any machine.
B18: 2.4 | C18: Anyone continuing this work should change parameters only on the Parameters sheet and source figures only on the Raw Data sheet. Everything else is formula-driven and should recalculate. After any change, look at cell C4 of the Checks sheet before relying on the output.
B21: 3. Data and its sources
B22: 3.1 | C22: Table 1, cumulative paid claims. Six accident years from 2020 to 2025, each observed at up to six development ages from 12 to 72 months, for each of three rating groups. Source: claims administration system extract of 14 January 2026. The data is simulated for the purposes of this assignment but is treated throughout as though it were a genuine extract.
B23: 3.2 | C23: Table 2, reported claim counts. Used only to set credibility weights. Source: the same extract.
B24: 3.3 | C24: Table 3, history of rate changes. The average rate change achieved on renewal, taken as effective on 1 January of the accident year shown. Source: the underwriting rate monitoring return.
B25: 3.4 | C25: Table 4, earned premium by accident year and rating group. Source: the finance system.
B26: 3.5 | C26: Tables 5 to 10 on the Parameters sheet hold the remaining inputs: exposure and expense ratios, economic assumptions, the business plan loss ratios and credibility standard, the extension parameters, the reinsurance terms and the validation thresholds. Each row carries its own source note in the right-hand column.
B27: 3.6 | C27: The claims data is the only input that has been treated as unreliable. It was deliberately reviewed on the assumption that a systems extract can contain gaps and keying errors, and this proved to be the case.
B30: 4. Assumptions
B31: 4.1 | C31: The account carries no salvage or subrogation recoveries. This was confirmed with the claims manager and is what justifies validation rule R2, that cumulative paid claims cannot fall.
B32: 4.2 | C32: Rate changes take effect on 1 January of the accident year shown. This allows the on-level factor to be a simple ratio of cumulative rate indices. A more exact treatment would allow for policies being written evenly through the year and earning over the following twelve months; that refinement is listed under next steps.
B33: 4.3 | C33: Past claims severity has trended at 5.5% a year and this rate is appropriate for restating historical accident years to the 2025 cost level.
B34: 4.4 | C34: The business plan loss ratios are an unbiased view of the account at 2025 rate and cost level, and are a suitable complement of credibility.
B35: 4.5 | C35: The three oldest accident years are sufficiently developed to give a usable experience indication. This is a judgement: at 72 months the oldest year is not fully run off, which is precisely why the tail factor matters in the extension.
B36: 4.6 | C36: The volume-weighted all-year average is an appropriate selection basis for development factors. No accident year has been excluded and no year weighting has been applied.
B37: 4.7 | C37: The development pattern is the same for every accident year within a rating group.
B38: 4.8 | C38: Claims payments fall at the end of each development period. This convention is used when working out the average lag of the remaining payments in the extension.
B39: 4.9 | C39: Tail payments beyond 72 months have an average lag of three years measured from the 72 month point.
B40: 4.10 | C40: The credibility standard of 1,082 claims corresponds to a 90% probability of being within 5% of expected claim frequency.
B41: 4.11 | C41: Claim counts are unaffected by the extension scenario, so the credibility factor is unchanged between the base and extension runs. Only the severity of the claims changes.
B42: 4.12 | C42: The reinsurance premium is payable in full whatever the outcome, and the reinsurer is treated as fully solvent, so no allowance is made for counterparty default.
B43: 4.13 | C43: The a priori loss ratio is derived once for the base scenarios and once for the extension. Within each scenario it is held fixed across all accident years.
B46: 5. Notation used in the equations below
B47: 5.1 | C47: Every equation in section 6 uses the symbols defined here, and no others. Two typefaces are used deliberately: a plain italic symbol (for example i, CDFⱼ, Z) is a mathematical variable calculated somewhere in the workbook, and a bold upright name in blue (for example Loss_trend, Ext_shock) is copied character for character from a defined name on the Parameters sheet, so that it can be pasted straight into the Excel Name Box to find it. The right-hand note against each symbol gives the worksheet and column, or the defined name, where it is actually calculated or held.
B48: 5.2 | C48: General
C49: i — accident year index, i = 1, …, 6 for 2020, …, 2025. Source: Model convention.
C50: j — development age step, j = 1, …, 6 for ages 12, …, 72 months. Source: Model convention.
C51: d(i) — development age index of accident year i at the reserving date, d(i) = 7 − i. Source: Model convention.
C52: g — rating group, g ∈ {A, B, C}. Source: Model convention.
B53: 5.3 | C53: Data validation
C54: LRclean,j — clean (volume-weighted) link ratio for development step j, from unflagged cells only. Source: Data Validation, 'Clean link ratio' row.
B55: 5.4 | C55: Development factors
C56: Paidi — validated cumulative paid claims for accident year i at its current age d(i). Source: S1 Chain Ladder, 'Paid to date' column.
C57: LDFj — selected age-to-age (link) development factor, age j to age j+1. Source: Dev Factors, 'Selected LDF' row.
C58: CDFj — cumulative development factor from age j to ultimate (base scenarios: CDF₆ = 1). Source: Dev Factors, 'CDF' row.
B59: 5.5 | C59: Chain Ladder
C60: CLi — Chain Ladder ultimate claims for accident year i. Source: S1 Chain Ladder, 'Ultimate claims' column.
C61: Reservei — unpaid claim liability = ultimate claims − claims paid to date. Source: each scenario sheet, 'Reserve' column.
B62: 5.6 | C62: On-level, trend, credibility
C63: RateIdxi — cumulative rate index for accident year i. Source: On-Level & Cred, 'Cumulative rate index'.
C64: OLFi — on-level factor = RateIdx₆ / RateIdxᵢ. Source: On-Level & Cred, 'On-level factor'.
C65: EPi — earned premium for accident year i. Source: Raw Data, Table 4.
C66: OLPi — on-level earned premium = EPᵢ × OLFᵢ. Source: On-Level & Cred, 'On-level premium'.
C67: Loss_trend — claims severity trend per annum. Source: Parameters, Table 6; named range Loss_trend.
C68: TFi — trend factor = (1 + Loss_trend)^(2025 − year of i). Source: On-Level & Cred, 'Trend factor'.
C69: n — reported claim count summed over the mature accident years. Source: On-Level & Cred derivation block.
C70: Cred_full — full credibility standard, in claims. Source: Parameters, Table 7; named range Cred_full.
C71: Cred_mature — number of accident years used in the experience indication. Source: Parameters, Table 7; named range Cred_mature.
C72: Z — credibility factor. Source: On-Level & Cred derivation block.
C73: EI — experience indication: on-level, trended ultimate loss ratio. Source: On-Level & Cred derivation block.
C74: Plan_LR — business plan ultimate loss ratio. Source: Parameters, Table 7; named range Plan_LR.
C75: ELR — a priori (credibility-weighted) loss ratio. Source: On-Level & Cred derivation block.
B76: 5.7 | C76: Expected Claims
C77: ECi — Expected Claims ultimate for accident year i. Source: S2 Expected Claims, 'Ultimate claims'.
B78: 5.8 | C78: Bornhuetter-Ferguson
C79: BFi — Bornhuetter-Ferguson ultimate for accident year i. Source: S3 BF, 'Ultimate claims'.
B80: 5.9 | C80: Extension
C81: Ext_tail — tail factor beyond 72 months development, by rating group. Source: Parameters, Table 8; named range Ext_tail.
C82: Ext_taillag — average lag of tail payments beyond 72 months, in years. Source: Parameters, Table 8; named range Ext_taillag.
C83: Ext_shock — additional claims inflation rate (the Chief Actuary shock). Source: Parameters, Table 8; named range Ext_shock.
C84: CDF'j — revised cumulative development factor including the tail = CDFⱼ × Ext_tail. Source: Extension, step E1.
C85: lagi — weighted average lag, in years, of the payments still outstanding for accident year i. Source: Extension, step E2.
C86: Uplifti — inflation uplift factor = (1 + Ext_shock)^lagᵢ. Source: Extension, step E2.
C87: Xi — ultimate claims on a given base scenario (X ∈ {CL, EC, BF}). Source: S1/S2/S3, "Ultimate claims" columns.
C88: X'i — ultimate claims on the corresponding extension scenario. Source: Extension, step E4.
B89: 5.10 | C89: ADC
C90: ADC_att — attachment point, as a % of the booked reserve. Source: Parameters, Table 9; named range ADC_att.
C91: ADC_exh — exhaustion point, as a % of the booked reserve. Source: Parameters, Table 9; named range ADC_exh.
C92: ADC_rol — rate on line, as a % of the limit. Source: Parameters, Table 9; named range ADC_rol.
C93: Booked — booked reserve on the basis named in cell C5. Source: ADC, 'Booked reserve'.
C94: Attach — attachment amount, £000 = Booked × ADC_att. Source: ADC, 'Attachment point'.
C95: Exhaust — exhaustion amount, £000 = Booked × ADC_exh. Source: ADC, 'Exhaustion point'.
C96: Limit — limit of cover, £000 = Exhaust − Attach. Source: ADC, 'Limit of cover'.
C97: Premium — reinsurance premium, £000 = Limit × ADC_rol. Source: ADC, 'Premium payable'.
C98: Recoveryi — recovery under the cover, £000 = min(max(Reserve'ᵢ − Attach, 0), Limit). Source: ADC, layer table.
B101: 6. Methodology, stage by stage
B102: 6.1 | C102: Stage 1, data validation (sheet: Data Validation). Five rules are applied and are set out in full at the top of that sheet. In outline: every cell inside the triangle must hold a number; cumulative paid claims must not fall; a link ratio above the outlier bound is treated as a keying error; a cell whose predecessor is already flagged is not itself ratio-tested, so a single defect is not counted twice; and rate changes outside a plausible band are flagged.
B103: 6.2 | C103: Four root defects were found in the paid triangles: a text entry in Group A 2023 at 24 months, a fall in cumulative paid in Group A 2022 at 48 months, a missing entry in Group B 2021 at 36 months, and an order-of-magnitude keying error in Group C 2020 at 24 months. The last of these cascades: because the corrupted value is very large, the following cell fails the monotonicity test as well. Five cells are therefore flagged in total, and check C1 tests for five rather than four. This cascade is a feature of the rules working correctly, not a fault.
B104: 6.2b | C104: The Group B entry is worth a further note. The link from the source system carries a genuinely blank cell through as blank rather than as zero, specifically so that this defect is caught by rule R1 as missing data. Had the link instead let a blank read through as zero, the cell would have passed rule R1 as a valid number, been caught only one step later by rule R2 as an implausible fall to zero, and would then have caused a division by zero when the following cell was ratio-tested against it. Rule R3 also guards against this directly, by flagging rather than dividing whenever a predecessor is zero or negative, so the same protection holds even where a genuine reported zero appears elsewhere in the data.
B105: 6.3 | C105: A flagged cell is replaced by the preceding validated cell multiplied by the volume-weighted average link ratio for that development step, computed from clean cells only. The clean average is built from a helper grid (columns Q to V on each block) in which any cell that is flagged, non-numeric or outside the triangle is set to zero; a pair of cells then enters the average only when both are strictly positive. This is why the SUMPRODUCT formulas in the link ratio row test for a value greater than zero.
C106: LDFj = ΣiPaidi,j+1 / ΣiPaidi,j
C107: sum taken over the accident years for which both ages j and j+1 are observed
B108: 6.4 | C108: A cell at 12 months has no predecessor and cannot be corrected this way. Check C2 confirms that no such cell is flagged. If a future data extract does flag one, the correction rule will need to be extended, for example by reference to the earned premium for that year.
B109: 6.5 | C109: The rate change history contained one defect: a Group C figure of 100% for 2024 where the rate monitoring return records 10.0%, a misplaced decimal point. This correction is entered manually as a blue input rather than derived, so that the correction and its reason are visible. The sensitivity shown immediately below quantifies what would happen if it were left uncorrected, and confirms the correction is material rather than cosmetic.
